Workbook

Sheet Progress List
B2: SPLUNK DECOMISSIONING
B4: Function/Area/Tool | C4: Total Cases | D4: Unstarted Work | E4: % Incomplete | F4: In Design | G4: % in Design | H4: Being Developed | I4: & in Being Developed | J4: Deployed | K4: % Deployed | L4: Comments/Updates | M4: Priotity
B5: Application Parameter Tool | C5: =COUNTIFS('Combination Splunk Activities'!$H:$H,"Application Parameter Tools") -> 13 | D5: =COUNTIFS('Combination Splunk Activities'!$H:$H,"Application Parameter Tools",'Combination Splunk Activities'!$K:$K,"Unstarted Work") -> 0 | E5: =D5/C5 -> 0 | F5: =COUNTIFS('Combination Splunk Activities'!$H:$H,"Application Parameter Tools",'Combination Splunk Activities'!$K:$K,"In Design") -> 0 | G5: =F5/C5 -> 0 | H5: =COUNTIFS('Combination Splunk Activities'!$H:$H,"Application Parameter Tools",'Combination Splunk Activities'!$K:$K,"Being Developed") -> 0 | I5: =H5/C5 -> 0 | J5: =COUNTIFS('Combination Splunk Activities'!$H:$H,"Application Parameter Tools",'Combination Splunk Activities'!$K:$K,"Deployed") -> 12 | K5: =(J5/C5) -> 0.92307692 | L5: 🔹 Application Parameter Tool - PIX TRX - 9/26/25 Update Development: Completed QA: Completed Current Phase: Business Validation - 11/6/25 Application Parameter Tool is Deployed Completed | M5: Completed
B6: MAWM Scheduled Script Dashboard for API's | C6: =COUNTIFS('Combination Splunk Activities'!H:H,"MAWM Scheduled Script Dashboard for API's",'Combination Splunk Activities'!B:B,"Yes") -> 11 | D6: =COUNTIFS('Combination Splunk Activities'!$H:$H,"MAWM Scheduled Script Dashboard for API's",'Combination Splunk Activities'!$K:$K,"Unstarted Work") -> 0 | E6: =D6/C6 -> 0 | F6: =COUNTIFS('Combination Splunk Activities'!$H:$H,"MAWM Scheduled Script Dashboard for API's",'Combination Splunk Activities'!$K:$K,"In Design") -> 0 | G6: =F6/C6 -> 0 | H6: =COUNTIFS('Combination Splunk Activities'!$H:$H,"MAWM Scheduled Script Dashboard for API's",'Combination Splunk Activities'!$K:$K,"Being Developed") -> 10 | I6: =H6/C6 -> 0.90909091 | J6: =COUNTIFS('Combination Splunk Activities'!$H:$H,"MAWM Scheduled Script Dashboard for API's",'Combination Splunk Activities'!$K:$K,"Deployed") -> 0 | K6: =(J6/C6) -> 0 | L6: 🔹 Scheduled Script Dashboard – Oddball SKU - 9/26/25 Use Case: CS15 - MAWM Scheduled Script Dashboard for APIs Development & Integration: In Progress - 11/6/2025 Scheduled Script tool in still In Progress in this sprint. Sprint ends in three weeks - 12/9/25 Completed but in business testing right now. This will be deployed in January due to the Blackout period. Two are built and there are eight left to build. - 1/6/2026 Ready to deploy to production for a few of the Scripts. Adding a Script for MATM that needed for go live next month. Next Steps: Deploy to Production, use a couple of the newly created Scheulded Scripts, shut them down in Splunk - 1/20/2026 Oddball SKU, waiting on the cloud deployment to production so this can begin running in production. Working on the TMS Scheulded script, have a call today to go through it with Michael Dubose today. This is being targeted for the next sprint. Going to look into the IREC after the TMS Scheulded Script Deployment. - 2/3/2026 Oddball script is completed and ready to go in WMS Tools. We are at the point where we can turn it off in Splunk and turn it on and have it run from the WMS Tool. TMS script for RNDC Level ORG is ready to test in Development. Michael & Thomas can run the test tomorrow to make sure it is working. | M6: 2
B7: New BI Tool/ Lambda Function - Will Call Alert | C7: =COUNTIFS('Combination Splunk Activities'!$H:$H,"New BI Tool/ Lambda Function") -> 1 | D7: =COUNTIFS('Combination Splunk Activities'!$H:$H,"New BI Tool/ Lambda Function",'Combination Splunk Activities'!$K:$K,"Unstarted Work") -> 0 | E7: =D7/C7 -> 0 | F7: =COUNTIFS('Combination Splunk Activities'!$H:$H,"New BI Tool/ Lambda Function",'Combination Splunk Activities'!$K:$K,"In Design") -> 0 | G7: =F7/C7 -> 0 | H7: =COUNTIFS('Combination Splunk Activities'!$H:$H,"New BI Tool/ Lambda Function",'Combination Splunk Activities'!$K:$K,"Being Developed") -> 1 | I7: =H7/C7 -> 1 | J7: =COUNTIFS('Combination Splunk Activities'!$H:$H,"New BI Tool/ Lambda Function",'Combination Splunk Activities'!$K:$K,"Deployed") -> 0 | K7: =(J7/C7) -> 0 | L7: 🔹 Will Call – Email Alerts - 9/26/25 Update Status: To be started after CS15 - MAWM Scheduled Script Dashboard for APIs use case is completed - 12/9/25 Decmossiong of the Server(2016), so we will need to priortize this case over the Alerting Dashboard Case. This is due to us needing to get off of the WMS and close the California. Current Note: Smooth planning, Get use case ready - 1/6/26 This is in Progress, althought it's being tracked separelty, it's going to be part of the Scheulded Scripts Dashboard. - 1/20/2026 Working on the WIll Call alert, which is still in development, hoping to put it into testing this week. - 2/3/2026 They are working on the email structure, which is HTML, which is closer to hwat we have currently, we decided against a PDF report. This will be in the development environment before the end of the week. The email structure to be used by the WIll Call alert and all of the other alerts is still being finalized, this is what will be used by all alerts going forward. | M7: 1
B8: Splunk Alerts(SQL/API Alerts) - WMS Tools Alerting Dashboard | C8: =COUNTIFS('Splunk Alerts'!$A$3:A123,"<>") -> 121 | D8: =COUNTIFS('Splunk Alerts'!$A:$A,"<>",'Splunk Alerts'!$I:$I,"Unstarted Work") -> 0 | E8: =D8/C8 -> 0 | F8: =COUNTIFS('Splunk Alerts'!$A:$A,"<>",'Splunk Alerts'!$I:$I,"In Design") -> 121 | G8: =F8/C8 -> 1 | H8: =COUNTIFS('Splunk Alerts'!$A:$A,"<>",'Splunk Alerts'!$I:$I,"Being Deveolped") -> 0 | I8: =H8/C8 -> 0 | J8: =COUNTIFS('Splunk Alerts'!$A:$A,"<>",'Splunk Alerts'!$I:$I,"Deployed") -> 0 | K8: =(J8/C8) -> 0 | L8: 🔹 WMS Tools Alerting Dashboard - 9/26/25 Kim & Memory to Meet with Camir next week to understand the POC that he built the first time around a year ago. - 11/6/25 Plan is to build this functionality into WMS Tools vs. Using Power BI/Power Automate. Kinsy & Thomas will start to work on this after the Scheudled Script Tool is Deployed to Production. - 12/9/25 Started Development. Using Inventory Adjustment PIX Missing Reason Code as a POC to start eh development. Time Frame : Kinsy to do some analysis to see how long it will take to complete the last three tools to get off of Splunk completely. - 1/6/26 Final list of Alerts is being complied. A few meetings have been had, we have close to the final list. Kinsy is working on an estimate of how long it will take to develop. - 1/20/2026 We have final list. We are goignt o scheuld a meeting to come up with a priority and that way development can begin on this section. - 2/3/2026 They are working on the embeded HTML table that will be used for all alerts, but they are starting with the Will Call alerts. Once it's complete we can move from the Will Call alert they will move on to the other alerting. | M8: 3
B10: Function/Area/Tool | C10: Total Cases | D10: Unstarted | E10: % Incomplete | F10: In Design | G10: % in Design | H10: Being Developed | I10: & in Being Developed | J10: Deployed | K10: % Deployed
B11: All | C11: =SUM(C5:C8) -> 146 | D11: =SUM(D5:D8) -> 0 | E11: =D11/C11 -> 0 | F11: =SUM(F5:F8) -> 121 | G11: =F11/C11 -> 0.82876712 | H11: =SUM(H5:H8) -> 11 | I11: =H11/C11 -> 0.075342466 | J11: =SUM(J5:J8) -> 12 | K11: =J11/C11 -> 0.082191781
B15: Power BI Dashboards
B17: Dashboard/Report/Tool | C17: MAWM Replicated SQL Complete? | D17: SQL Rewritten in Snowflake? | E17: Comments | G17: Data Model Created? | H17: Comments | J17: Power BI Dashboard Created? | K17: Comments
B18: Workload Summary | C18: Complete | D18: Complete | E18: Need to Open a Ticket with W&H, to double check the validy of their data. | G18: Complete | H18: I believe Mark has the initial Model created. There is a data issue on how this data is pulled into snowflake, and it has to do with a date field that is being populated. | J18: In Progress | K18: Chad to provide some assistance with writing a Power BI report for this.
B19: Inventory Tracking Dashboard | C19: Complete | D19: Complete | E19: Data Team had Snowflake SQL. | G19: In Progress | H19: No started yet | J19: Incomplete
B20: Inbound Receiving Volume Dashboard | C20: Complete | D20: Complete | E20: Updates being made to MAWM Replicated SQL | G20: Incomplete | H20: Not started yet | J20: Incomplete
B21: Inbound Transfer Volume Dashboard | C21: Complete | D21: Complete | E21: Updates being made to MAWM Replicated SQL | G21: Incomplete | H21: Not started yet | J21: Incomplete
B22: Demand Order Outbound Volume Dashboard | C22: Complete | D22: Complete | E22: Updates being made to MAWM Replicated SQL | G22: Incomplete | H22: Not started yet | J22: Incomplete
B23: Slotting Dashboard | C23: Complete | D23: Complete | E23: Data Team had Snowflake SQL. | G23: Complete | H23: From what I understand this is in progress. - This is completed, ready to write the Power BI report. | J23: Incomplete | K23: Chad to provide some assistance with writing a Power BI report for this.
B24: Cycle Count Dashboard | C24: Complete | D24: Complete | E24: Updates being made to MAWM Replicated SQL | G24: Incomplete | H24: Not started yet | J24: Incomplete
B25: Returns Dashboard | C25: In Progress | D25: Incomplete | E25: This has not been started yet. Will be upon completion of the Inbound Dashboards. | G25: Incomplete | H25: Not started yet | J25: Incomplete
B26: Activity Tracking Warehouse Report | C26: In Progress | D26: Incomplete | E26: Requested the Current SQL that Agilitics wrote, need to review. | G26: Incomplete | H26: Not started yet | J26: Incomplete
B27: Foecast Data SQL's | C27: Completed | D27: Completed | E27: Bricz currently working on Snowflake SQL. | G27: Incomplete | H27: Not started yet | J27: Incomplete

Sheet Sheet1
D11: Power BI Dashboards
D13: Dashboard/Report/Tool | E13: MAWM Replicated SQL Complete? | F13: SQL Rewritten in Snowflake? | G13: Data Model Created? | H13: Power BI Dashboard Created?
D14: Workload Summary | E14: Complete | F14: Complete | G14: Complete | H14: In Progress
D15: Inventory Tracking Dashboard | E15: Complete | F15: Complete | G15: In Progress | H15: Incomplete
D16: Inbound Receiving Volume Dashboard | E16: Complete | F16: Complete | G16: Incomplete | H16: Incomplete
D17: Inbound Transfer Volume Dashboard | E17: Complete | F17: Complete | G17: Incomplete | H17: Incomplete
D18: Demand Order Outbound Volume Dashboard | E18: Complete | F18: In Progress | G18: Incomplete | H18: Incomplete
D19: Slotting Dashboard | E19: Complete | F19: Complete | G19: Complete | H19: Incomplete
D20: Cycle Count Dashboard | E20: In Progress | F20: Incomplete | G20: Incomplete | H20: Incomplete
D21: Returns Dashboard | E21: In Progress | F21: Incomplete | G21: Incomplete | H21: Incomplete
D22: Activity Tracking Warehouse Report | E22: In Progress | F22: Incomplete | G22: Incomplete | H22: Incomplete
D23: Foecast Data SQL's | E23: Completed | F23: Completed | G23: Incomplete | H23: Incomplete

Sheet Final_List-Alerts
A1: Tasks | B1: Priority | C1: ERP/WMS | D1: Needed | E1: Type | F1: Database | G1: Assigned To | H1: Email | I1: Comments | J1: Stakeholder | K1: Email Template | L1: DEV | M1: QA | N1: Production
A2: ALLOCATED LPNS WITH NO OPEN TASK DETAILS API FAILURE | B2: Low | C2: WMS | D2: Yes | E2: API | F2: MAWM | G2: Kinsy | I2: splunk/manhattan_active/ASH/alloclpns_noopntskdtls
A3: ALPHA ASN ERROR | B3: Medium | C3: ERP | D3: Yes | E3: FTP File Search | F3: ALPHA | G3: Thomas | I3: ALPHA ASN ERROR & ASW ASN ERROR are same index = main host="misssplunksh01.corp.rndc-usa.com" sourcetype=alphaasn | eval file_date=strftime(now(), "%Y-%m-%d") | eval mySource="/splunk/FTP/Alpha/asn/abq_asnhdr_" + file_date + ".txt" | where match(source, mySource) | eval ASN=substr(_raw,1,20), STATUS=substr(substr(_raw,20,21),1,2) | eval House="ABQ" | eval Error_Description=case(STATUS == " 1", "Header Error", STATUS ==" 2", "Line Item Error") | where STATUS in (" 1"," 2") | rename STATUS as "Error Status", Error_Description as "Error Description" | table House, ASN, "Error Status", "Error Description", _time This Splunk search pulls today’s ABQ ASN header file, extracts the ASN number and error status from fixed positions in the file, and labels the warehouse as ABQ. It then filters only error records (Status 1 = Header Error, Status 2 = Line Item Error) and displays the results with timestamps for reporting. The final result will send via email formatted as table using HTML embedded in the email | J3: Jacod Reed or Dax Solomon
A4: ALPHA OPEN ADJUSTMENTS > 35DAYS | B4: 11 | C4: ERP | D4: Yes | E4: FTP File Search | F4: ALPHA | G4: Thomas | I4: sourcetype=alpha_adj | regex "\s\s\s\s\s\s\s\s\s\s\s\s\s\s\s\s\s\s\s\s\s\s\s\s\s\s\s\s\s\s\s\s\s\s\s\s\s\s\s\s\s\s\s\s\s\s\s\s\s\s\s\s\s\s\s[1]" | eval file_date=strftime(now(), "%Y-%m-%d")| eval mySource="/splunk/FTP/Alpha/adj/atl_adjtrx_" + file_date + ".txt" | where match(source, mySource) | table source,Item, REASON, _time | rex field=source mode=sed "s/\/splunk\/FTP\/Alpha\/adj\/atl_*(.+)/ATL/g" | rename source AS "House" | sort House |dedup Item This search filters **today’s ATL Alpha adjustment file** to find records with a specific fixed-position pattern (ending in status **1**), indicating a certain type of adjustment/error. It then formats the output to show **House (ATL), Item, Reason, and Time**, removes duplicates by Item, and sorts the results for clean reporting. The final result will send via email formatted as table using HTML embedded in the email
A5: ALPHA OPEN/ERROR ASN | B5: 12 | C5: ERP | D5: Yes | E5: FTP File Search | F5: ALPHA | G5: Thomas | I5: sourcetype=alphaasn White!=9 latest=-2d@d earliest=0 | eval file_date=strftime(now(), "%Y-%m-%d") | eval mySource="/splunk/FTP/Alpha/asn/abq_asnhdr_" + file_date + ".txt" | where match(source, mySource)| search | eval Date=_time | convert timeformat="%Y-%m-%d" ctime(Date) | table source,ASN,White,Date | rex field=source mode=sed "s/\/splunk\/FTP\/Alpha\/asn\/abq_*(.+)/ABQ/g" | rex field=White mode=sed "s/[0]/Open_ASN/g" | rex field=White mode=sed "s/[1]/Header_Values_Errors/g" | rex field=White mode=sed "s/[2]/Line_Item_Errors/g" | rename source AS "House", White AS "Status" | sort House ----- This search pulls today’s ABQ ASN header file and filters records where the ASN status is not “9,” then formats the date for reporting. It converts numeric status codes into readable error descriptions (Open, Header Errors, Line Item Errors) and displays the results by House, ASN, Status, and Date.
A6: ALPHA OPEN RETURNS | B6: Medium | C6: ERP | D6: Yes | E6: FTP File Search | F6: ALPHA | G6: Thomas | I6: index = alpharet punct=__________________________________________________ | eval file_date=strftime(now(), "%Y-%m-%d") | eval mySource="/splunk/FTP/Alpha/ret/atl_retlpn_" + file_date + ".txt" | where match(source, mySource)| search This Splunk search looks in the alpharet index for events whose source file name matches today’s ATL retail LPN file (based on the current date). It then filters the results to only those matching that specific file path and applies any additional search conditions. The final result will send via email formatted as table using HTML embedded in the email
A7: ASN S WITH NO ASN LEVEL VERIFICATION > 5DAYS | B7: Low | C7: Middleware | D7: Yes | E7: DBQuery | F7: Mulesoft | G7: Thomas | I7: ABQ_MIDDLE_PROD | J7: Mikaelo or Shrini
A8: ASW ASN ERROR | B8: Medium | C8: ERP | D8: Yes | E8: FTP File Search | F8: ASW | G8: Thomas | I8: sourcetype = asn_error_csv | eval file_date=strftime(now(), "%Y_%m_%d") | eval mySource="/splunk/FTP/ASW/ASN_Errors_" + file_date + ".csv" | where match(source, mySource) | table AHZMSROM AHZMASNN _time | rename AHZMSROM AS "HOUSE" AHZMASNN AS "ASN" -----This Splunk search finds today’s ASN error CSV file and filters events to only that specific file path. It then displays the HOUSE, ASN, and time fields in a clean table format. The final result will send via email formatted as table using HTML embedded in the email | J8: Harvey Goldstein, Robert curl
A9: DIVERT CONFIRMATION DOWN | B9: High | C9: WMS | D9: Yes | E9: API | G9: Thomas | I9: /splunk/manhattan_active/ALLMAWM/au02_divert_confirm_source_destination_down
A10: DUPLICATE PIX S IN MIDDLEWARE WMS | B10: High | C10: Middleware | D10: Yes | E10: DBQuery | F10: Mulesoft | G10: Thomas | I10: Combine DUPLICATE PIX S IN MIDDLEWARE WMS " & DUPLICATE PIX S IN SOA WMS name as Mulesoft - refer the code in SOA
A11: DUPLICATE PIX S IN SOA WMS | D11: No | E11: DBQuery | F11: My SQL | G11: Kinsy | I11: 10.248.248.195 - MAPRD_NEW
A12: DUPLICATE SHIP CONFIRM | B12: High | C12: Middleware | D12: Yes | E12: DBQuery | F12: Oracle/Mulesoft | G12: Kinsy | I12: MAWM_SOA_PRD - jdbc:oracle:thin:@at4ex01-scan1.corp.rndc-usa.com:1521/pwmsods_svc1
A13: ENDPOINT QUEUE FAILURES | B13: Low | C13: WMS | D13: Yes | E13: API | G13: Thomas | I13: /splunk/manhattan_active/ABQ/failure_count/
A14: ENDPOINT STATUS | B14: Medium | C14: WMS | D14: Yes | E14: API | G14: Thomas | I14: /splunk/manhattan_active/ARK/endpoint_status/
A15: ILPNS WITH MISSING PHYSICALENTITYCODEID | B15: Low | C15: WMS | D15: Yes | E15: DBQuery | F15: My SQL | G15: Kinsy | I15: 10.248.248.195 - MAPRD_NEW
A16: ILPNS WITH NEGATIVE ALLOCATED QUANTITY API FAILURE | B16: Low | C16: WMS | D16: Yes | E16: API | G16: Kinsy
A17: INVENTORY ADJUSTMENT PIX MISSING REASON CODE | B17: High | C17: WMS | D17: Yes | E17: DBQuery | F17: My SQL | G17: Kinsy
A18: INVENTORY SYNC SCHEDULE API FAILED | B18: 13 | C18: WMS | D18: Yes | E18: API | G18: Kinsy | I18: Same inventory_sync_schedule - calling script /splunk/manhattan_active/ABQ/inventory_sync_schedule/inventory_sync_schedule_check_status.csv | K18: The alert condition for '$name$' was triggered. Description: Manhattan case 7115910 is open for this. ***MSP TO CLEAN UP*** Steps to Correct:Run the SQL update(s) in the Middleware DB for each house. Commit these updates after running. | L18: 5 | M18: 2 | N18: 1
A19: ITEM IMAGE URL FAILURE | B19: 17 | C19: WMS | D19: Yes | E19: API | G19: Kinsy | I19: FTP file path to get the image list
A20: ITEM LEVEL RECEIPTS WITH 0 QUANTITY | B20: High | C20: WMS | D20: Yes | E20: DBQuery | F20: My SQL | G20: Kinsy | I20: 10.248.248.195 - MAPRD_NEW
A21: LIA RECORDS WITH PACK UOM TYPE POPULATED | B21: Low | C21: WMS | D21: Yes | E21: DBQuery | F21: My SQL | G21: Kinsy | K21: The alert condition for '$name$' was triggered. ***MSP TO CLEAN UP***
A22: LOCATION POSITION > STREET LENGTH | B22: Low | C22: WMS/LMS | D22: Yes | E22: DBQuery | F22: My SQL | G22: Kinsy | I22: 10.248.248.195 - MAPRD_NEW ; email to lmteam@rndc-usa.com
A23: LOCATION REBUILD FAILURE | B23: Low | C23: WMS | D23: Yes | E23: API | G23: Kinsy | I23: splunk/manhattan_active/ABQ/location_rebuild. Only API call and no select query from mysql
A24: LOCATIONS W/ INVENTORY FOR ITEMS NOT ASSIGNED | B24: Low | C24: WMS | D24: Yes | E24: DBQuery | F24: My SQL | G24: Kinsy | I24: 10.248.248.195 - MAPRD_NEW
A25: LONG RUNNING OR ABORTED WAVES | B25: High | C25: WMS | D25: Yes | E25: DBQuery | F25: My SQL | G25: Kinsy | I25: 10.248.248.195 - MAPRD_NEW
A26: LPNS WITH CONSUMED/CANCELLED ALLOCATED QUANTITY API FAILURE | B26: Meium | C26: WMS | D26: Yes | E26: API | G26: Kinsy | I26: execute select sql and call MA API Endpoint. /splunk/manhattan_active/ABQ/lpn_consumed_cancel_allocation
A27: MISSING ITEM LEVEL VERIFICATION PIX | B27: High | C27: Middleware | D27: Yes | E27: DBQuery | F27: Oracle/Mulesoft | G27: Kinsy | I27: MAWM_SOA_PRD - jdbc:oracle:thin:@at4ex01-scan1.corp.rndc-usa.com:1521/pwmsods_svc1
A28: MONTHLY SLOTTING DASHBOARD | C28: WMS | D28: No | E28: DBQuery | F28: My SQL | G28: Kinsy | I28: Query runs in python script and create csv file. /splunk/manhattan_active/ALLMAWM/monthly_slotting_dashboard
A29: OPEN PICK PACK TASK DETAILS API FAILURE | B29: Low | C29: WMS | D29: Yes | E29: API | G29: Kinsy | I29: Run select query and update API endpoint. /splunk/manhattan_active/ABQ/tskdtls_comp_openpickpacktskdtls
A30: ASW OPEN RETURNS | B30: Medium | C30: ERP | D30: Yes | E30: FTP File Search | F30: ASW | G30: Kinsy | I30: Returns House and Open Return values from today’s Cust_Rtn_Pallets CSV file only, with the event date displayed.. Searching FTP file path /splunk/FTP/ASW/Cust_Rtn_Pallets_* The final result will send via email formatted as table using PDF attached in the email
A31: OPEN TASK API FAILURE | B31: Low | C31: WMS | D31: Yes | E31: API | G31: Kinsy | I31: Run select query and update API endpoint. - /splunk/manhattan_active/LUB/open_task
A32: OPEN TASK DETAILS API FAILURE | B32: Low | C32: WMS | D32: Yes | E32: API | G32: Kinsy | I32: Run select query and update API endpoint. - /splunk/manhattan_active/ATL/open_task_details
A33: ORDERS NOT PROCESS IN HOST > 15 MINUTES | B33: 4 | C33: Middleware | D33: Yes | E33: DBQuery | F33: Oracle/Mulesoft | G33: Kinsy | I33: | dbxquery query="SELECT warehouse, invoice_no, item_no, ship_qty, prc_status, created_dttm, messageid FROM ark_wmsods.ship_confirm WHERE prc_status = 10 AND created_dttm < sysdate - 60/1440 ORDER BY created_dttm desc" connection="MAWM_SOA_PRD"
A34: ORDERS STUCK IN CREATED STATUS > 15 MINUTES | B34: 5 | C34: WMS | D34: Yes | E34: DBQuery | F34: My SQL | G34: Kinsy | I34: 10.248.248.195 - MAPRD_NEW
A35: ELP ASW -PENDING SHIPMENT QUANTITIES > 1 WEEK | B35: Low | C35: Host | D35: Yes | E35: FTP File Search | F35: ASW | G35: Kinsy | I35: To retrieve and display today’s Pending Open Shipments records for SISROM = EL1 by filtering events to today’s CSV file and presenting key shipment fields in a readable format. (/splunk/FTP/ASW/Pending_Shipments_Open_" + file_date + ".csv") The final result will send via email formatted as table using PDF attached in the email
A36: PICK LOCATIONS WITH NEGATIVE TBF API FAILURE | B36: High | C36: WMS | D36: Yes | E36: API | G36: Kinsy | I36: Run select query and update API endpoint../splunk/manhattan_active/ABQ/pick_loc_negative_tbf
A37: PICK LOCATIONS WITH TBF QUANTITY AND NO OPEN TASK DETAILS API FAILURE | B37: High | C37: WMS | D37: Yes | E37: API | G37: Kinsy | I37: /splunk/manhattan_active/ABQ/pick_loc_tbf_qty_taskdtls
A38: PUTAWAY TASK DETAILS API FAILURE | B38: Medium | C38: WMS | D38: Yes | E38: API | G38: Kinsy | I38: /splunk/manhattan_active/ABQ/ptwytskdtlsopen_nottiedtskhdr
A39: RECOUP SORTING UPDATE API FAILURE | B39: Medium | C39: WMS | D39: Yes | E39: API | G39: Kinsy | I39: /splunk/manhattan_active/DFB/recoup_sort_update_lpn
A40: ROUTED ORDERS CANCELLED | B40: High | C40: WMS | D40: Yes | E40: DBQuery | F40: My SQL | G40: Kinsy | I40: 10.248.248.195 - MAPRD_NEW
A41: ROUTES WITH MULTIPLE WAVE NUMBERS | B41: 14 | C41: WMS | D41: Yes | E41: DBQuery | F41: My SQL | G41: Kinsy | I41: 10.248.248.195 - MAPRD_NEW
A42: SHIPPED OLPN W/ CONSOLIDATION LOCATION ASSIGNMENT | B42: Medium | C42: WMS | D42: Yes | E42: DBQuery | F42: My SQL | G42: Kinsy | I42: 10.248.248.195 - MAPRD_NEW
A43: SLOTTING ITEM DEMAND PACK FAILURE | B43: High | C43: WMS | D43: Yes | E43: API | G43: Kinsy | I43: Run select query and update API
A44: SLOTTING ITEM DEMAND UNIT FAILURE | B44: High | C44: WMS | D44: Yes | E44: API | G44: Kinsy | I44: Run select query and update API
A45: SLOTTING LIA DELETE PK RECORDS API FAILURE | B45: Medium | C45: WMS | D45: Yes | E45: API | G45: Kinsy | I45: No query only API search and delete
A46: SPLUNK API SCRIPTS SUMMARY | B46: Low | C46: Splunk | D46: Yes | E46: DBQuery | F46: Pstgres | G46: Kinsy | I46: /splunk/manhattan_active/ALLMAWM/api_schedules/api_schedules.txt
A47: STANDARD ORDERS DESELECTED DURING WAVING | B47: 6 | C47: WMS | D47: Yes | E47: DBQuery | F47: My SQL | G47: Kinsy | I47: 10.248.248.195 - MAPRD_NEW
A48: STANDARD ORDERS W/ NO DESIGNATED OR ASSIGNED SHIPMENTS CREATED | B48: 7 | C48: WMS | D48: Yes | E48: DBQuery | F48: My SQL | G48: Kinsy | I48: 10.248.248.195 - MAPRD_NEW
A49: STANDARD ORDERS W/ NO DESIGNATED SHIPMENTS CREATED | B49: 8 | C49: WMS | D49: Yes | E49: DBQuery | F49: My SQL | G49: Kinsy | I49: 10.248.248.195 - MAPRD_NEW
A50: STATIC ROUTE MISSING THRESHOLD VALUE | B50: 9 | C50: WMS | D50: Yes | E50: DBQuery | F50: My SQL | G50: Kinsy | I50: 10.248.248.195 - MAPRD_NEW
A51: STATIC ROUTE UI MISSING DFLT VALUE | B51: 10 | C51: WMS | D51: Yes | E51: DBQuery | F51: My SQL | G51: Kinsy | I51: 10.248.248.195 - MAPRD_NEW
A52: TEMPORARY RESERVE LOCATIONS W/ ASSIGNMENTS, BUT NO INVENTORY | B52: Medium | C52: WMS | D52: Yes | E52: DBQuery | F52: My SQL | G52: Kinsy | I52: 10.248.248.195 - MAPRD_NEW
A53: TEMPORARY RESERVE LOCATIONS W/ INVENTORY, BUT NO ASSIGNMENTS | B53: Medium | C53: WMS | D53: Yes | E53: DBQuery | F53: My SQL | G53: Kinsy | I53: 10.248.248.195 - MAPRD_NEW
A54: TRAVEL > 4 MINS | B54: Low Low | C54: WMS/LMS | D54: Yes | E54: DBQuery | F54: Oracle | G54: Kinsy | I54: MAWM_SOA_PRD
A55: USERS W/ INCORRECT USER DEFAULT CONFIGURATION | B55: Low | C55: WMS | D55: Yes | E55: DBQuery | F55: My SQL | G55: Kinsy | I55: 10.248.248.195 - MAPRD_NEW | J55: Put in Application Configuration Tool
A56: USER TASK GROUP BULK IMPORT FAILURE | B56: Low | C56: WMS | D56: Yes | E56: API | G56: Kinsy | I56: Run select query and update API
A57: WEEKLY SLOTTING DASHBOARD | C57: WMS | D57: No | E57: DBQuery | F57: My SQL | G57: Kinsy | I57: /splunk/manhattan_active/ALLMAWM/monthly_slotting_dashboard - run as python in splunk
A58: WILL CALL | B58: 1 | C58: WMS | D58: Yes | E58: API | G58: Kinsy | I58: 1/23 - dev completion
A59: ALL - MAWM - LPN Storage Locs with Inventory Not Tied to an LPN | B59: Low | C59: WMS | D59: Yes | E59: DBQuery | F59: My SQL | G59: Kinsy | I59: 10.248.248.195 - MAPRD_NEW
A60: ALL - MAWM - Pallet LPNs w/ Inventory Records | B60: Low | C60: WMS | D60: Yes | E60: DBQuery | F60: My SQL | G60: Kinsy | I60: 10.248.248.195 - MAPRD_NEW
A61: Item Loc Prod (ITEMLOC_PRD) | B61: 16 | C61: WMS | D61: Yes | E61: DBQuery | F61: MySQL, Oracle | G61: Kinsy | I61: /splunk/manhattan_active/ABQ/ITEMLOC_PRD - runs as python file. Select data from my sql and insert in oracle table
A62: Mark Dynamic Case Pick (dynamic_casepick_liquor) | B62: 14 | C62: WMS | D62: Yes | E62: API | G62: Kinsy | I62: Run select query and update API. /splunk/manhattan_active/LIV/dynamic_casepick_liquor | J62: Wesley for Details
A63: Mark Dynamic Wine (dynamic_casepick_wine) | B63: 15 | C63: WMS | D63: Yes | E63: API | G63: Kinsy | I63: Run select query and update API.. /splunk/manhattan_active/LIV/dynamic_casepick_wine | J63: Wesley for Details
A64: ALL - MAWM - Splunk Alerts Summary | B64: Low | C64: WMS | D64: Yes | E64: Report | F64: Pstgres | G64: Kinsy | I64: |rest /servicesNS/-/-/saved/searches splunk_server=local |search (title = "*MAWM*" ) |table title, action.email.message.alert, action.email.to, action.email.cc, actions, cron_schedule, disabled, eai:acl.app, qualifiedSearch - -- It list the complete alerts list
A65: ALL - MAWM - oLPNs w/ Multiple Details of the Same Item | B65: Low | C65: WMS | D65: Yes | E65: DBQuery | F65: My SQL | G65: Kinsy | I65: 10.248.248.195 - MAPRD_NEW
A66: OPEN ORDER IN WM > 1 WEEK | B66: Low | C66: WMS | D66: Yes | E66: DBQuery | F66: My SQL | G66: Kinsy | I66: 10.248.248.195 - MAPRD_NEW
A67: AU01 FAILURE [URGENT] | B67: 2 | C67: WMS | D67: Yes | E67: API | G67: Kinsy | I67: Only API serach and return the data
A68: WMS- NEW Alpha Open Adjustments > 45days | B68: Meduim | C68: ERP | D68: Yes | E68: FTP File Search | F68: ALPHA | G68: Kinsy | I68: sourcetype=alpha_adj | eval file_date=strftime(now(), "%Y-%m-%d") | eval mySource="/splunk/FTP/Alpha/adj/new_adjtrx_" + file_date + ".txt" | where match(source, mySource) | eval Item=substr(_raw,1,8), Reason_Code=substr(_raw,19,2), Status=substr(_raw,46,1), CreateDate=substr(_raw,23,8), Created_Date_Time=strftime(_time, "%Y%m%d"), House="NEW" | eval search_date=strftime(relative_time(now(), "-45d@d"), "%Y%m%d") | eval CreateDateformatt=strptime(CreateDate, "%Y%m%d"), CreateDateformatted=strftime(CreateDateformatt, "%Y%m%d") | where Status<2 AND CreateDateformatted <= search_date | table House, Item, Reason_Code, Status, CreateDate | sort +Item CreateDate | dedup Item Reason_Code CreateDate | dedup consecutive=true Item, Reason_Code -------- This search pulls today’s Alpha adjustment file, extracts item and status details, filters records older than 45 days with low status values, and removes duplicate entries for clean reporting. The final result will send via email formatted as table using HTML embedded in the email
A69: ALPHA OPEN ADJUSTMENTS > 40 DAYS | B69: 11 | C69: ERP | D69: Yes | E69: FTP File Search | F69: ALPHA | G69: Kinsy | I69: This search pulls today’s LAF Alpha adjustment file, extracts item, reason, status, and create date from fixed positions, and filters records with Status < 2 that are older than 40 days. It then sorts and removes duplicates so only unique Item + Reason_Code adjustment records remain for reporting. The final result will send via email formatted as table using HTML embedded in the email
A70: ABQ - MAWM - Travel > 4 Mins | B70: Lo Lo | C70: WMS/LMS | D70: Yes | E70: DBQuery | F70: Oracle | G70: Kinsy | I70: MAWM_SOA_PRD - jdbc:oracle:thin:@at4ex01-scan1.corp.rndc-usa.com:1521/pwmsods_svc1
A71: POR - MAWM - Duplicate PIX's in Middleware WMS | B71: Medium | C71: Middleware | D71: Yes | E71: DBQuery | F71: Oracle SQL | G71: Kinsy | I71: 10.248.248.195 - MAPRD_NEW
A72: ALL - MAWM - PIX Specification Found > 1 Hour | B72: High | C72: WMS | D72: Yes | E72: DBQuery | F72: My SQL | G72: Kinsy | I72: 10.248.248.195 - MAPRD_NEW
A73: ALL - MAWM - Inventory Adjustment PIX w/ Null PO Line | B73: Medium | C73: WMS | D73: Yes | E73: DBQuery | F73: Oracle SQL | G73: Kinsy | I73: This search reads usernames from MA_SOA.csv and runs a database query for each user against the MAWM_SOA_PRD connection. It returns recent Inventory Adjustment transactions (last 24 hours) where ASN and PO exist but PO line is missing, sorted by latest transaction time.
A74: ALL - MAWM - In Packing oLPNS > 5 Minutes | B74: Medium | C74: WMS | D74: Yes | E74: DBQuery | F74: My SQL | G74: Kinsy | I74: 10.248.248.195 - MAPRD_NEW
A75: ALL - MAWM - Loaded Shipments w/ no Ship Confirm > 6 hours | B75: Medium | C75: WMS | D75: Yes | E75: DBQuery | F75: My SQL | G75: Kinsy | I75: 10.248.248.195 - MAPRD_NEW
A76: ALL - MAWM - Putaway Task is Open but iLPN is Putaway | B76: Medium | C76: WMS | D76: Yes | E76: DBQuery | F76: My SQL | G76: Kinsy | I76: 10.248.248.195 - MAPRD_NEW
A77: ALL - MAWM - Task Completed or Cancelled w/ Open Task Details | B77: Medium | C77: WMS | D77: Yes | E77: DBQuery | F77: My SQL | G77: Kinsy | I77: 10.248.248.195 - MAPRD_NEW
A78: ALL - MAWM - Task Open w/ Completed or Cancelled Task Details | B78: Medium | C78: WMS | D78: Yes | E78: DBQuery | F78: My SQL | G78: Kinsy | I78: 10.248.248.195 - MAPRD_NEW
A79: ALL - MAWM - Task ‘In Progress’ w/ Completed or Cancelled Task Details | B79: Medium | C79: WMS | D79: Yes | E79: DBQuery | F79: My SQL | G79: Kinsy | I79: 10.248.248.195 - MAPRD_NEW
A80: ALL - MAWM - Unprocessed or Failed Ship Confirms Last 24 Hours | B80: High | C80: WMS | D80: Yes | E80: DBQuery | F80: My SQL | G80: Kinsy | I80: 10.248.248.195 - MAPRD_NEW
A81: All - MAWM - Multiple Order Lines Per Original Order Line | B81: Low | C81: WMS | D81: Yes | E81: DBQuery | F81: My SQL | G81: Kinsy | I81: 10.248.248.195 - MAPRD_NEW
... A83: ALL - MAWM - Items Volume with Large Dimensions | B83: Low | C83: WMS | D83: Yes | E83: DBQuery | F83: My SQL | G83: Kinsy | I83: 10.248.248.195 - MAPRD_NEW
A84: ATL In Transit RMA ASNs > 30 Days Splunk Alert | B84: 3 | C84: WMS | D84: Yes | E84: API | I84: New Alert - Looking for delivery in End of Feb
A85: mawm_consolidation_report | C85: WMS - Report - Send email report | E85: API
A86: LIA Sync Application Parameter | C86: Application Parameter | E86: Application Parameter
A87: inventory_sync_schedule | E87: API
A88: update_ext_display_barcode | C88: WMS | D88: Yes | E88: API | F88: My SQL | H88: No
A89: MATM - SPO Import Failure | B89: High | C89: MATM | D89: Yes | E89: DBQuery | F89: My SQL | H89: Yes | I89: New Alert requested by Brandon and TMS Team.

Sheet api.alert
A2: No | B2: ='Final_List-Alerts'!A1 -> Tasks | C2: sorting | D2: Priority | E2: splunk search content | F2: python + sql + shell script | G2: FTP | H2: TXT | I2: csv | J2: PY | K2: eval | L2: SQL | M2: MAPI | N2: dev status | O2: Notes | P2: csv file name
A3: 1 | B3: ='Final_List-Alerts'!A58 -> WILL CALL | C3: =D3 -> 1 | D3: ='Final_List-Alerts'!B58 -> 1 | J3: 1 | M3: 1 | N3: pending dev
A4: =A3+1 -> 2 | B4: ='Final_List-Alerts'!A67 -> AU01 FAILURE [URGENT] | C4: =D4 -> 2 | D4: ='Final_List-Alerts'!B67 -> 2 | E4: source="/splunk/manhattan_active/ABQ/failure_count_10min/message_failure_count_list.csv" host="misssplunksh01.corp.rndc-usa.com" index="ymc_dev_wms" Endpoint_Name=WOR_DEI_AllocationDownloadMsg |rename Endpoint_Name as Name, Error_Count as Count | table Name Count | F4: /splunk/manhattan_active/ABQ/message_count.py and /dmui-facade/api/dmui-facade/metric/search | J4: 1 | M4: 1
A5: =A4+1 -> 3 | B5: ='Final_List-Alerts'!A84 -> ATL In Transit RMA ASNs > 30 Days Splunk Alert | C5: =D5 -> 3 | D5: ='Final_List-Alerts'!B84 -> 3 | E5: source="/splunk/manhattan_active/ALLMAWM/hawaii-in-transit-rma-asns/Logs/hawaii-in-transit-rma-asns-HAW.csv" host="misssplunksh01.corp.rndc-usa.com" index="ymc_dev_wms" sourcetype="csv" | Table "ASN Id", Status | F5: "/splunk/manhattan_active/ALLMAWM | I5: 1 | J5: 1 | M5: 1 | O5: ="questions at " & misc.questions!A3 & "." & misc.questions!B3& " org id haw, kap, kau, mau, oah " -> questions at hawaii-in-transit-rma-asns.do we need to do both stage and prod org id haw, kap, kau, mau, oah | P5: =MID(E5, LEN("source=""/splunk/manhattan_active/"), FIND("csv", E5) - LEN("source=""/splunk/manhattan_active/")+3) -> /ALLMAWM/hawaii-in-transit-rma-asns/Logs/hawaii-in-transit-rma-asns-HAW.csv
A6: =A5+1 -> 4 | B6: ='Final_List-Alerts'!A18 -> INVENTORY SYNC SCHEDULE API FAILED | C6: =D6 -> 13 | D6: ='Final_List-Alerts'!B18 -> 13 | E6: source="/splunk/manhattan_active/ABQ/inventory_sync_schedule/inventory_sync_schedule_check_status.csv" host="misssplunksh01.corp.rndc-usa.com" index="ymc_dev_wms" "Inventory sync schedule API Failed" |rename "Inventory sync schedule API Status" as Status | table Status, _time | I6: 1 | J6: 1 | M6: 1 | P6: =MID(E6, LEN("source=""/splunk/manhattan_active/"), FIND("csv", E6) - LEN("source=""/splunk/manhattan_active/")+3) -> /ABQ/inventory_sync_schedule/inventory_sync_schedule_check_status.csv
A7: =A6+1 -> 5 | B7: ='Final_List-Alerts'!A62 -> Mark Dynamic Case Pick (dynamic_casepick_liquor) | C7: =D7 -> 14 | D7: ='Final_List-Alerts'!B62 -> 14
A8: =A7+1 -> 6 | B8: ='Final_List-Alerts'!A63 -> Mark Dynamic Wine (dynamic_casepick_wine) | C8: =D8 -> 15 | D8: ='Final_List-Alerts'!B63 -> 15
A9: =A8+1 -> 7 | B9: ='Final_List-Alerts'!A19 -> ITEM IMAGE URL FAILURE | C9: =D9 -> 17 | D9: ='Final_List-Alerts'!B19 -> 17 | E9: source="/splunk/manhattan_active/ABQ/item_image_url/itemURL_bulk_import_check_status.csv" host="misssplunksh01.corp.rndc-usa.com" index="ymc_dev_wms" sourcetype="csv" "ItemURL Bulk Import API Failed" | rename "Item URL Bulk Import API Status" as Status | table Status, _time | G9: 1 | I9: 1 | J9: 1 | M9: 1 | P9: =MID(E9, LEN("source=""/splunk/manhattan_active/"), FIND("csv", E9) - LEN("source=""/splunk/manhattan_active/")+3) -> /ABQ/item_image_url/itemURL_bulk_import_check_status.csv
A10: =A9+1 -> 8 | B10: ='Final_List-Alerts'!A9 -> DIVERT CONFIRMATION DOWN | C10: 100 | D10: ='Final_List-Alerts'!B9 -> High | E10: source="/splunk/manhattan_active/ALLMAWM/au02_divert_confirm_source_destination_down/au02_divert_confirm_source_destination_down_Prod.csv" host="misssplunksh01.corp.rndc-usa.com" index="ymc_dev_wms" sourcetype="csv" |rename PROFILEID as Profile_ID, ENDPOINTID as Endpoint_ID | table Profile_ID Endpoint_ID | I10: 1 | J10: 1 | M10: 1 | P10: =MID(E10, LEN("source=""/splunk/manhattan_active/"), FIND("csv", E10) - LEN("source=""/splunk/manhattan_active/")+3) -> /ALLMAWM/au02_divert_confirm_source_destination_down/au02_divert_confirm_source_destination_down_Prod.csv
A11: =A10+1 -> 9 | B11: ='Final_List-Alerts'!A36 -> PICK LOCATIONS WITH NEGATIVE TBF API FAILURE | C11: 100 | D11: ='Final_List-Alerts'!B36 -> High | E11: source="/splunk/manhattan_active/ABQ/pick_loc_negative_tbf/pick_loc_negative_tbf_status.csv" host="misssplunksh01.corp.rndc-usa.com" index="ymc_dev_wms" sourcetype="csv" "Pick Locations With Negative TBF API Failed" | rename "Pick Locations With Negative TBF API Status" as Status | table Status, _time | I11: 1 | J11: 1 | L11: 1 | M11: 1 | P11: =MID(E11, LEN("source=""/splunk/manhattan_active/"), FIND("csv", E11) - LEN("source=""/splunk/manhattan_active/")+3) -> /ABQ/pick_loc_negative_tbf/pick_loc_negative_tbf_status.csv
A12: =A11+1 -> 10 | B12: ='Final_List-Alerts'!A37 -> PICK LOCATIONS WITH TBF QUANTITY AND NO OPEN TASK DETAILS API FAILURE | C12: 100 | D12: ='Final_List-Alerts'!B37 -> High | E12: source="/splunk/manhattan_active/ABQ/pick_loc_tbf_qty_taskdtls/pick_loc_tbf_qty_taskdtls_status.csv" host="misssplunksh01.corp.rndc-usa.com" index="ymc_dev_wms" sourcetype="csv" "Pick Location TBF Qty Open Task Details API Failed" | rename "Pick Location TBF Qty Open Task Details API Status" as Status | table Status, _time | I12: 1 | J12: 1 | L12: 1 | M12: 1 | P12: =MID(E12, LEN("source=""/splunk/manhattan_active/"), FIND("csv", E12) - LEN("source=""/splunk/manhattan_active/")+3) -> /ABQ/pick_loc_tbf_qty_taskdtls/pick_loc_tbf_qty_taskdtls_status.csv
A13: =A12+1 -> 11 | B13: ='Final_List-Alerts'!A43 -> SLOTTING ITEM DEMAND PACK FAILURE | C13: 100 | D13: ='Final_List-Alerts'!B43 -> High | E13: source="/splunk/manhattan_active/ABQ/slot_itemdemand_pack/slotitemdemand_pack_check_status.csv" host="misssplunksh01.corp.rndc-usa.com" index="ymc_dev_wms" sourcetype="csv" "Slotting Item Demand Pack Import API Failed" | rename "Slot Item Demand Pack Import API Status" as Status | table Status, _time | I13: 1 | J13: 1 | L13: 1 | M13: 1 | P13: =MID(E13, LEN("source=""/splunk/manhattan_active/"), FIND("csv", E13) - LEN("source=""/splunk/manhattan_active/")+3) -> /ABQ/slot_itemdemand_pack/slotitemdemand_pack_check_status.csv
A14: =A13+1 -> 12 | B14: ='Final_List-Alerts'!A44 -> SLOTTING ITEM DEMAND UNIT FAILURE | C14: 100 | D14: ='Final_List-Alerts'!B44 -> High | E14: source="/splunk/manhattan_active/ABQ/slot_itemdemand_unit/slotitemdemand_unit_check_status.csv" host="misssplunksh01.corp.rndc-usa.com" index="ymc_dev_wms" sourcetype="csv" "Slotting Item Demand Unit Import API Failed" | rename "Slot Item Demand Unit Import API Status" as Status | table Status, _time | I14: 1 | J14: 1 | L14: 1 | M14: 1 | P14: =MID(E14, LEN("source=""/splunk/manhattan_active/"), FIND("csv", E14) - LEN("source=""/splunk/manhattan_active/")+3) -> /ABQ/slot_itemdemand_unit/slotitemdemand_unit_check_status.csv
A15: =A14+1 -> 13 | B15: ='Final_List-Alerts'!A14 -> ENDPOINT STATUS | C15: 200 | D15: ='Final_List-Alerts'!B14 -> Medium | E15: source="/splunk/manhattan_active/AUB/endpoint_status/endpoint_status.csv" host="misssplunksh01.corp.rndc-usa.com" index="ymc_dev_wms" sourcetype="ma-endpoint_csv" "AU01_WaveDownload_Endpoint" OR "AU02_DivertConfirm_Endpoint" OR "AU02_PickComplete_Endpoint" OR "AU03_CartonComplete_Endpoint" OR AU02_PickComplete_AWPF_Endpoint OR AU03CompleteCartonEndpoint | where Status = "Stopped" | table Create_time Description Name Type Status | I15: 1 | J15: 1 | M15: 1 | P15: =MID(E15, LEN("source=""/splunk/manhattan_active/"), FIND("csv", E15) - LEN("source=""/splunk/manhattan_active/")+3) -> /AUB/endpoint_status/endpoint_status.csv
A16: =A15+1 -> 14 | B16: ='Final_List-Alerts'!A26 -> LPNS WITH CONSUMED/CANCELLED ALLOCATED QUANTITY API FAILURE | C16: 200 | D16: ='Final_List-Alerts'!B26 -> Meium | E16: source="/splunk/manhattan_active/ABQ/alloclpns_noopntskdtls/rebuild_lpn_status.csv" host="misssplunksh01.corp.rndc-usa.com" index="ymc_dev_wms" sourcetype="csv" "Rebuild LPNs API Failed" | rename "Rebuild LPNs Status" as Status | table Status, _time | I16: 1 | J16: 1 | L16: 1 | M16: 1 | P16: =MID(E16, LEN("source=""/splunk/manhattan_active/"), FIND("csv", E16) - LEN("source=""/splunk/manhattan_active/")+3) -> /ABQ/alloclpns_noopntskdtls/rebuild_lpn_status.csv
A17: =A16+1 -> 15 | B17: ='Final_List-Alerts'!A38 -> PUTAWAY TASK DETAILS API FAILURE | C17: 200 | D17: ='Final_List-Alerts'!B38 -> Medium | E17: source="/splunk/manhattan_active/ABQ/ptwytskdtlsopen_nottiedtskhdr/putaway_task_details_status.csv" host="misssplunksh01.corp.rndc-usa.com" index="ymc_dev_wms" sourcetype="csv" "Putaway Task Details API Failed" | rename "Putaway Task Details" as Status | table Status, _time | dedup Status | I17: 1 | J17: 1 | L17: 1 | M17: 1 | P17: =MID(E17, LEN("source=""/splunk/manhattan_active/"), FIND("csv", E17) - LEN("source=""/splunk/manhattan_active/")+3) -> /ABQ/ptwytskdtlsopen_nottiedtskhdr/putaway_task_details_status.csv
A18: =A17+1 -> 16 | B18: ='Final_List-Alerts'!A39 -> RECOUP SORTING UPDATE API FAILURE | C18: 200 | D18: ='Final_List-Alerts'!B39 -> Medium | E18: source="/splunk/manhattan_active/DFB/recoup_sort_update_lpn/update_lpn_status.csv" host="misssplunksh01.corp.rndc-usa.com" index="ymc_dev_wms" sourcetype="csv" "Update LPN Inventory API Failed" | rename "Update LPN Inventory API Status" as Status | table Status, _time | I18: 1 | J18: 1 | L18: 1 | M18: 1 | P18: =MID(E18, LEN("source=""/splunk/manhattan_active/"), FIND("csv", E18) - LEN("source=""/splunk/manhattan_active/")+3) -> /DFB/recoup_sort_update_lpn/update_lpn_status.csv
A19: =A18+1 -> 17 | B19: ='Final_List-Alerts'!A45 -> SLOTTING LIA DELETE PK RECORDS API FAILURE | C19: 200 | D19: ='Final_List-Alerts'!B45 -> Medium | E19: source="/splunk/manhattan_active/ABQ/slotting_lia_delete/slotting_lia_delete_status.csv" host="misssplunksh01.corp.rndc-usa.com" index="ymc_dev_wms" sourcetype="csv" "Slotting" | rename "Slotting Location PK Search API Status" as Status | table Status, _time | I19: 1 | J19: 1 | L19: 1 | M19: 1 | P19: =MID(E19, LEN("source=""/splunk/manhattan_active/"), FIND("csv", E19) - LEN("source=""/splunk/manhattan_active/")+3) -> /ABQ/slotting_lia_delete/slotting_lia_delete_status.csv
A20: =A19+1 -> 18 | B20: ='Final_List-Alerts'!A2 -> ALLOCATED LPNS WITH NO OPEN TASK DETAILS API FAILURE | C20: 300 | D20: ='Final_List-Alerts'!B2 -> Low | E20: source="/splunk/manhattan_active/ABQ/alloclpns_noopntskdtls/rebuild_lpn_status.csv" host="misssplunksh01.corp.rndc-usa.com" index="ymc_dev_wms" sourcetype="csv" "Rebuild LPNs API Failed" | rename "Rebuild LPNs Status" as Status | table Status, _time | F20: /splunk/manhattan_active/ABQ/alloclpns_noopntskdtls/alloclpns_noopntskdtls.py and alloclpns_noopntskdtls.sql | I20: 1 | J20: 1 | L20: 1 | P20: =MID(E20, LEN("source=""/splunk/manhattan_active/"), FIND("csv", E20) - LEN("source=""/splunk/manhattan_active/")+3) -> /ABQ/alloclpns_noopntskdtls/rebuild_lpn_status.csv
A21: =A20+1 -> 19 | B21: ='Final_List-Alerts'!A13 -> ENDPOINT QUEUE FAILURES | C21: 300 | D21: ='Final_List-Alerts'!B13 -> Low | E21: source="/splunk/manhattan_active/ABQ/failure_count/message_failure_count_list.csv" host="misssplunksh01.corp.rndc-usa.com" index="ymc_dev_wms" sourcetype="msg_csv" NOT AU06CancelCartonDestinationEndpoint NOT EndpointId NOT AU06CancelCartonEndpoint NOT EX59_RouteStopDownload | rename Endpoint_Name as Name, Error_Count as Count | where Count > 100 | table Name Count | I21: 1 | J21: 1 | M21: 1 | P21: =MID(E21, LEN("source=""/splunk/manhattan_active/"), FIND("csv", E21) - LEN("source=""/splunk/manhattan_active/")+3) -> /ABQ/failure_count/message_failure_count_list.csv
A22: 1 | B22: ='Final_List-Alerts'!A16 -> ILPNS WITH NEGATIVE ALLOCATED QUANTITY API FAILURE | C22: 300 | D22: ='Final_List-Alerts'!B16 -> Low | E22: source="/splunk/manhattan_active/ABQ/lpn_negative_allocation/update_lpn_inv_check_status.csv" host="misssplunksh01.corp.rndc-usa.com" index="ymc_dev_wms" sourcetype="csv" "Update Lpn Inventory API Failed" | rename "Update Lpn Inventory API Status" as Status | table Status, _time | I22: 1 | J22: 1 | M22: 1 | P22: =MID(E22, LEN("source=""/splunk/manhattan_active/"), FIND("csv", E22) - LEN("source=""/splunk/manhattan_active/")+3) -> /ABQ/lpn_negative_allocation/update_lpn_inv_check_status.csv
A23: =A22+1 -> 2 | B23: ='Final_List-Alerts'!A23 -> LOCATION REBUILD FAILURE | C23: 300 | D23: ='Final_List-Alerts'!B23 -> Low | E23: source="/splunk/manhattan_active/ABQ/location_rebuild/location_rebuild_check_status.csv" host="misssplunksh01.corp.rndc-usa.com" index="ymc_dev_wms" "Location Rebuild API Failed" | rename "Location Rebuild API Status" as Status | table Status, _time | I23: 1 | J23: 1 | M23: 1 | P23: =MID(E23, LEN("source=""/splunk/manhattan_active/"), FIND("csv", E23) - LEN("source=""/splunk/manhattan_active/")+3) -> /ABQ/location_rebuild/location_rebuild_check_status.csv
A24: =A23+1 -> 3 | B24: ='Final_List-Alerts'!A29 -> OPEN PICK PACK TASK DETAILS API FAILURE | C24: 300 | D24: ='Final_List-Alerts'!B29 -> Low | E24: source="/splunk/manhattan_active/ABQ/tskdtls_comp_openpickpacktskdtls/open_pickpack_task_details_status.csv" host="misssplunksh01.corp.rndc-usa.com" index="ymc_dev_wms" sourcetype="csv" "Open Pick Pack Task Details API Failed" | rename "Open Pick Pack Task Details" as Status | table Status, _time | dedup Status | I24: 1 | J24: 1 | L24: 1 | M24: 1 | P24: =MID(E24, LEN("source=""/splunk/manhattan_active/"), FIND("csv", E24) - LEN("source=""/splunk/manhattan_active/")+3) -> /ABQ/tskdtls_comp_openpickpacktskdtls/open_pickpack_task_details_status.csv
A25: =A24+1 -> 4 | B25: ='Final_List-Alerts'!A31 -> OPEN TASK API FAILURE | C25: 300 | D25: ='Final_List-Alerts'!B31 -> Low | E25: source="/splunk/manhattan_active/ABQ/open_task/open_task_status.csv" host="misssplunksh01.corp.rndc-usa.com" index="ymc_dev_wms" sourcetype="csv" "Open Task API Failed" | rename "Open Task API Status" as Status, "Task Id" as TaskId | table TaskId, Status, _time | I25: 1 | J25: 1 | L25: 1 | M25: 1 | P25: =MID(E25, LEN("source=""/splunk/manhattan_active/"), FIND("csv", E25) - LEN("source=""/splunk/manhattan_active/")+3) -> /ABQ/open_task/open_task_status.csv
A26: =A25+1 -> 5 | B26: ='Final_List-Alerts'!A32 -> OPEN TASK DETAILS API FAILURE | C26: 300 | D26: ='Final_List-Alerts'!B32 -> Low | E26: source="/splunk/manhattan_active/ABQ/open_task_details/open_task_details_status.csv" host="misssplunksh01.corp.rndc-usa.com" index="ymc_dev_wms" sourcetype="csv" "Open Task Details API Failed" | rename "Open Task Details API Status" as Status | table Status, _time | I26: 1 | J26: 1 | L26: 1 | M26: 1 | P26: =MID(E26, LEN("source=""/splunk/manhattan_active/"), FIND("csv", E26) - LEN("source=""/splunk/manhattan_active/")+3) -> /ABQ/open_task_details/open_task_details_status.csv
A27: =A26+1 -> 6 | B27: ='Final_List-Alerts'!A56 -> USER TASK GROUP BULK IMPORT FAILURE | C27: 300 | D27: ='Final_List-Alerts'!B56 -> Low | E27: source="/splunk/manhattan_active/ABQ/user_task_group/user_task_group_status.csv" host="misssplunksh01.corp.rndc-usa.com" index="ymc_dev_wms" sourcetype="csv" "User Task Group Bulk Import API Failed" | rename "User Task Group Bulk Import API Status" as Status | table Status, _time | I27: 1 | J27: 1 | L27: 1 | M27: 1 | P27: =MID(E27, LEN("source=""/splunk/manhattan_active/"), FIND("csv", E27) - LEN("source=""/splunk/manhattan_active/")+3) -> /ABQ/user_task_group/user_task_group_status.csv
A28: =A27+1 -> 7 | B28: ='Final_List-Alerts'!A87 -> inventory_sync_schedule | C28: 1000 | D28: ='Final_List-Alerts'!B87 -> 0 | E28: source="/splunk/manhattan_active/ABQ/inventory_sync_schedule/inventory_sync_schedule_check_status.csv" host="misssplunksh01.corp.rndc-usa.com" index="ymc_dev_wms" "Inventory sync schedule API Failed" |rename "Inventory sync schedule API Status" as Status | table Status, _time | I28: 1 | J28: 1 | M28: 1 | P28: =MID(E28, LEN("source=""/splunk/manhattan_active/"), FIND("csv", E28) - LEN("source=""/splunk/manhattan_active/")+3) -> /ABQ/inventory_sync_schedule/inventory_sync_schedule_check_status.csv
A29: =A28+1 -> 8 | B29: ='Final_List-Alerts'!A85 -> mawm_consolidation_report | C29: 1000 | D29: ='Final_List-Alerts'!B85 -> 0 | O29: POR - MAWM - Shipped oLPN w/ Consolidation Location Assignment????
A30: =A29+1 -> 9 | B30: ='Final_List-Alerts'!A88 -> update_ext_display_barcode | C30: 1000 | D30: ='Final_List-Alerts'!B88 -> 0 | E30: | dbxquery query="select INVOICE, SHIP_TO, CUSTOMER_NUMBER, EMAIL, ITEM, PACK, ITEM_SIZE, SHIP_QTY, ORDER_QTY, ITEM_DESC from c_will_call_ark where tax_id is null" connection="CONF_OKL_WM13" | rename INVOICE AS Invoice, SHIP_TO AS "Ship To", CUSTOMER_NUMBER AS "Cust #" | eval ShortQty = ORDER_QTY - SHIP_QTY | fields - _raw, _time | stats list(ITEM) as "Item", list(ITEM_SIZE) as "Size", list(SHIP_QTY) AS "Ship Qty (Btls)", list(ORDER_QTY) AS "Ord Qty (Btls)", list(ShortQty) as "Short Qty (Btls)",list(PACK) AS "Pack" , list(ITEM_DESC) as "Item Description", values(EMAIL) as "Email" delim=":", by Invoice,"Ship To", "Cust #" | rex mode=sed field="Item Description" "s/:/\n/g" | rex mode=sed field="Ord Qty (Btls)" "s/:/\n/g" | rex mode=sed field=Size "s/:/\n/g" | rex mode=sed field="Ship Qty (Btls)" "s/:/\n/g" | rex mode=sed field="Short Qty (Btls)" "s/:/\n/g" | rex mode=sed field="Pack" "s/:/\n/g" | rex mode=sed field="Item" "s/:/\n/g" | rex mode=sed field="Item Description" "s/ /_/g" | eval "Ship To"=lower('Ship To') | eval "Ship To"=upper(substr('Ship To',1,1)).substr('Ship To',2) |table Invoice "Ship To" "Cust #" Email Item Pack Size "Ship Qty (Btls)" "Ord Qty (Btls)" "Short Qty (Btls)" "Item Description" | J30: 1 | K30: 1 | L30: 1 | M30: 1
B31: Divert Confirm Endpoint Shutdown
B32: WMS - Divert Confirm Endpoint Shutdown
B43: =B2 -> Tasks | C43: =P2 -> csv file name
B44: =B5 -> ATL In Transit RMA ASNs > 30 Days Splunk Alert | C44: =P5 -> /ALLMAWM/hawaii-in-transit-rma-asns/Logs/hawaii-in-transit-rma-asns-HAW.csv | F44: Kinsy : Need to lookinto this
B45: =B6 -> INVENTORY SYNC SCHEDULE API FAILED | C45: =P6 -> /ABQ/inventory_sync_schedule/inventory_sync_schedule_check_status.csv | F45: Combine two schedules
B46: =B9 -> ITEM IMAGE URL FAILURE | C46: =P9 -> /ABQ/item_image_url/itemURL_bulk_import_check_status.csv | F46: /splunk/FTP/DWH/Product_image_dimension.txt
B47: =B10 -> DIVERT CONFIRMATION DOWN | C47: =P10 -> /ALLMAWM/au02_divert_confirm_source_destination_down/au02_divert_confirm_source_destination_down_Prod.csv
B48: =B11 -> PICK LOCATIONS WITH NEGATIVE TBF API FAILURE | C48: =P11 -> /ABQ/pick_loc_negative_tbf/pick_loc_negative_tbf_status.csv
B49: =B12 -> PICK LOCATIONS WITH TBF QUANTITY AND NO OPEN TASK DETAILS API FAILURE | C49: =P12 -> /ABQ/pick_loc_tbf_qty_taskdtls/pick_loc_tbf_qty_taskdtls_status.csv
B50: =B13 -> SLOTTING ITEM DEMAND PACK FAILURE | C50: =P13 -> /ABQ/slot_itemdemand_pack/slotitemdemand_pack_check_status.csv
B51: =B14 -> SLOTTING ITEM DEMAND UNIT FAILURE | C51: =P14 -> /ABQ/slot_itemdemand_unit/slotitemdemand_unit_check_status.csv
B52: =B15 -> ENDPOINT STATUS | C52: =P15 -> /AUB/endpoint_status/endpoint_status.csv
B53: =B16 -> LPNS WITH CONSUMED/CANCELLED ALLOCATED QUANTITY API FAILURE | C53: =P16 -> /ABQ/alloclpns_noopntskdtls/rebuild_lpn_status.csv
B54: =B17 -> PUTAWAY TASK DETAILS API FAILURE | C54: =P17 -> /ABQ/ptwytskdtlsopen_nottiedtskhdr/putaway_task_details_status.csv
B55: =B18 -> RECOUP SORTING UPDATE API FAILURE | C55: =P18 -> /DFB/recoup_sort_update_lpn/update_lpn_status.csv
B56: =B19 -> SLOTTING LIA DELETE PK RECORDS API FAILURE | C56: =P19 -> /ABQ/slotting_lia_delete/slotting_lia_delete_status.csv
B57: =B20 -> ALLOCATED LPNS WITH NO OPEN TASK DETAILS API FAILURE | C57: =P20 -> /ABQ/alloclpns_noopntskdtls/rebuild_lpn_status.csv
B58: =B21 -> ENDPOINT QUEUE FAILURES | C58: =P21 -> /ABQ/failure_count/message_failure_count_list.csv
... B65: =B28 -> inventory_sync_schedule | C65: =P28 -> /ABQ/inventory_sync_schedule/inventory_sync_schedule_check_status.csv

Sheet Combination Splunk Activities
A1: Script Details | L1: House Enabled
A2: Current Script Name | B2: In Use | C2: New Script Name | D2: Description | E2: Desired Cron Frequency | F2: Script Type | G2: Email Notification | H2: Tool | I2: Priority | J2: Note | K2: Unstarted Work/In Design/Being Develped/Deployed | L2: ABQ | M2: ARK | N2: ASH | O2: ATL | P2: AUB | Q2: CCR | R2: CHI | S2: COL | T2: DEN | U2: DFB | V2: ELP | W2: FAR | X2: GRP | Y2: HAW | Z2: HOU | AA2: IND | AB2: JAC | AC2: JES | AD2: KAP | AE2: KAU | AF2: LAF | AG2: LIV | AH2: LOU | AI2: LUB | AJ2: MAU | AK2: NEW | AL2: OAH | AM2: OKL | AN2: OMA | AO2: ORL | AP2: PEN | AQ2: PHO | AR2: POR | AS2: ROM | AT2: RVR | AU2: SAA | AV2: SIO | AW2: TAM | AX2: TOL | AY2: WSD
A3: alloclpns_noopntskdtls | B3: No | D3: Automated cleanup script | E3: Disabled | J3: CRON Disabled for all sites | L3: No | M3: No | N3: No | O3: No | P3: No | Q3: No | R3: No | S3: No | T3: No | U3: No | V3: No | W3: No | X3: No | Y3: No | Z3: No | AA3: No | AB3: No | AC3: No | AD3: No | AE3: No | AF3: No | AG3: No | AH3: No | AI3: No | AJ3: No | AK3: No | AL3: No | AM3: No | AN3: No | AO3: No | AP3: No | AQ3: No | AR3: No | AS3: No | AT3: No | AU3: No | AV3: No | AW3: No | AX3: No | AY3: No
A4: asn_parameter_missing | B4: Yes | C4: ASN Receiving Template Header Application Parameter Missing | D4: This parameter helps to avoid child loads during ASN updates. This reduces component memory usage, DB queries, and improves GC stability. | E4: 8:14 on Monday- Prod | F4: API, Python | G4: Y | H4: Application Parameter Tools | J4: MAWM Scheduled Script Dashboard for API's | K4: Deployed | L4: Yes | M4: Yes | N4: Yes | O4: Yes | P4: Yes | Q4: Yes | R4: Yes | S4: Yes | T4: Yes | U4: Yes | V4: Yes | W4: Yes | X4: Yes | Y4: No | Z4: Yes | AA4: Yes | AB4: Yes | AC4: Yes | AD4: No | AE4: No | AF4: Yes | AG4: Yes | AH4: Yes | AI4: Yes | AJ4: No | AK4: No | AL4: No | AM4: Yes | AN4: Yes | AO4: Yes | AP4: Yes | AQ4: No | AR4: Yes | AS4: No | AT4: Yes | AU4: Yes | AV4: Yes | AW4: Yes | AX4: No | AY4: Yes
A5: asn_parameter_missing | B5: Yes | C5: ASN Receiving Template Header Application Parameter Missing | D5: This parameter helps to avoid child loads during ASN updates. This reduces component memory usage, DB queries, and improves GC stability. | E5: 8:16 on Monday- Stage | F5: API, Python | G5: N | H5: Application Parameter Tools | K5: Deployed | L5: Yes | M5: Yes | N5: Yes | O5: Yes | P5: Yes | Q5: Yes | R5: Yes | S5: Yes | T5: Yes | U5: Yes | V5: Yes | W5: Yes | X5: Yes | Y5: No | Z5: Yes | AA5: Yes | AB5: Yes | AC5: Yes | AD5: No | AE5: No | AF5: Yes | AG5: Yes | AH5: Yes | AI5: Yes | AJ5: No | AK5: No | AL5: No | AM5: Yes | AN5: Yes | AO5: Yes | AP5: Yes | AQ5: No | AR5: Yes | AS5: No | AT5: Yes | AU5: Yes | AV5: Yes | AW5: Yes | AX5: No | AY5: Yes
A6: component_health_check | B6: No | D6: No longer Applicable | E6: Disabled | J6: Only available for LAF, CRON disabled | L6: No | M6: No | N6: No | O6: No | P6: No | Q6: No | R6: No | S6: No | T6: No | U6: No | V6: No | W6: No | X6: No | Y6: No | Z6: No | AA6: No | AB6: No | AC6: No | AD6: No | AE6: No | AF6: No | AG6: No | AH6: No | AI6: No | AJ6: No | AK6: No | AL6: No | AM6: No | AN6: No | AO6: No | AP6: No | AQ6: No | AR6: No | AS6: No | AT6: No | AU6: No | AV6: No | AW6: No | AX6: No | AY6: No
A7: dcorder_ops_parameter_missing | B7: Yes | C7: Dcorder OPS Application Parameter Missing | D7: Max Cut off hours to monitor order planning run metrics | E7: 8:12 on Monday- Prod | F7: API | G7: N | H7: Application Parameter Tools | J7: MAWM Scheduled Script Dashboard for API's----Brandon Johnson | K7: Deployed | L7: Yes | M7: Yes | N7: Yes | O7: Yes | P7: Yes | Q7: Yes | R7: Yes | S7: Yes | T7: Yes | U7: Yes | V7: Yes | W7: Yes | X7: Yes | Y7: No | Z7: Yes | AA7: Yes | AB7: Yes | AC7: Yes | AD7: No | AE7: No | AF7: Yes | AG7: Yes | AH7: Yes | AI7: Yes | AJ7: No | AK7: No | AL7: No | AM7: Yes | AN7: Yes | AO7: Yes | AP7: Yes | AQ7: No | AR7: Yes | AS7: No | AT7: Yes | AU7: Yes | AV7: Yes | AW7: Yes | AX7: No | AY7: Yes
A8: dcorder_ops_parameter_missing | B8: Yes | C8: Dcorder OPS Application Parameter Missing | D8: Max Cut off hours to monitor order planning run metrics | E8: 8:10 on Monday- Stage | F8: API | G8: N | H8: Application Parameter Tools | K8: Deployed | L8: Yes | M8: Yes | N8: Yes | O8: Yes | P8: Yes | Q8: Yes | R8: Yes | S8: Yes | T8: Yes | U8: Yes | V8: Yes | W8: Yes | X8: Yes | Y8: No | Z8: Yes | AA8: Yes | AB8: Yes | AC8: Yes | AD8: No | AE8: No | AF8: Yes | AG8: Yes | AH8: Yes | AI8: Yes | AJ8: No | AK8: No | AL8: No | AM8: Yes | AN8: Yes | AO8: Yes | AP8: Yes | AQ8: No | AR8: Yes | AS8: No | AT8: Yes | AU8: Yes | AV8: Yes | AW8: Yes | AX8: No | AY8: Yes
A9: dybd_parameter | B9: Yes | C9: DYBD Putaway Application Parameter Not Set | D9: Aids in the putaway portion of DYBD Replenishment to prevent the LPN expected container promps during fill portion of task | E9: 9:30 on Monday- Prod | F9: API, Python | G9: N | H9: Application Parameter Tools | J9: POST {{app_host}}/putaway/api/idempotency/applicationParameter/search { "Query": "ApplicationParameterId != null", "Size": 1 } Trigger Condition: Fire the alert if no PK value is returned for the Org in question. | K9: Deployed | L9: Yes | M9: Yes | N9: Yes | O9: Yes | P9: Yes | Q9: Yes | R9: Yes | S9: Yes | T9: Yes | U9: Yes | V9: Yes | W9: Yes | X9: Yes | Y9: No | Z9: Yes | AA9: Yes | AB9: Yes | AC9: Yes | AD9: No | AE9: No | AF9: Yes | AG9: Yes | AH9: Yes | AI9: Yes | AJ9: No | AK9: No | AL9: No | AM9: Yes | AN9: Yes | AO9: Yes | AP9: Yes | AQ9: No | AR9: Yes | AS9: No | AT9: Yes | AU9: Yes | AV9: Yes | AW9: Yes | AX9: No | AY9: Yes
A10: dybd_parameter | B10: Yes | C10: DYBD Putaway Application Parameter Not Set | D10: Aids in the putaway portion of DYBD Replenishment to prevent the LPN expected container promps during fill portion of task | E10: 9:45 on Monday- Stage | F10: API, Python | G10: N | H10: Application Parameter Tools | K10: Deployed | L10: Yes | M10: Yes | N10: Yes | O10: Yes | P10: Yes | Q10: Yes | R10: Yes | S10: Yes | T10: Yes | U10: Yes | V10: Yes | W10: Yes | X10: Yes | Y10: No | Z10: Yes | AA10: Yes | AB10: Yes | AC10: Yes | AD10: No | AE10: No | AF10: Yes | AG10: Yes | AH10: Yes | AI10: Yes | AJ10: No | AK10: No | AL10: No | AM10: Yes | AN10: Yes | AO10: Yes | AP10: Yes | AQ10: No | AR10: Yes | AS10: No | AT10: Yes | AU10: Yes | AV10: Yes | AW10: Yes | AX10: No | AY10: Yes
A11: missing_TGE_parameter | B11: Yes | C11: Missing Putaway Replenishment TGE Application Parameter | D11: Allows to bypass TGE checks on putaway portion of replen tasks | E11: 8:00 on Monday | F11: API, Python | G11: Y | H11: Application Parameter Tools | J11: Under MAWM Scheduled Script Dashboard for API's | K11: Deployed | L11: Yes | M11: Yes | N11: Yes | O11: Yes | P11: Yes | Q11: Yes | R11: Yes | S11: Yes | T11: Yes | U11: Yes | V11: Yes | W11: Yes | X11: Yes | Y11: No | Z11: Yes | AA11: Yes | AB11: Yes | AC11: Yes | AD11: No | AE11: No | AF11: Yes | AG11: Yes | AH11: Yes | AI11: Yes | AJ11: No | AK11: No | AL11: No | AM11: Yes | AN11: Yes | AO11: Yes | AP11: Yes | AQ11: No | AR11: Yes | AS11: No | AT11: Yes | AU11: Yes | AV11: Yes | AW11: Yes | AX11: No | AY11: Yes
A12: dynamic_casepick_liquor | B12: Yes | C12: Mark Dynamic Case Pick | D12: LIV Heavy Hitters | E12: 00:00 every day Mon-Sat | F12: API, Python | G12: Y | H12: MAWM Scheduled Script Dashboard for API's | I12: 5 | J12: Only for LIV, Related to line 62 & 63 on the Final List. | K12: Being Developed | L12: No | M12: No | N12: No | O12: No | P12: No | Q12: No | R12: No | S12: No | T12: No | U12: No | V12: No | W12: No | X12: No | Y12: No | Z12: No | AA12: No | AB12: No | AC12: No | AD12: No | AE12: No | AF12: No | AG12: Yes | AH12: No | AI12: No | AJ12: No | AK12: No | AL12: No | AM12: No | AN12: No | AO12: No | AP12: No | AQ12: No | AR12: No | AS12: No | AT12: No | AU12: No | AV12: No | AW12: No | AX12: No | AY12: No
A13: dynamic_casepick_wine | B13: Yes | C13: Mark Dynamic Wine | D13: LIV Heavy Hitters | E13: 19:00 every day Mon through Fri | F13: API, Python | G13: Y | H13: MAWM Scheduled Script Dashboard for API's | I13: 4 | J13: Only for LIV, Related to line 62 & 63 on the Final List. | K13: Being Developed | L13: No | M13: No | N13: No | O13: No | P13: No | Q13: No | R13: No | S13: No | T13: No | U13: No | V13: No | W13: No | X13: No | Y13: No | Z13: No | AA13: No | AB13: No | AC13: No | AD13: No | AE13: No | AF13: No | AG13: Yes | AH13: No | AI13: No | AJ13: No | AK13: No | AL13: No | AM13: No | AN13: No | AO13: No | AP13: No | AQ13: No | AR13: No | AS13: No | AT13: No | AU13: No | AV13: No | AW13: No | AX13: No | AY13: No
A14: dynamic_casepick_wine | B14: Yes | C14: Mark Dynamic Wine | D14: LIV Heavy Hitters | E14: At minute 0, 15, 30, and 45 past hour 17 and 18 on every day-of-week from Monday through Friday | F14: API, Python | G14: Y | H14: MAWM Scheduled Script Dashboard for API's | I14: 4 | J14: Only for LIV, Related to line 62 & 63 on the Final List. | K14: Being Developed | L14: No | M14: No | N14: No | O14: No | P14: No | Q14: No | R14: No | S14: No | T14: No | U14: No | V14: No | W14: No | X14: No | Y14: No | Z14: No | AA14: No | AB14: No | AC14: No | AD14: No | AE14: No | AF14: No | AG14: Yes | AH14: No | AI14: No | AJ14: No | AK14: No | AL14: No | AM14: No | AN14: No | AO14: No | AP14: No | AQ14: No | AR14: No | AS14: No | AT14: No | AU14: No | AV14: No | AW14: No | AX14: No | AY14: No
A15: will_call_master | B15: Yes | C15: Will Call Master | D15: Notifies SalesPerson when Will Call order is completed | E15: See CRON Frequency Tab | F15: DB Query / API Import / Python | G15: Y | H15: New BI Tool/ Lambda Function | K15: Being Developed | L15: Yes | M15: Yes | N15: Yes | O15: Yes | P15: No | Q15: Yes | R15: No | S15: Yes | T15: Yes | U15: Yes | V15: Yes | W15: Yes | X15: Yes | Y15: No | Z15: Yes | AA15: Yes | AB15: Yes | AC15: Yes | AD15: No | AE15: No | AF15: Yes | AG15: Yes | AH15: Yes | AI15: Yes | AJ15: No | AK15: No | AL15: No | AM15: Yes | AN15: Yes | AO15: Yes | AP15: Yes | AQ15: No | AR15: No | AS15: No | AT15: No | AU15: Yes | AV15: Yes | AW15: Yes | AX15: No | AY15: Yes
A16: endpoint_status | B16: Yes | C16: Endpoint Status | D16: Queries status of AU* Endpoints | E16: At Minute 15 | F16: API , Python | G16: Y | H16: Alert | L16: Yes | M16: Yes | N16: Yes | O16: Yes | P16: Yes | Q16: Yes | R16: Yes | S16: Yes | T16: Yes | U16: Yes | V16: Yes | W16: Yes | X16: Yes | Y16: No | Z16: Yes | AA16: Yes | AB16: Yes | AC16: Yes | AD16: No | AE16: No | AF16: Yes | AG16: Yes | AH16: Yes | AI16: Yes | AJ16: No | AK16: No | AL16: No | AM16: Yes | AN16: Yes | AO16: Yes | AP16: Yes | AQ16: No | AR16: Yes | AS16: No | AT16: Yes | AU16: Yes | AV16: Yes | AW16: Yes | AX16: No | AY16: Yes
A17: inventory_sync_all | B17: No | D17: Fires weekly inventory Sync | E17: Disabled | F17: API Job | G17: Y | H17: MAWM Scheduled Script Dashboard for API's | J17: CRON Disabled for all sites | L17: No | M17: No | N17: No | O17: No | P17: No | Q17: No | R17: No | S17: No | T17: No | U17: No | V17: No | W17: No | X17: No | Y17: No | Z17: No | AA17: No | AB17: No | AC17: No | AD17: No | AE17: No | AF17: No | AG17: No | AH17: No | AI17: No | AJ17: No | AK17: No | AL17: No | AM17: No | AN17: No | AO17: No | AP17: No | AQ17: No | AR17: No | AS17: No | AT17: No | AU17: No | AV17: No | AW17: No | AX17: No | AY17: No
A18: inventory_sync_schedule | B18: Yes | C18: WMS Inventory Sync | D18: Triggers Inventory Sync for ERPs | E18: See CRON Frequency Tab | G18: N | H18: MAWM Scheduled Script Dashboard for API's | I18: 1 | J18: Line 87 | K18: Being Developed | L18: Yes | M18: Yes | N18: Yes | O18: Yes | P18: Yes | Q18: Yes | R18: Yes | S18: Yes | T18: Yes | U18: Yes | V18: Yes | W18: Yes | X18: Yes | Y18: No | Z18: Yes | AA18: Yes | AB18: Yes | AC18: Yes | AD18: No | AE18: No | AF18: Yes | AG18: Yes | AH18: Yes | AI18: Yes | AJ18: No | AK18: No | AL18: No | AM18: Yes | AN18: Yes | AO18: Yes | AP18: Yes | AQ18: No | AR18: Yes | AS18: No | AT18: Yes | AU18: Yes | AV18: Yes | AW18: Yes | AX18: No | AY18: Yes
A19: item_bulk_import | B19: Yes | C19: Item Oddball SKU Update | D19: Marks SKUs as oddball | E19: See CRON Frequency Tab | F19: SQL, API | G19: N | H19: MAWM Scheduled Script Dashboard for API's | I19: Complete | J19: Pending Production Release | K19: Being Developed | L19: Yes | M19: Yes | N19: Yes | O19: Yes | P19: Yes | Q19: Yes | R19: Yes | S19: Yes | T19: Yes | U19: Yes | V19: Yes | W19: Yes | X19: Yes | Y19: No | Z19: Yes | AA19: Yes | AB19: Yes | AC19: Yes | AD19: No | AE19: No | AF19: Yes | AG19: Yes | AH19: Yes | AI19: Yes | AJ19: No | AK19: No | AL19: No | AM19: Yes | AN19: Yes | AO19: Yes | AP19: Yes | AQ19: No | AR19: Yes | AS19: No | AT19: Yes | AU19: Yes | AV19: Yes | AW19: Yes | AX19: No | AY19: Yes
A20: item_image_url | B20: Yes | C20: Item Image URL Import | D20: Imports Item Image URLs from data warehouse feed into WM | E20: See CRON Frequency Tab | F20: Python, API | G20: N | H20: MAWM Scheduled Script Dashboard for API's | I20: 3 | J20: Line 19 | K20: Being Developed | L20: Yes | M20: Yes | N20: Yes | O20: Yes | P20: Yes | Q20: Yes | R20: Yes | S20: Yes | T20: Yes | U20: Yes | V20: Yes | W20: Yes | X20: Yes | Y20: No | Z20: Yes | AA20: Yes | AB20: Yes | AC20: Yes | AD20: No | AE20: No | AF20: Yes | AG20: Yes | AH20: Yes | AI20: Yes | AJ20: No | AK20: No | AL20: No | AM20: Yes | AN20: Yes | AO20: Yes | AP20: Yes | AQ20: No | AR20: Yes | AS20: No | AT20: Yes | AU20: Yes | AV20: Yes | AW20: Yes | AX20: No | AY20: Yes
A21: item_master_search | B21: Yes | C21: Item Master Left Join Search Application Parameter | D21: The application parameter within the item master component is necessary to prevent cubing errors resulting in orders from deselecting and ensuring Item Level verification PIX from receiving populate with the correct data. | E21: 7:45 on Monday | F21: Python, API | G21: N | H21: Application Parameter Tools | J21: POST {{app_host}}/item-master/api/idempotency/applicationParameter/search { "Query": "ApplicationParameterId = item.remove.left.join.item.search and Value = true" } | K21: Deployed | L21: Yes | M21: Yes | N21: Yes | O21: Yes | P21: Yes | Q21: Yes | R21: Yes | S21: Yes | T21: Yes | U21: Yes | V21: Yes | W21: Yes | X21: Yes | Y21: No | Z21: Yes | AA21: Yes | AB21: Yes | AC21: Yes | AD21: No | AE21: No | AF21: Yes | AG21: Yes | AH21: Yes | AI21: Yes | AJ21: No | AK21: No | AL21: No | AM21: Yes | AN21: Yes | AO21: Yes | AP21: Yes | AQ21: No | AR21: Yes | AS21: No | AT21: Yes | AU21: Yes | AV21: Yes | AW21: Yes | AX21: No | AY21: Yes
A22: item_volume | B22: Yes | E22: 8:00 on Sunday | J22: Reach out to Shiva or Kinsy or Thomas for details | L22: Yes | M22: Yes | N22: Yes | O22: Yes | P22: Yes | Q22: Yes | R22: Yes | S22: Yes | T22: Yes | U22: Yes | V22: Yes | W22: Yes | X22: Yes | Y22: No | Z22: Yes | AA22: Yes | AB22: Yes | AC22: Yes | AD22: No | AE22: No | AF22: Yes | AG22: Yes | AH22: Yes | AI22: Yes | AJ22: No | AK22: No | AL22: No | AM22: Yes | AN22: Yes | AO22: Yes | AP22: Yes | AQ22: No | AR22: Yes | AS22: No | AT22: Yes | AU22: Yes | AV22: Yes | AW22: Yes | AX22: No | AY22: Yes
A23: ITEMLOC_PRD | B23: Yes | C23: ItemLoc PRD | D23: Item locations are sent into staging tables that are read by ERPs | E23: See CRON Frequency Tab | F23: SQL, Python | G23: N | H23: MAWM Scheduled Script Dashboard for API's | I23: 2 | J23: Line 61 | K23: Being Developed | L23: Yes | M23: Yes | N23: Yes | O23: Yes | P23: No | Q23: Yes | R23: No | S23: Yes | T23: Yes | U23: Yes | V23: Yes | W23: Yes | X23: Yes | Y23: No | Z23: Yes | AA23: Yes | AB23: Yes | AC23: Yes | AD23: No | AE23: No | AF23: Yes | AG23: Yes | AH23: Yes | AI23: Yes | AJ23: No | AK23: No | AL23: No | AM23: Yes | AN23: Yes | AO23: Yes | AP23: Yes | AQ23: No | AR23: No | AS23: No | AT23: No | AU23: Yes | AV23: Yes | AW23: Yes | AX23: No | AY23: Yes
A24: location_rebuild | B24: No | C24: Location Rebuild | D24: Rebuilding Locations in WM | E24: Disabled | F24: API | J24: CRON Disabled for all sites | L24: No | M24: No | N24: No | O24: No | P24: No | Q24: No | R24: No | S24: No | T24: No | U24: No | V24: No | W24: No | X24: No | Y24: No | Z24: No | AA24: No | AB24: No | AC24: No | AD24: No | AE24: No | AF24: No | AG24: No | AH24: No | AI24: No | AJ24: No | AK24: No | AL24: No | AM24: No | AN24: No | AO24: No | AP24: No | AQ24: No | AR24: No | AS24: No | AT24: No | AU24: No | AV24: No | AW24: No | AX24: No | AY24: No
A25: lpn_consumed_cancel_allocation | B25: No | D25: No longer Applicable | E25: Disabled | J25: CRON Disabled for all sites | L25: Yes | M25: No | N25: Yes | O25: Yes | P25: No | Q25: Yes | R25: No | S25: Yes | T25: Yes | U25: Yes | V25: Yes | W25: Yes | X25: Yes | Y25: No | Z25: Yes | AA25: Yes | AB25: Yes | AC25: Yes | AD25: No | AE25: No | AF25: Yes | AG25: Yes | AH25: Yes | AI25: Yes | AJ25: No | AK25: No | AL25: No | AM25: Yes | AN25: Yes | AO25: Yes | AP25: Yes | AQ25: No | AR25: Yes | AS25: No | AT25: No | AU25: Yes | AV25: Yes | AW25: Yes | AX25: No | AY25: Yes
A26: lpn_location_assignment | B26: No | C26: LPN Location Assignment | D26: Tracks invalid location assignments via API delete failures | E26: 5* | F26: Python, API, SQL | G26: Y | L26: No | M26: No | N26: No | O26: No | P26: No | Q26: No | R26: No | S26: No | T26: No | U26: No | V26: No | W26: No | X26: Yes | Y26: No | Z26: No | AA26: No | AB26: No | AC26: No | AD26: No | AE26: No | AF26: No | AG26: No | AH26: No | AI26: No | AJ26: No | AK26: No | AL26: No | AM26: No | AN26: No | AO26: No | AP26: No | AQ26: No | AR26: No | AS26: No | AT26: No | AU26: No | AV26: No | AW26: No | AX26: No | AY26: No
A27: lpn_negative_allocation | B27: No | D27: No longer Applicable | E27: Disabled | J27: CRON Disabled for all sites | L27: Yes | M27: No | N27: Yes | O27: Yes | P27: No | Q27: Yes | R27: No | S27: Yes | T27: Yes | U27: Yes | V27: Yes | W27: Yes | X27: Yes | Y27: No | Z27: Yes | AA27: Yes | AB27: Yes | AC27: Yes | AD27: No | AE27: No | AF27: Yes | AG27: Yes | AH27: Yes | AI27: Yes | AJ27: No | AK27: No | AL27: No | AM27: Yes | AN27: Yes | AO27: Yes | AP27: Yes | AQ27: No | AR27: Yes | AS27: No | AT27: No | AU27: Yes | AV27: Yes | AW27: Yes | AX27: No | AY27: Yes
A28: mawm_consolidation_report | B28: Yes | C28: MAWM Consolidation Report | D28: Shows consolidation opportunities for WM | E28: See CRON Frequency Tab | F28: Report,SQL | G28: N | H28: Report | J28: This alert simply execute 7 different scripts and send email from python code itself. Need a tool like simply feed the sql files and send the results. | L28: Yes | M28: Yes | N28: Yes | O28: Yes | P28: Yes | Q28: Yes | R28: Yes | S28: Yes | T28: Yes | U28: Yes | V28: Yes | W28: Yes | X28: Yes | Y28: No | Z28: Yes | AA28: Yes | AB28: Yes | AC28: Yes | AD28: No | AE28: No | AF28: Yes | AG28: Yes | AH28: Yes | AI28: Yes | AJ28: No | AK28: No | AL28: No | AM28: Yes | AN28: Yes | AO28: Yes | AP28: Yes | AQ28: No | AR28: Yes | AS28: No | AT28: Yes | AU28: Yes | AV28: Yes | AW28: Yes | AX28: No | AY28: Yes
A29: failure_count | B29: Yes | C29: Failure Count | D29: Retrieves message failure counts from dashboard in last 24 hrs | E29: At 9:55 | F29: API, Python | G29: Y | H29: Alert | L29: Yes | M29: Yes | N29: Yes | O29: Yes | P29: Yes | Q29: Yes | R29: Yes | S29: Yes | T29: Yes | U29: Yes | V29: Yes | W29: Yes | X29: Yes | Y29: No | Z29: Yes | AA29: Yes | AB29: Yes | AC29: Yes | AD29: No | AE29: No | AF29: Yes | AG29: Yes | AH29: Yes | AI29: Yes | AJ29: No | AK29: No | AL29: No | AM29: Yes | AN29: Yes | AO29: Yes | AP29: Yes | AQ29: No | AR29: Yes | AS29: No | AT29: Yes | AU29: Yes | AV29: Yes | AW29: Yes | AX29: No | AY29: Yes
A30: failure_count_10min | B30: Yes | C30: Failure Count 10 Minutes | D30: Retrieves message failure counts from dashboard in last 10 minutes | E30: At Minute 10 | F30: API, Python | G30: Y | H30: Alert | L30: Yes | M30: Yes | N30: Yes | O30: Yes | P30: Yes | Q30: Yes | R30: Yes | S30: Yes | T30: Yes | U30: Yes | V30: Yes | W30: Yes | X30: Yes | Y30: No | Z30: Yes | AA30: Yes | AB30: Yes | AC30: Yes | AD30: No | AE30: No | AF30: Yes | AG30: Yes | AH30: Yes | AI30: Yes | AJ30: No | AK30: No | AL30: No | AM30: Yes | AN30: Yes | AO30: Yes | AP30: Yes | AQ30: No | AR30: Yes | AS30: No | AT30: Yes | AU30: Yes | AV30: Yes | AW30: Yes | AX30: No | AY30: Yes
A31: missing_TGE_parameter | B31: No | D31: No longer Applicable | E31: 0.6875 | J31: CRON Disabled | L31: Yes | M31: Yes | N31: Yes | O31: Yes | P31: Yes | Q31: Yes | R31: Yes | S31: Yes | T31: Yes | U31: Yes | V31: Yes | W31: Yes | X31: Yes | Y31: No | Z31: Yes | AA31: Yes | AB31: Yes | AC31: Yes | AD31: No | AE31: No | AF31: Yes | AG31: Yes | AH31: Yes | AI31: Yes | AJ31: No | AK31: No | AL31: No | AM31: Yes | AN31: Yes | AO31: Yes | AP31: Yes | AQ31: No | AR31: Yes | AS31: No | AT31: Yes | AU31: Yes | AV31: Yes | AW31: Yes | AX31: No | AY31: Yes
A32: mawm_wave_runtime | B32: Yes | C32: MAWM Wave Runtime | D32: Looks at long-running waves | E32: 8:30 every day on Mon-Fri | F32: SQL, API | G32: Y | H32: Report | L32: Yes | M32: Yes | N32: Yes | O32: Yes | P32: Yes | Q32: Yes | R32: Yes | S32: Yes | T32: Yes | U32: Yes | V32: Yes | W32: Yes | X32: Yes | Y32: No | Z32: Yes | AA32: Yes | AB32: Yes | AC32: Yes | AD32: No | AE32: No | AF32: Yes | AG32: Yes | AH32: Yes | AI32: Yes | AJ32: No | AK32: No | AL32: No | AM32: Yes | AN32: Yes | AO32: Yes | AP32: Yes | AQ32: No | AR32: Yes | AS32: No | AT32: Yes | AU32: Yes | AV32: Yes | AW32: Yes | AX32: No | AY32: Yes
A33: monthly_slotting_dashboard | B33: No | D33: No longer Applicable | E33: At 3:00 on 1st Day of Month | J33: CRON Disabled | L33: Yes | M33: Yes | N33: Yes | O33: Yes | P33: Yes | Q33: Yes | R33: Yes | S33: Yes | T33: Yes | U33: Yes | V33: Yes | W33: Yes | X33: Yes | Y33: No | Z33: Yes | AA33: Yes | AB33: Yes | AC33: Yes | AD33: No | AE33: No | AF33: Yes | AG33: Yes | AH33: Yes | AI33: Yes | AJ33: No | AK33: No | AL33: No | AM33: Yes | AN33: Yes | AO33: Yes | AP33: Yes | AQ33: No | AR33: Yes | AS33: No | AT33: Yes | AU33: Yes | AV33: Yes | AW33: Yes | AX33: No | AY33: Yes
A34: monthly_slotting_dashboard | B34: No | D34: No longer Applicable | E34: at 9:00 on Sunday | J34: CRON Disabled | L34: Yes | M34: Yes | N34: Yes | O34: Yes | P34: Yes | Q34: Yes | R34: Yes | S34: Yes | T34: Yes | U34: Yes | V34: Yes | W34: Yes | X34: Yes | Y34: No | Z34: Yes | AA34: Yes | AB34: Yes | AC34: Yes | AD34: No | AE34: No | AF34: Yes | AG34: Yes | AH34: Yes | AI34: Yes | AJ34: No | AK34: No | AL34: No | AM34: Yes | AN34: Yes | AO34: Yes | AP34: Yes | AQ34: No | AR34: Yes | AS34: No | AT34: Yes | AU34: Yes | AV34: Yes | AW34: Yes | AX34: No | AY34: Yes
A35: monthly_slotting_dashboard | B35: No | D35: No longer Applicable | E35: At 15:42 | J35: CRON Disabled | L35: Yes | M35: Yes | N35: Yes | O35: Yes | P35: Yes | Q35: Yes | R35: Yes | S35: Yes | T35: Yes | U35: Yes | V35: Yes | W35: Yes | X35: Yes | Y35: No | Z35: Yes | AA35: Yes | AB35: Yes | AC35: Yes | AD35: No | AE35: No | AF35: Yes | AG35: Yes | AH35: Yes | AI35: Yes | AJ35: No | AK35: No | AL35: No | AM35: Yes | AN35: Yes | AO35: Yes | AP35: Yes | AQ35: No | AR35: Yes | AS35: No | AT35: Yes | AU35: Yes | AV35: Yes | AW35: Yes | AX35: No | AY35: Yes
A36: onhold_iteminventory | B36: No | C36: Onhold item inventory | D36: Looks in Oracle to see if item is active or not, and cross references to MAWM via database link, outputs results via email | E36: At 11:00 Mon-Fri | F36: SQL | G36: Y | J36: For West Sites | L36: No | M36: No | N36: No | O36: No | P36: Yes | Q36: No | R36: Yes | S36: No | T36: No | U36: No | V36: No | W36: No | X36: No | Y36: No | Z36: No | AA36: No | AB36: No | AC36: No | AD36: No | AE36: No | AF36: No | AG36: No | AH36: No | AI36: No | AJ36: No | AK36: No | AL36: No | AM36: No | AN36: No | AO36: No | AP36: No | AQ36: No | AR36: Yes | AS36: No | AT36: Yes | AU36: No | AV36: No | AW36: No | AX36: No | AY36: No
A37: open_task | B37: No | D37: No longer Applicable | E37: Disabled | J37: CRON Disabled for all sites | L37: No | M37: No | N37: No | O37: No | P37: No | Q37: No | R37: No | S37: No | T37: No | U37: No | V37: No | W37: No | X37: No | Y37: No | Z37: No | AA37: No | AB37: No | AC37: No | AD37: No | AE37: No | AF37: No | AG37: No | AH37: No | AI37: No | AJ37: No | AK37: No | AL37: No | AM37: No | AN37: No | AO37: No | AP37: No | AQ37: No | AR37: No | AS37: No | AT37: No | AU37: No | AV37: No | AW37: No | AX37: No | AY37: No
A38: open_task_details | B38: No | D38: No longer Applicable | E38: Disabled | J38: CRON Disabled for all sites | L38: No | M38: No | N38: No | O38: No | P38: No | Q38: No | R38: No | S38: No | T38: No | U38: No | V38: No | W38: No | X38: No | Y38: No | Z38: No | AA38: No | AB38: No | AC38: No | AD38: No | AE38: No | AF38: No | AG38: No | AH38: No | AI38: No | AJ38: No | AK38: No | AL38: No | AM38: No | AN38: No | AO38: No | AP38: No | AQ38: No | AR38: No | AS38: No | AT38: No | AU38: No | AV38: No | AW38: No | AX38: No | AY38: No
A39: pick_loc_negative_tbf | B39: No | D39: No longer Applicable | E39: Disabled | J39: CRON Disabled for all sites | L39: Yes | M39: No | N39: Yes | O39: Yes | P39: No | Q39: Yes | R39: No | S39: Yes | T39: Yes | U39: Yes | V39: Yes | W39: Yes | X39: Yes | Y39: No | Z39: Yes | AA39: Yes | AB39: Yes | AC39: Yes | AD39: No | AE39: No | AF39: Yes | AG39: Yes | AH39: Yes | AI39: Yes | AJ39: No | AK39: No | AL39: No | AM39: Yes | AN39: Yes | AO39: Yes | AP39: Yes | AQ39: No | AR39: Yes | AS39: No | AT39: No | AU39: Yes | AV39: Yes | AW39: Yes | AX39: No | AY39: Yes
A40: pick_loc_tbf_qty_taskdtls | B40: No | D40: No longer Applicable | E40: Disabled | J40: CRON Disabled for all sites | L40: Yes | M40: No | N40: Yes | O40: Yes | P40: No | Q40: Yes | R40: No | S40: Yes | T40: Yes | U40: Yes | V40: Yes | W40: Yes | X40: Yes | Y40: No | Z40: Yes | AA40: Yes | AB40: Yes | AC40: Yes | AD40: No | AE40: No | AF40: Yes | AG40: Yes | AH40: Yes | AI40: Yes | AJ40: No | AK40: No | AL40: No | AM40: Yes | AN40: Yes | AO40: Yes | AP40: Yes | AQ40: No | AR40: Yes | AS40: No | AT40: No | AU40: Yes | AV40: Yes | AW40: Yes | AX40: No | AY40: Yes
A41: mawm_wave_runtime_weekly | B41: Yes | C41: MAWM Wave Runtime Weekly | D41: Looks at long-running waves by week | E41: 8:00 on Monday | F41: SQL, API | G41: Y | H41: Report | L41: Yes | M41: Yes | N41: Yes | O41: Yes | P41: Yes | Q41: Yes | R41: Yes | S41: Yes | T41: Yes | U41: Yes | V41: Yes | W41: Yes | X41: Yes | Y41: No | Z41: Yes | AA41: Yes | AB41: Yes | AC41: Yes | AD41: No | AE41: No | AF41: Yes | AG41: Yes | AH41: Yes | AI41: Yes | AJ41: No | AK41: No | AL41: No | AM41: Yes | AN41: Yes | AO41: Yes | AP41: Yes | AQ41: No | AR41: Yes | AS41: No | AT41: Yes | AU41: Yes | AV41: Yes | AW41: Yes | AX41: No | AY41: Yes
A42: ptwytskdtlsopen_nottiedtskhdr | B42: No | D42: No longer Applicable | E42: Disabled | J42: CRON Disabled for all sites | L42: No | M42: No | N42: No | O42: No | P42: No | Q42: No | R42: No | S42: No | T42: No | U42: No | V42: No | W42: No | X42: No | Y42: No | Z42: No | AA42: No | AB42: No | AC42: No | AD42: No | AE42: No | AF42: No | AG42: No | AH42: No | AI42: No | AJ42: No | AK42: No | AL42: No | AM42: No | AN42: No | AO42: No | AP42: No | AQ42: No | AR42: No | AS42: No | AT42: No | AU42: No | AV42: No | AW42: No | AX42: No | AY42: No
A43: receiving_user_exit_response | B43: Yes | C43: Receiving Component User Exit Response Template | D43: The application parameter uses a response template that nullifies the ASN in the custom EX53 payload. Deleting this application parameter is necessary for EX53 Empty Keg returns functionality to work correctly. | E43: 7:45 on Monday | F43: API, Python | G43: N | H43: Application Parameter Tools | J43: MAWM Scheduled Script Dashboard for API's | K43: Deployed | L43: Yes | M43: Yes | N43: Yes | O43: Yes | P43: Yes | Q43: Yes | R43: Yes | S43: Yes | T43: Yes | U43: Yes | V43: Yes | W43: Yes | X43: Yes | Y43: No | Z43: Yes | AA43: Yes | AB43: Yes | AC43: Yes | AD43: No | AE43: No | AF43: Yes | AG43: Yes | AH43: Yes | AI43: Yes | AJ43: No | AK43: No | AL43: No | AM43: Yes | AN43: Yes | AO43: Yes | AP43: Yes | AQ43: No | AR43: Yes | AS43: No | AT43: Yes | AU43: Yes | AV43: Yes | AW43: Yes | AX43: No | AY43: Yes
A44: recoup_sort_update_lpn | B44: No | D44: No longer Applicable due to EX73 | E44: At Minute 10 | J44: Can be disabled | L44: No | M44: No | N44: No | O44: No | P44: No | Q44: No | R44: No | S44: No | T44: No | U44: Yes | V44: No | W44: No | X44: No | Y44: No | Z44: No | AA44: No | AB44: No | AC44: No | AD44: No | AE44: No | AF44: No | AG44: No | AH44: No | AI44: No | AJ44: No | AK44: No | AL44: No | AM44: No | AN44: No | AO44: No | AP44: No | AQ44: No | AR44: No | AS44: No | AT44: No | AU44: No | AV44: No | AW44: No | AX44: No | AY44: No
A45: reslot_app_parameter_missing | B45: Yes | C45: Slotting Component Manual Re-Slot Application Parameter Missing | D45: Allows to run manual reslot proccess without getting internal service error | E45: 8:33 on Monday-Prod | F45: API, Python | G45: N | H45: Application Parameter Tools | K45: Deployed | L45: Yes | M45: Yes | N45: Yes | O45: Yes | P45: Yes | Q45: Yes | R45: Yes | S45: Yes | T45: Yes | U45: Yes | V45: Yes | W45: Yes | X45: Yes | Y45: No | Z45: Yes | AA45: Yes | AB45: Yes | AC45: Yes | AD45: No | AE45: No | AF45: Yes | AG45: Yes | AH45: Yes | AI45: Yes | AJ45: No | AK45: No | AL45: No | AM45: Yes | AN45: Yes | AO45: Yes | AP45: Yes | AQ45: No | AR45: Yes | AS45: No | AT45: Yes | AU45: Yes | AV45: Yes | AW45: Yes | AX45: No | AY45: Yes
A46: reslot_app_parameter_missing | B46: Yes | C46: Slotting Component Manual Re-Slot Application Parameter Missing | D46: Allows to run manual reslot proccess without getting internal service error | E46: 8:30 on Monday- Stage | F46: ApI, Python | G46: N | H46: Application Parameter Tools | K46: Deployed | L46: Yes | M46: Yes | N46: Yes | O46: Yes | P46: Yes | Q46: Yes | R46: Yes | S46: Yes | T46: Yes | U46: Yes | V46: Yes | W46: Yes | X46: Yes | Y46: No | Z46: Yes | AA46: Yes | AB46: Yes | AC46: Yes | AD46: No | AE46: No | AF46: Yes | AG46: Yes | AH46: Yes | AI46: Yes | AJ46: No | AK46: No | AL46: No | AM46: Yes | AN46: Yes | AO46: Yes | AP46: Yes | AQ46: No | AR46: Yes | AS46: No | AT46: Yes | AU46: Yes | AV46: Yes | AW46: Yes | AX46: No | AY46: Yes
A47: slot_itemdemand_pack | B47: Yes | C47: Slotting Full Case Demand Import | D47: Imports Slotting Case Demand | E47: See CRON Frequency Tab | F47: DB Query / API Import | G47: N | H47: MAWM Scheduled Script Dashboard for API's | I47: 6 | J47: Line 43 | K47: Being Developed | L47: Yes | M47: Yes | N47: Yes | O47: Yes | P47: Yes | Q47: Yes | R47: Yes | S47: Yes | T47: Yes | U47: Yes | V47: Yes | W47: Yes | X47: Yes | Y47: No | Z47: Yes | AA47: Yes | AB47: Yes | AC47: Yes | AD47: No | AE47: No | AF47: Yes | AG47: Yes | AH47: Yes | AI47: Yes | AJ47: No | AK47: No | AL47: No | AM47: Yes | AN47: Yes | AO47: Yes | AP47: Yes | AQ47: No | AR47: Yes | AS47: No | AT47: Yes | AU47: Yes | AV47: Yes | AW47: Yes | AX47: No | AY47: Yes
A48: slot_itemdemand_unit | B48: Yes | C48: Slotting Loose Bottle Demand Import | D48: Imports Slotting Bottle Demand | E48: See CRON Frequency Tab | F48: DB Query / API Import | G48: N | H48: MAWM Scheduled Script Dashboard for API's | I48: 7 | J48: Line 44 | K48: Being Developed | L48: Yes | M48: Yes | N48: Yes | O48: Yes | P48: Yes | Q48: Yes | R48: Yes | S48: Yes | T48: Yes | U48: Yes | V48: Yes | W48: Yes | X48: Yes | Y48: No | Z48: Yes | AA48: Yes | AB48: Yes | AC48: Yes | AD48: No | AE48: No | AF48: Yes | AG48: Yes | AH48: Yes | AI48: Yes | AJ48: No | AK48: No | AL48: No | AM48: Yes | AN48: Yes | AO48: Yes | AP48: Yes | AQ48: No | AR48: Yes | AS48: No | AT48: Yes | AU48: Yes | AV48: Yes | AW48: Yes | AX48: No | AY48: Yes
A49: slotting_lia_delete | B49: No | D49: No longer Applicable | E49: Disabled | L49: Yes | M49: No | N49: Yes | O49: Yes | P49: No | Q49: Yes | R49: No | S49: Yes | T49: Yes | U49: Yes | V49: Yes | W49: Yes | X49: Yes | Y49: No | Z49: Yes | AA49: Yes | AB49: Yes | AC49: Yes | AD49: No | AE49: No | AF49: Yes | AG49: Yes | AH49: Yes | AI49: Yes | AJ49: No | AK49: No | AL49: No | AM49: Yes | AN49: Yes | AO49: Yes | AP49: Yes | AQ49: No | AR49: Yes | AS49: No | AT49: No | AU49: Yes | AV49: Yes | AW49: Yes | AX49: No | AY49: Yes
A50: slotting_pk_delete | B50: No | D50: No longer Applicable | E50: Disabled | L50: Yes | M50: No | N50: Yes | O50: Yes | P50: No | Q50: Yes | R50: No | S50: Yes | T50: Yes | U50: Yes | V50: Yes | W50: Yes | X50: Yes | Y50: No | Z50: Yes | AA50: Yes | AB50: Yes | AC50: Yes | AD50: No | AE50: No | AF50: Yes | AG50: Yes | AH50: Yes | AI50: Yes | AJ50: No | AK50: No | AL50: No | AM50: Yes | AN50: Yes | AO50: Yes | AP50: Yes | AQ50: No | AR50: Yes | AS50: No | AT50: No | AU50: Yes | AV50: Yes | AW50: Yes | AX50: No | AY50: Yes
A51: soa_item_location | B51: Yes | C51: Item Location | D51: Imports Item Location into ERP | E51: See CRON Frequency Tab | F51: DB Query, Python | G51: N | J51: Verify if soa is still running, compare with item_loc | L51: Yes | M51: Yes | N51: Yes | O51: Yes | P51: No | Q51: Yes | R51: No | S51: Yes | T51: Yes | U51: Yes | V51: Yes | W51: Yes | X51: Yes | Y51: No | Z51: Yes | AA51: Yes | AB51: Yes | AC51: Yes | AD51: No | AE51: No | AF51: Yes | AG51: Yes | AH51: Yes | AI51: Yes | AJ51: No | AK51: No | AL51: No | AM51: Yes | AN51: Yes | AO51: Yes | AP51: Yes | AQ51: No | AR51: No | AS51: No | AT51: No | AU51: Yes | AV51: Yes | AW51: Yes | AX51: No | AY51: Yes
A52: token | B52: Yes | C52: Token | D52: Script to get Auth Token for all sites | E52: 8*** | F52: API | G52: N | H52: All Tools | L52: Yes | M52: Yes | N52: Yes | O52: Yes | P52: Yes | Q52: Yes | R52: Yes | S52: Yes | T52: Yes | U52: Yes | V52: Yes | W52: Yes | X52: Yes | Y52: No | Z52: Yes | AA52: Yes | AB52: Yes | AC52: Yes | AD52: No | AE52: No | AF52: Yes | AG52: Yes | AH52: Yes | AI52: Yes | AJ52: No | AK52: No | AL52: No | AM52: Yes | AN52: Yes | AO52: Yes | AP52: Yes | AQ52: No | AR52: Yes | AS52: No | AT52: Yes | AU52: Yes | AV52: Yes | AW52: Yes | AX52: No | AY52: Yes
A53: tskdtls_comp_openpickpacktskdtls | B53: No | D53: No longer Applicable | E53: Disabled | J53: CRON Disabled for all sites | L53: Yes | M53: No | N53: Yes | O53: Yes | P53: No | Q53: Yes | R53: No | S53: Yes | T53: Yes | U53: Yes | V53: Yes | W53: Yes | X53: Yes | Y53: No | Z53: Yes | AA53: Yes | AB53: Yes | AC53: Yes | AD53: No | AE53: No | AF53: Yes | AG53: Yes | AH53: Yes | AI53: Yes | AJ53: No | AK53: No | AL53: No | AM53: Yes | AN53: Yes | AO53: Yes | AP53: Yes | AQ53: No | AR53: Yes | AS53: No | AT53: No | AU53: Yes | AV53: Yes | AW53: Yes | AX53: No | AY53: Yes
A54: user_task_group | B54: Yes | C54: User Task Group | D54: Imports user task pool eligibilities | E54: See CRON Frequency Tab | F54: API, Python, SQL | G54: N | H54: MAWM Scheduled Script Dashboard for API's | I54: 8 | J54: Line 56 - Needs to be absorbed into user creation tool | K54: Being Developed | L54: Yes | M54: Yes | N54: Yes | O54: Yes | P54: Yes | Q54: Yes | R54: Yes | S54: Yes | T54: Yes | U54: Yes | V54: Yes | W54: Yes | X54: Yes | Y54: No | Z54: Yes | AA54: Yes | AB54: Yes | AC54: Yes | AD54: No | AE54: No | AF54: Yes | AG54: Yes | AH54: Yes | AI54: Yes | AJ54: No | AK54: No | AL54: No | AM54: Yes | AN54: Yes | AO54: Yes | AP54: Yes | AQ54: No | AR54: Yes | AS54: No | AT54: Yes | AU54: Yes | AV54: Yes | AW54: Yes | AX54: No | AY54: Yes
A55: printing_failures | B55: Yes | C55: Printing Failures | D55: Looks at printing journal and fires off any errors that are seen in printing journal | E55: At Minute 15 | F55: API | G55: Y | H55: Alert | J55: Contact Jason Richter | L55: No | M55: No | N55: No | O55: No | P55: No | Q55: No | R55: No | S55: No | T55: No | U55: No | V55: No | W55: Yes | X55: No | Y55: No | Z55: No | AA55: No | AB55: No | AC55: No | AD55: No | AE55: No | AF55: No | AG55: No | AH55: No | AI55: No | AJ55: No | AK55: No | AL55: No | AM55: No | AN55: No | AO55: No | AP55: No | AQ55: No | AR55: No | AS55: No | AT55: No | AU55: No | AV55: No | AW55: No | AX55: No | AY55: No
A56: putaway_cc_missing_condition_code | B56: No | C56: Putaway Condition Codes Missing | D56: There was an issue with the IREC where it was off because there were condition | E56: When Parameter is incorrect | F56: API | G56: N | H56: Application Parameter Tools | K56: Deployed | L56: Yes | M56: Yes | N56: Yes | O56: Yes | P56: Yes | Q56: Yes | R56: Yes | S56: Yes | T56: Yes | U56: Yes | V56: Yes | W56: Yes | X56: Yes | Y56: Yes | Z56: Yes | AA56: Yes | AB56: Yes | AC56: Yes | AD56: Yes | AE56: Yes | AF56: Yes | AG56: Yes | AH56: Yes | AI56: Yes | AJ56: Yes | AK56: Yes | AL56: Yes | AM56: Yes | AN56: Yes | AO56: Yes | AP56: Yes | AQ56: Yes | AR56: Yes | AS56: Yes | AT56: Yes | AU56: Yes | AV56: Yes | AW56: Yes | AX56: Yes | AY56: Yes
A57: USERS W/ INCORRECT USER DEFAULT CONFIGURATION | B57: Yes | C57: See Final List number line 55 | G57: N | H57: Application Parameter Tools
A58: LIA Sync Application Parameter | B58: Yes | D58: Fires these two API's when it runs. - LocationCapacitySync - LocationItemAssignmentSync | G58: N | H58: MAWM Scheduled Script Dashboard for API's | I58: 9 | J58: Get with Sean on this one, he knows the details on how it is working.

Sheet AWS Splunk Alerts
A1: type | B1: title | C1: search | D1: description | E1: eai:acl.app | F1: eai:acl.owner | G1: next_scheduled_time | H1: updated | I1: Needed?
A2: alert | B2: ABQ - MAWM - Item Bulk Import Failure | C2: source="/splunk/manhattan_active/ABQ/item_bulk_import/item_bulk_import_check_status.csv" host="misssplunksh01.corp.rndc-usa.com" index="ymc_dev_wms" sourcetype="csv" "Item Bulk Import API Failed" | rename "Item Bulk Import API Status" as Status | table Status, _time | D2: ABQ - WM Active - Item Bulk Import Failure | E2: search | F2: scriptuser | H2: 2022-02-20T16:19:02-05:00 | I2: Already Covered
A3: alert | B3: ABQ - MAWM -Inventory Sync Schedule API Failed | C3: source="/splunk/manhattan_active/ABQ/inventory_sync_schedule/inventory_sync_schedule_check_status.csv" host="misssplunksh01.corp.rndc-usa.com" index="ymc_dev_wms" "Inventory sync schedule API Failed" |rename "Inventory sync schedule API Status" as Status | table Status, _time | D3: ABQ - WM Active -Inventory Sync Schedule Failed | E3: search | F3: scriptuser | H3: 2022-11-15T15:11:56-05:00 | I3: Already Covered
A4: alert | B4: ALL - MAWM - Component Health Check | C4: source="/splunk/manhattan_active/Apps/component_health_check/health_check_status.csv" host="misssplunksh01.corp.rndc-usa.com" index="ymc_dev_wms" |where Status != "UP" AND Status != "Status" AND Service_Name != "com-manh-cp-sorting" |dedup Service_Name, Status |rename Service_Name as "Service Name" |table "Service Name", Status | D4: ALL - MAWM - Component Health Check | E4: search | F4: scriptuser | H4: 2023-10-08T23:59:21-04:00 | I4: Not Needed
A5: alert | B5: ALL - MAWM - Loaded Shipments w/ no Ship Confirm > 30 Minutes | C5: | dbxquery query="SELECT S.ORG_ID, SHIP_STATUS.SHIPMENT_ID , S.UPDATED_TIMESTAMP AS SHIPMENT_UPDATED, CONCAT(SHIP_STATUS.MIN_STATUS,'-',OLPN_STAT.DESCRIPTION) MIN_OLPN_STATUS, MAX_TIME AS OLPN_UPDATED FROM ( SELECT OLPN.ORG_ID, OLPN.SHIPMENT_ID, min(OLPN.STATUS) MIN_STATUS, MAX(UPDATED_TIMESTAMP) MAX_TIME FROM ( SELECT OLPN.ORG_ID, OLPN.OLPN_ID, OLPN.LPN_TYPE, OLPN.STATUS, CONCAT(OLPN.STATUS,'-',OLPN_STAT.DESCRIPTION) OLPN_STATUS ,OLPN.ORDER_ID, OLPN.ORDER_TYPE, ORDER_PLANNING_RUN_ID, OLPN.UPDATED_BY, OLPN.PICK_LOCATION_ID, OLPN.SHIPMENT_ID, OLPN.UPDATED_TIMESTAMP FROM default_pickpack.PPK_OLPN OLPN LEFT JOIN default_pickpack.PPK_OLPN_STATUS OLPN_STAT ON OLPN_STAT.OLPN_STATUS_ID = OLPN.STATUS ) OLPN GROUP BY OLPN.SHIPMENT_ID, OLPN.ORG_ID ORDER BY MIN_STATUS asc ) SHIP_STATUS LEFT JOIN default_shipment.SHP_SHIPMENT S ON S.SHIPMENT_ID = SHIP_STATUS.SHIPMENT_ID AND S.ORG_ID = SHIP_STATUS.ORG_ID LEFT JOIN default_pickpack.PPK_OLPN_STATUS OLPN_STAT ON OLPN_STAT.OLPN_STATUS_ID = SHIP_STATUS.MIN_STATUS WHERE 1=1 AND SHIP_STATUS.MIN_STATUS IN ('7900','7800') AND SHIP_STATUS.MAX_TIME <= NOW() - INTERVAL 30 MINUTE AND SHIP_STATUS.SHIPMENT_ID NOT IN (SELECT SHIPMENT_ID FROM default_shipconfirm.SHC_SHIP_CONFIRM_BATCH WHERE SHIPMENT_ID IS NOT NULL)" connection="MAPRD_NEW" | D5: ALL - MAWM - Loaded Shipments w/ no Ship Confirm > 30 Minutes | E5: search | F5: scriptuser | H5: 2023-09-13T10:27:31-04:00 | I5: Required
A6: alert | B6: ALL - MAWM - Locations with Null Max UOM Quantity | C6: | dbxquery query="SELECT DISTINCT LIA.ORG_ID, LOC.STORAGE_UOM_ID, TASK_MOVEMENT_ZONE_ID, LIA.LOCATION_ID, LIA.ASSIGNMENT_ID, LIA.MAX_UOM_QUANTITY, LIA.ITEM_ID, ITEM.DESCRIPTION FROM default_dcinventory.DCI_LOCATION_ITEM_ASSIGNMENT LIA LEFT JOIN default_dcinventory.DCI_LOCATION LOC ON LOC.LOCATION_ID = LIA.LOCATION_ID AND SUBSTR(LOC.PROFILE_ID,1,3) = LIA.ORG_ID LEFT JOIN default_dcinventory.ITL_ITEM ITEM ON ITEM.ITEM_ID = LIA.ITEM_ID AND ITEM.ORG_ID = LIA.ORG_ID WHERE 1=1 AND LIA.LOCATION_ID NOT LIKE '%DYBD%' AND LIA.LOCATION_ID <> 'DYB1' AND LIA.MAX_UOM_QUANTITY IS NULL Order by 1" connection="MAPRD_NEW" | D6: ALL - MAWM - Locations with Null Max UOM Quantity | E6: search | F6: scriptuser | H6: 2022-11-18T12:51:55-05:00 | I6: Required
A7: alert | B7: ALL - MAWM - Orders Stuck in Created Status > 10 Minutes | C7: | dbxquery query="SELECT OO.ORG_ID, OO.CREATED_TIMESTAMP, OO.BILLING_ACCOUNT_NUMBER, OO.ORIGINAL_ORDER_ID, OO.ORDER_TYPE, OO.MAXIMUM_STATUS, STATUS.DESCRIPTION, OO.CANCELLED, OO.BILL_TO_NAME, OO.EXT_ROUTE_ID, OO.EXT_SHIPMENT_STOP_NUMBER FROM default_dcorder.DCO_ORIGINAL_ORDER OO JOIN default_dcorder.DCO_ORDER_STATUS STATUS ON OO.MAXIMUM_STATUS = STATUS.ORDER_STATUS_ID WHERE 1=1 AND (OO.MAXIMUM_STATUS = '0000' or OO.MAXIMUM_STATUS = '0000') AND OO.CREATED_TIMESTAMP <= DATE_SUB(now(), INTERVAL '10' MINUTE); " connection="MAPRD_NEW" |rename ORG_ID as "Org ID", CREATED_TIMESTAMP AS "Created Timestamp", BILLING_ACCOUNT_NUMBER AS "Billing Acct #", ORIGINAL_ORDER_ID AS "Original Order ID", ORDER_TYPE AS "Order Type", MAXIMUM_STATUS AS "Maximum Status", DESCRIPTION AS "Description", CANCELLED AS "Cancelled", BILL_TO_NAME AS "Bill-to Name", EXT_ROUTE_ID AS "Ext Route ID", EXT_SHIPMENT_STOP_NUMBER AS "Ext Shipment Stop #" |table "Org ID", "Created Timestamp", "Billing Acct #", "Original Order ID", "Order Type", "Maximum Status", "Description", "Cancelled", "Bill-to Name", "Ext Route ID", "Ext Shipment Stop #" | D7: ALL - MAWM - Orders Stuck in Created Status > 10 Minutes | E7: search | F7: scriptuser | H7: 2023-09-13T11:15:11-04:00 | I7: Required
A8: alert | B8: ALL - MAWM - Pick Locations With Negative TBF | C8: | dbxquery query="SELECT org_id, location_id, item_id, on_hand, to_be_filled, allocated, updated_timestamp, INVENTORY_ID FROM default_dcinventory.DCI_INVENTORY WHERE to_be_filled < 0 ORDER BY org_id, item_id; " connection="MAPRD_NEW" | D8: ALL - MAWM - Pick Locations With Negative TBF | E8: search | F8: scriptuser | H8: 2023-08-07T08:46:39-04:00 | I8: Required
A9: alert | B9: ALL - MAWM - Splunk Alerts Summary | C9: |rest /servicesNS/-/-/saved/searches splunk_server=local |search (title = "*MAWM*" ) |table title, action.email.message.alert, action.email.to, action.email.cc, actions, cron_schedule, disabled, eai:acl.app, qualifiedSearch | E9: search | F9: scriptuser | H9: 2024-04-18T12:24:32-04:00 | I9: Required
A10: alert | B10: ALL - MAWM - iLPNs w/ Multiple Details of the Same Item | C10: | dbxquery query="select distinct INVN.ORG_ID, INVN.ILPN_ID AS ILPN, INVN.ITEM_ID, L.STATUS, LS.DESCRIPTION, INVN.LOCATION_ID CURRENT_LOC, B.TASK_ID AS LAST_TASK, B.UPDATED_TIMESTAMP, count(*) ILPN_DTL_COUNT from default_dcinventory.DCI_INVENTORY INVN LEFT JOIN (SELECT * FROM ( SELECT DISTINCT T.ORG_ID,TD.SOURCE_CONTAINER_ID LPN, T.TASK_ID, TD.UPDATED_TIMESTAMP, RANK() OVER(PARTITION BY SOURCE_CONTAINER_ID ORDER BY UPDATED_TIMESTAMP DESC) RNK FROM default_task.TSK_TASK T LEFT JOIN default_task.TSK_TASK_DETAIL TD ON T.TASK_ID = TD.TASK_ID AND T.ORG_ID = TD.ORG_ID AND SOURCE_CONTAINER_TYPE_ID = 'ILPN' AND SOURCE_CONTAINER_ID IS NOT NULL ) A WHERE LPN IS NOT NULL AND RNK = 1 ) B ON B.LPN = INVN.ILPN_ID AND INVN.ORG_ID = B.ORG_ID LEFT JOIN default_dcinventory.DCI_ILPN L ON L.ILPN_ID = INVN.ILPN_ID AND L.ORG_ID = INVN.ORG_ID LEFT JOIN default_dcinventory.DCI_ILPN_STATUS LS ON LS.ILPN_STATUS_ID = L.STATUS where 1=1 AND ABS(L.STATUS) < '9000' and INVN.inventory_container_type_id ='ILPN' and INVN.ON_HAND > 0 group by INVN.ORG_ID, INVN.ilpn_id, INVN.ITEM_ID, INVN.LOCATION_ID, L.STATUS, LS.DESCRIPTION ,B.TASK_ID, B.UPDATED_TIMESTAMP having count(*) > 1 order by 1; " connection="MAPRD_NEW" | rename ORG_ID AS "Org ID", ILPN AS "iLPN", ITEM_ID AS "Item ID", STATUS as "Status", DESCRIPTION AS "Description", CURRENT_LOC AS "Current Location", LAST_TASK AS "Last Task", UPDATED_TIMESTAMP AS "Updated Timestamp", ILPN_DTL_COUNT AS "iLPN Detail Count" | table "Org ID", "iLPN", "Item ID", Status, Description, "Current Location", "Last Task", "Updated Timestamp", "iLPN Detail Count" | D10: ALL - MAWM - iLPNs w/ Multiple Details of the Same Item | E10: search | F10: scriptuser | H10: 2022-11-18T12:58:30-05:00 | I10: Required
A11: alert | B11: ALL - WM Active - Component Health Check | C11: source="/splunk/manhattan_active/Apps/component_health_check/health_check_status.csv" host="misssplunksh01.corp.rndc-usa.com" index="ymc_dev_wms" |where Status != "UP" AND Status != "Status" AND Service_Name != "com-manh-cp-sorting" |dedup Service_Name, Status |rename Service_Name as "Service Name" |table "Service Name", Status | D11: ALL - WM Active - Component Health Check | E11: search | F11: scriptuser | H11: 2022-02-14T13:50:25-05:00 | I11: Not Needed
A12: alert | B12: Auburn-Multiple Stops on Same Shipment for the same Customer | C12: | dbxquery query="SELECT O.DO_STATUS, S.TC_SHIPMENT_ID, STOP.SHIPMENT_ID, STOP.STOP_LOCATION_NAME, STOP.FACILITY_ID, COUNT(DISTINCT STOP.STOP_SEQ) AS \"STOP COUNT\" FROM WMSAUB.STOP JOIN WMSAUB.ORDERS O ON O.SHIPMENT_ID = STOP.SHIPMENT_ID AND O.D_FACILITY_ID = STOP.FACILITY_ID JOIN WMSAUB.SHIPMENT S ON S.SHIPMENT_ID = STOP.SHIPMENT_ID WHERE O.DO_STATUS <= '130' GROUP BY O.DO_STATUS, S.TC_SHIPMENT_ID, STOP.SHIPMENT_ID, STOP.STOP_LOCATION_NAME, STOP.FACILITY_ID HAVING COUNT(DISTINCT STOP.STOP_SEQ) > 1 " connection="YMC_AUB_PROD" | D12: YMC-Auburn-Multiple Stops on Same Shipment for the same Customer | E12: search | F12: scriptuser | H12: 2022-01-19T13:35:20-05:00 | I12: Required
A13: alert | B13: Chino-Multiple Stops on Same Shipment for the same Customer | C13: | dbxquery query="SELECT O.DO_STATUS, S.TC_SHIPMENT_ID, STOP.SHIPMENT_ID, STOP.STOP_LOCATION_NAME, STOP.FACILITY_ID, COUNT(DISTINCT STOP.STOP_SEQ) AS \"STOP COUNT\" FROM WMSCHI.STOP JOIN WMSCHI.ORDERS O ON O.SHIPMENT_ID = STOP.SHIPMENT_ID AND O.D_FACILITY_ID = STOP.FACILITY_ID JOIN WMSCHI.SHIPMENT S ON S.SHIPMENT_ID = STOP.SHIPMENT_ID WHERE O.DO_STATUS <= '130' GROUP BY O.DO_STATUS, S.TC_SHIPMENT_ID, STOP.SHIPMENT_ID, STOP.STOP_LOCATION_NAME, STOP.FACILITY_ID HAVING COUNT(DISTINCT STOP.STOP_SEQ) > 1 " connection="YMC_PROD" | D13: YMC-Chino-Multiple Stops on Same Shipment for the same Customer | E13: search | F13: scriptuser | H13: 2022-02-07T17:58:35-05:00 | I13: Not Needed
A14: alert | B14: DEN - MAWM - Item Bulk Import Failure | C14: source="/splunk/manhattan_active/DEN/item_bulk_import/item_bulk_import_check_status.csv" host="misssplunksh01.corp.rndc-usa.com" index="ymc_dev_wms" sourcetype="csv" "Item Bulk Import API Failed" | rename "Item Bulk Import API Status" as Status | table Status, _time | D14: DEN - WM Active - Item Bulk Import Failure | E14: search | F14: scriptuser | H14: 2022-11-15T17:14:40-05:00 | I14: Already Covered
A15: alert | B15: DEN - MAWM - Standard Orders w/ No Designated Shipments Created | C15: | dbxquery query="SELECT O.ORG_ID, O.ORIGINAL_ORDER_ID AS \"ORDER\", O.ORDER_TYPE ,CONCAT(O.MAXIMUM_STATUS,'-',MAX_STAT.DESCRIPTION) MAX_STATUS ,CONCAT(O.MINIMUM_STATUS,'-',MIN_STAT.DESCRIPTION) MIN_STATUS , O.DESIGNATED_SHIPMENT_ID SHIPMENT, O.CREATED_TIMESTAMP FROM default_dcorder.DCO_ORIGINAL_ORDER O LEFT JOIN default_dcorder.DCO_ORDER_STATUS MAX_STAT ON MAX_STAT.ORDER_STATUS_ID = O.MAXIMUM_STATUS LEFT JOIN default_dcorder.DCO_ORDER_STATUS MIN_STAT ON MIN_STAT.ORDER_STATUS_ID = O.MAXIMUM_STATUS WHERE 1=1 AND O.ORG_ID = 'DEN' AND O.ORDER_TYPE = 'Standard' AND O.MINIMUM_STATUS < '8000' AND O.CREATED_TIMESTAMP <= NOW() - INTERVAL 15 MINUTE AND O.DESIGNATED_SHIPMENT_ID NOT IN (SELECT DISTINCT SHIPMENT_ID FROM default_shipment.SHP_SHIPMENT S WHERE S.ORG_ID = O.ORG_ID)" connection="MAPRD_NEW" | D15: DEN - MAWM - Standard Orders w/ No Designated Shipments Created | E15: search | F15: scriptuser | H15: 2023-01-13T11:41:28-05:00 | I15: Required
A16: alert | B16: DEN - MAWM - Users Missing User Default Configuration | C16: | dbxquery query="SELECT DEFAULT_ORGANIZATION, USER_ID FROM default_organization.ORG_USER_DEFAULTS WHERE USER_ID NOT IN (SELECT USER_ID FROM default_task.TSK_USER_DEFAULTS) AND SUBSTR(USER_ID,1,3) = DEFAULT_ORGANIZATION AND DEFAULT_ORGANIZATION = 'DEN' " connection="MAPRD_NEW" | D16: DEN - MAWM - Users Missing User Default Configuration | E16: search | F16: scriptuser | H16: 2023-06-16T12:14:17-04:00 | I16: Required
A17: alert | B17: DEN - MAWM - Users w/ Incorrect User Default Configuration | C17: | dbxquery query="SELECT SUBSTR(PROFILE_ID, 1, 3) ORG_ID, USER_ID, TASK_GROUP_DEFAULT_BEHAVIOR_ID FROM default_task.TSK_USER_DEFAULTS WHERE SUBSTR(PROFILE_ID,1,3) = 'DEN' AND ((task_group_default_behavior_id <> 'Select' AND task_group_default_behavior_id <> 'None') OR (task_group_id is null AND task_group_default_behavior_id = 'None')); " connection="MAPRD_NEW" | D17: DEN - MAWM - Users w/ Incorrect User Default Configuration | E17: search | F17: scriptuser | H17: 2023-06-16T12:14:32-04:00 | I17: Required
A18: alert | B18: DEN - MAWM Active -Inventory Sync Schedule API Failed | C18: source="/splunk/manhattan_active/DEN/inventory_sync_schedule/inventory_sync_schedule_check_status.csv" host="misssplunksh01.corp.rndc-usa.com" index="ymc_dev_wms" "Inventory sync schedule API Failed" |rename "Inventory sync schedule API Status" as Status | table Status, _time | D18: DEN - MAWM -Inventory Sync Schedule Failed | E18: search | F18: scriptuser | H18: 2022-11-15T17:31:52-05:00 | I18: Already Covered
A19: alert | B19: DEN - WM Active - Item Bulk Import Failure | C19: source="/splunk/manhattan_active/DEN/item_bulk_import/item_bulk_import_check_status.csv" host="misssplunksh01.corp.rndc-usa.com" index="ymc_dev_wms" sourcetype="csv" "Item Bulk Import API Failed" | rename "Item Bulk Import API Status" as Status | table Status, _time | D19: DEN - WM Active - Item Bulk Import Failure | E19: search | F19: scriptuser | H19: 2022-02-16T14:34:12-05:00 | I19: Already Covered
A20: alert | B20: DEN - WM Active -Inventory Sync Schedule API Failed | C20: source="/splunk/manhattan_active/DEN/inventory_sync_schedule/inventory_sync_schedule_check_status.csv" host="misssplunksh01.corp.rndc-usa.com" index="ymc_dev_wms" "Inventory sync schedule API Failed" |rename "Inventory sync schedule API Status" as Status | table Status, _time | D20: DEN - WM Active -Inventory Sync Schedule Failed | E20: search | F20: scriptuser | H20: 2022-02-16T16:34:56-05:00 | I20: Already Covered
A21: alert | B21: DFB - MAWM - Routed Orders Cancelled | C21: | dbxquery query="SELECT O.ORG_ID, O.ORIGINAL_ORDER_ID AS \"ORDER\", ORDER_TYPE, O.BILLING_ACCOUNT_NUMBER, O.BILL_TO_NAME AS CUSTOMER , CONCAT(O.MAXIMUM_STATUS,'-',DS.DESCRIPTION) ORDER_STATUS, OLI.ORIGINAL_ORDER_PLANNING_RUN_ID , OLI.ITEM_ID SKU, OLI.DESCRIPTION SKU_DESCRIPTION , O.UPDATED_TIMESTAMP, O.UPDATED_BY FROM default_dcorder.DCO_ORIGINAL_ORDER O LEFT JOIN default_dcorder.DCO_ORDER_STATUS DS ON DS.ORDER_STATUS_ID = O.MAXIMUM_STATUS LEFT JOIN default_dcorder.DCO_ORDER_LINE OLI ON OLI.ORIGINAL_ORDER_ID = O.ORIGINAL_ORDER_ID AND O.ORG_ID = OLI.ORG_ID WHERE 1=1 AND O.ORG_ID = 'DFB' AND UPPER(O.ORDER_TYPE) = 'STANDARD' AND O.MAXIMUM_STATUS = '9000' AND O.UPDATED_TIMESTAMP >= NOW() - INTERVAL 1 DAY" connection="MAPRD_NEW" | D21: DFB - MAWM - Routed Orders Cancelled | E21: search | F21: scriptuser | H21: 2024-12-29T09:28:55-05:00 | I21: Required
A22: alert | B22: EDI - EMS_Data_17222 not running on ediprd05 | C22: sourcetype="ps" host="misediprd05*" "EMS_Data_17222" | stats count(PID) as ProcessCounts | where ProcessCounts = 0 | E22: search | F22: admin | H22: 2022-02-10T12:04:10-05:00 | I22: ?
A23: alert | B23: EDI - FTP Confirmation Count New | C23: index=tibco host="misediprd02.corp.rndc-usa.com" OR host="misediprd03.corp.rndc-usa.com" "/shBC/bc/backup/x12/Out/FINTECH/*" "EDI Document has been sent to the Trading Partner successfully" "<ns0:statusCode>226</ns0:statusCode>" | stats count, list(field1) by _time | where count > 0 | rename list(field1) as "File Information" | rex field="File Information" "\<ns0\:transactionID\>(?<TranID>.*)\<\/ns0\:transactionID" | D23: FTP Transaction count | E23: search | F23: admin | H23: 2022-02-21T10:59:02-05:00 | I23: ?
A24: alert | B24: Email Test | C24: index="_internal" | table _raw | head | E24: search | F24: scriptuser | H24: 2023-06-17T09:33:58-04:00 | I24: ?
A25: alert | B25: Email test Alert | C25: index="_internal" source="/splunk/var/log/splunk/metrics.log" | table _raw | head 5 | E25: search | F25: scriptuser | H25: 2022-05-17T14:54:16-04:00 | I25: ?
A26: alert | B26: LAF - MAWM -Inventory Sync Schedule API Failed | C26: source="/splunk/manhattan_active/LAF/inventory_sync_schedule/inventory_sync_schedule_check_status.csv" host="misssplunksh01.corp.rndc-usa.com" index="ymc_dev_wms" "Inventory sync schedule API Failed" |rename "Inventory sync schedule API Status" as Status | table Status, _time | D26: LAF - WM Active -Inventory Sync Schedule Failed | E26: search | F26: scriptuser | H26: 2022-11-16T18:27:30-05:00 | I26: Already Covered
A27: alert | B27: LAF - MAWM- Item Bulk Import Failure | C27: source="/splunk/manhattan_active/LAF/item_bulk_import/item_bulk_import_check_status.csv" host="misssplunksh01.corp.rndc-usa.com" index="ymc_dev_wms" sourcetype="csv" "Item Bulk Import API Failed" | rename "Item Bulk Import API Status" as Status | table Status, _time | D27: LAF - MAWM - Item Bulk Import Failure | E27: search | F27: scriptuser | H27: 2022-11-16T18:28:28-05:00 | I27: Already Covered
A28: alert | B28: LAF - WM Active - Item Bulk Import Failure | C28: source="/splunk/manhattan_active/LAF/item_bulk_import/item_bulk_import_check_status.csv" host="misssplunksh01.corp.rndc-usa.com" index="ymc_dev_wms" sourcetype="csv" "Item Bulk Import API Failed" | rename "Item Bulk Import API Status" as Status | table Status, _time | D28: LAF - WM Active - Item Bulk Import Failure | E28: search | F28: scriptuser | H28: 2022-02-16T16:37:48-05:00 | I28: Already Covered
A29: alert | B29: LAF - WM Active -Inventory Sync Schedule API Failed | C29: source="/splunk/manhattan_active/LAF/inventory_sync_schedule/inventory_sync_schedule_check_status.csv" host="misssplunksh01.corp.rndc-usa.com" index="ymc_dev_wms" "Inventory sync schedule API Failed" |rename "Inventory sync schedule API Status" as Status | table Status, _time | D29: LAF - WM Active -Inventory Sync Schedule Failed | E29: search | F29: scriptuser | H29: 2022-02-15T00:43:18-05:00 | I29: Already Covered
A30: alert | B30: LM - TAM - Travel Aisle Missing from System Codes | C30: | dbxquery query="select distinct lh.travel_aisle \"Travel Aisle\" from locn_hdr lh left join sys_code sc on sc.code_id = lh.travel_aisle where sc.code_type = '844' and sc.code_id is null order by travel_aisle" connection="TAM_WM13" | E30: search | F30: scriptuser | H30: 2022-04-12T09:28:06-04:00 | I30: Required
A31: alert | B31: MGH - MISSING WM_INVENTORY RECORD | C31: | dbxquery query="SELECT PLD.PICK_LOCN_DTL_ID, LH.DSP_LOCN, IC.ITEM_NAME, PLD.INVN_TYPE FROM WMSMGH.PICK_LOCN_DTL PLD LEFT JOIN WMSMGH.LOCN_HDR LH ON LH.LOCN_ID = PLD.LOCN_ID LEFT JOIN WMSMGH.ITEM_CBO IC ON IC.ITEM_ID = PLD.ITEM_ID LEFT JOIN WMSMGH.WM_INVENTORY WI ON WI.LOCATION_ID = PLD.LOCN_ID AND WI.ITEM_ID = PLD.ITEM_ID AND WI.INVENTORY_TYPE = PLD.INVN_TYPE WHERE WI.WM_INVENTORY_ID IS NULL AND PLD.LAST_WAVE_NBR NOT IN ( SELECT MAX(SHIP_WAVE_NBR) FROM WMSMGH.SHIP_WAVE_PARM ) " connection="YMC_PROD" | D31: MGH - MISSING WM_INVENTORY RECORD | E31: search | F31: scriptuser | H31: 2020-10-02T17:29:07-04:00 | I31: Not Needed
A32: alert | B32: Manhattan Active - Component Health Check | C32: source="/splunk/manhattan_active/Apps/component_health_check/health_check_status.csv" host="misssplunksh01.corp.rndc-usa.com" index="ymc_dev_wms" |where Status != "UP" AND Status != "Status" |dedup Service_Name, Status |rename Service_Name as "Service Name" |table "Service Name", Status | E32: search | F32: scriptuser | H32: 2021-10-20T13:13:03-04:00 | I32: Not Needed
A33: alert | B33: Manhattan Active - Static Route Missing Threshold Value | C33: | dbxquery query="SELECT SUBSTR(PROFILE_ID, 1, 3) WHSE, STATIC_ROUTE_ID, EXT_THRESHOLD THRESHOLD_VALUE FROM default_routing.RTG_STATIC_ROUTE WHERE EXT_THRESHOLD IS NULL " connection="MAPRD_NEW" | E33: search | F33: scriptuser | H33: 2021-10-13T14:04:08-04:00 | I33: Required
A34: alert | B34: Manhattan Active - Static Route UI Missing DFLT Value | C34: |inputlookup MANH_Active_Lookup.csv |map maxsearches=100 search="| dbxquery query=\" SELECT * FROM ( SELECT \"'$WAREHOUSE$'\" AS WHSE, CASE WHEN COUNT(*) = '0' THEN 'MISSING DFLT STATIC ROUTE VALUE' ELSE 'OK' END AS STATUS FROM ( SELECT STATIC_ROUTE_ID, PROFILE_ID FROM default_routing.RTG_STATIC_ROUTE WHERE STATIC_ROUTE_ID = 'DFLT' AND PROFILE_ID = \"'$PROFILE_ID$'\" ) A ) B WHERE STATUS <> 'OK' \" connection=$CONNECTION$ shortnames=true" |rename WHSE as Warehouse, STATUS as Status |table Warehouse, Status | D34: Static Route UI missing default value | E34: search | F34: scriptuser | H34: 2021-10-07T11:02:36-04:00 | I34: Required
A35: alert | B35: Manhattan Active NEW - Locations with item assignments but 0 inventory | C35: | dbxquery query="/*Temporary Reserve Locations WITH assignments but no inventory*/SELECT ASSIGN.LOCATION_ID, ASSIGN.ITEM_ID, ASSIGN.ASSIGNMENT_ID FROM default_dcinventory.DCI_LOCATION_ITEM_ASSIGNMENT ASSIGN LEFT JOIN default_dcinventory.DCI_LOCATION LOC ON LOC.LOCATION_ID = ASSIGN.LOCATION_ID WHERE ASSIGN.LOCATION_ID NOT IN (SELECT DISTINCT INVN1.LOCATION_ID FROM default_dcinventory.DCI_INVENTORY INVN1 WHERE INVN1.LOCATION_ID IS NOT NULL) AND ASSIGN.LOCATION_ID NOT IN (SELECT DISTINCT INVN2.INVENTORY_CONTAINER_ID FROM default_dcinventory.DCI_INVENTORY INVN2 WHERE INVN2.INVENTORY_CONTAINER_TYPE_ID = 'LOCATION') AND LOC.STORAGE_UOM_ID = 'LPN' AND LOC.SKU_DEDICATION_TYPE_ID = 'TEMPORARY' AND LOC.LOCATION_TYPE_ID = 'STORAGE' ; " connection="MAPRD_NEW" | E35: search | F35: scriptuser | H35: 2021-10-13T19:09:27-04:00 | I35: Required
A36: alert | B36: Manhattan Active: ABQ - Endpoint Queue Failures | C36: source="/splunk/manhattan_active/ABQ/failure_count/message_failure_count_list.csv" host="misssplunksh01.corp.rndc-usa.com" index="ymc_dev_wms" sourcetype="msg_csv" NOT AU06CancelCartonDestinationEndpoint NOT EndpointId NOT AU06CancelCartonEndpoint NOT EX59_RouteStopDownload | rename Endpoint_Name as Name, Error_Count as Count | where Count > 100 | table Name Count | E36: search | F36: scriptuser | H36: 2022-02-20T16:18:12-05:00 | I36: Required
A37: alert | B37: Manhattan Active: ABQ - Location Rebuild Failure | C37: source="/splunk/manhattan_active/ABQ/location_rebuild/location_rebuild_check_status.csv" host="misssplunksh01.corp.rndc-usa.com" index="ymc_dev_wms" "Location Rebuild API Failed" | rename "Location Rebuild API Status" as Status | table Status, _time | D37: Manhattan Active: ABQ - Location Rebuild Failure | E37: search | F37: scriptuser | H37: 2022-02-20T16:19:23-05:00 | I37: Required
A38: alert | B38: Manhattan Active: DEN - Endpoint Queue Failures | C38: source="/splunk/manhattan_active/DEN/failure_count/message_failure_count_list.csv" host="misssplunksh01.corp.rndc-usa.com" index="ymc_dev_wms" sourcetype="msg_csv" NOT AU06CancelCartonDestinationEndpoint NOT EndpointId NOT AU06CancelCartonEndpoint NOT EX59_RouteStopDownload | rename Endpoint_Name as Name, Error_Count as Count | where Count > 100 | table Name Count | E38: search | F38: scriptuser | H38: 2022-02-06T12:52:00-05:00 | I38: Required
A39: alert | B39: Manhattan Active: DEN - Location Rebuild Failure | C39: source="/splunk/manhattan_active/DEN/location_rebuild/location_rebuild_check_status.csv" host="misssplunksh01.corp.rndc-usa.com" index="ymc_dev_wms" "Location Rebuild API Failed" | rename "Location Rebuild API Status" as Status | table Status, _time | D39: Manhattan Active: DEN - Location Rebuild Failure | E39: search | F39: scriptuser | H39: 2022-02-05T11:02:22-05:00 | I39: Required
A40: alert | B40: Manhattan Active: LAF - Endpoint Queue Failures | C40: source="/splunk/manhattan_active/LAF/failure_count/message_failure_count_list.csv" host="misssplunksh01.corp.rndc-usa.com" index="ymc_dev_wms" sourcetype="msg_csv" NOT AU06CancelCartonDestinationEndpoint NOT EndpointId NOT AU06CancelCartonEndpoint NOT EX59_RouteStopDownload | rename Endpoint_Name as Name, Error_Count as Count | where Count > 100 | table Name Count | E40: search | F40: scriptuser | H40: 2021-10-15T20:32:40-04:00 | I40: Required
A41: alert | B41: Manhattan Active: LAF - Location Rebuild Failure | C41: source="/splunk/manhattan_active/LAF/location_rebuild/location_rebuild_check_status.csv" host="misssplunksh01.corp.rndc-usa.com" index="ymc_dev_wms" "Location Rebuild API Failed" | rename "Location Rebuild API Status" as Status | table Status, _time | D41: Manhattan Active: LAF - Location Rebuild Failure | E41: search | F41: scriptuser | H41: 2021-10-19T15:42:54-04:00 | I41: Required
A42: alert | B42: Manhattan Active: NEW - Component Health Check | C42: source="/splunk/manhattan_active/Apps/component_health_check/health_check_status.csv" host="misssplunksh01.corp.rndc-usa.com" index="ymc_dev_wms" |where Status != "UP" AND Status != "Status" |dedup Service_Name, Status |rename Service_Name as "Service Name" |table "Service Name", Status | E42: search | F42: scriptuser | H42: 2021-10-12T19:18:13-04:00 | I42: Not Needed
A43: alert | B43: Manhattan Active: NEW - Endpoint Queue Failures | C43: source="/splunk/manhattan_active/Apps/failure_count/message_failure_count_list.csv" host="misssplunksh01.corp.rndc-usa.com" index="ymc_dev_wms" sourcetype="msg_csv" NOT AU06CancelCartonDestinationEndpoint NOT EndpointId NOT AU06CancelCartonEndpoint NOT EX59_RouteStopDownload | rename Endpoint_Name as Name, Error_Count as Count | where Count > 100 | table Name Count | E43: search | F43: scriptuser | H43: 2021-10-15T20:31:05-04:00 | I43: Required
A44: alert | B44: Manhattan Active: NEW - Health Check | C44: source="/splunk/manhattan_active/Apps/health_check/health_check_status.csv" host="misssplunksh01.corp.rndc-usa.com" index="ymc_dev_wms" | where DiscoveryClient != "DiscoveryClient" | where DiscoveryClient != "UP" or Eureka != "UP" or DiskSpace != "UP" or Db != "UP" or Elasticsearch != "UP" |table DiscoveryClient,Eureka,DiskSpace,Db,Elasticsearch | head 1 | E44: search | F44: scriptuser | H44: 2021-10-06T17:35:21-04:00 | I44: ?
A45: alert | B45: Manhattan Active: NEW - Location Rebuild Failure | C45: source="/splunk/manhattan_active/Apps/location_rebuild/location_rebuild_check_status.csv" host="misssplunksh01.corp.rndc-usa.com" index="ymc_dev_wms" "Location Rebuild API Failed" | rename "Location Rebuild API Status" as Status | table Status, _time | D45: Manhattan Active: NEW - Location Rebuild Failure | E45: search | F45: scriptuser | H45: 2021-10-19T16:01:44-04:00 | I45: Required
A46: alert | B46: Morgan hill-Multiple Stops on Same Shipment for the same Customer | C46: | dbxquery query="SELECT O.DO_STATUS, S.TC_SHIPMENT_ID, STOP.SHIPMENT_ID, STOP.STOP_LOCATION_NAME, STOP.FACILITY_ID, COUNT(DISTINCT STOP.STOP_SEQ) AS \"STOP COUNT\" FROM WMSMGH.STOP JOIN WMSMGH.ORDERS O ON O.SHIPMENT_ID = STOP.SHIPMENT_ID AND O.D_FACILITY_ID = STOP.FACILITY_ID JOIN WMSMGH.SHIPMENT S ON S.SHIPMENT_ID = STOP.SHIPMENT_ID WHERE O.DO_STATUS <= '130' GROUP BY O.DO_STATUS, S.TC_SHIPMENT_ID, STOP.SHIPMENT_ID, STOP.STOP_LOCATION_NAME, STOP.FACILITY_ID HAVING COUNT(DISTINCT STOP.STOP_SEQ) > 1 " connection="YMC_PROD" | D46: YMC-Morgan hill-Multiple Stops on Same Shipment for the same Customer | E46: search | F46: scriptuser | H46: 2021-08-19T14:21:26-04:00 | I46: Not Needed
A47: alert | B47: NEW - MAWM - Item Bulk Import Failure | C47: source="/splunk/manhattan_active/Apps/item_bulk_import/item_bulk_import_check_status.csv" host="misssplunksh01.corp.rndc-usa.com" index="ymc_dev_wms" sourcetype="csv" "Item Bulk Import API Failed" | rename "Item Bulk Import API Status" as Status | table Status, _time | D47: NEW - WM Active - Item Bulk Import Failure | E47: search | F47: scriptuser | H47: 2022-11-16T18:45:44-05:00 | I47: Already Covered
A48: alert | B48: NEW - MAWM -Inventory Sync Schedule API Failed | C48: source="/splunk/manhattan_active/Apps/inventory_sync_schedule/inventory_sync_schedule_check_status.csv" host="misssplunksh01.corp.rndc-usa.com" index="ymc_dev_wms" "Inventory sync schedule API Failed" |rename "Inventory sync schedule API Status" as Status | table Status, _time | D48: NEW - WM Active -Inventory Sync Schedule Failed | E48: search | F48: scriptuser | H48: 2022-11-16T18:57:07-05:00 | I48: Already Covered
A49: alert | B49: NEW - WM Active - Item Bulk Import Failure | C49: source="/splunk/manhattan_active/Apps/item_bulk_import/item_bulk_import_check_status.csv" host="misssplunksh01.corp.rndc-usa.com" index="ymc_dev_wms" sourcetype="csv" "Item Bulk Import API Failed" | rename "Item Bulk Import API Status" as Status | table Status, _time | D49: NEW - WM Active - Item Bulk Import Failure | E49: search | F49: scriptuser | H49: 2022-02-15T00:52:10-05:00 | I49: Already Covered
A50: alert | B50: NEW - WM Active -Inventory Sync Schedule API Failed | C50: source="/splunk/manhattan_active/Apps/inventory_sync_schedule/inventory_sync_schedule_check_status.csv" host="misssplunksh01.corp.rndc-usa.com" index="ymc_dev_wms" "Inventory sync schedule API Failed" |rename "Inventory sync schedule API Status" as Status | table Status, _time | D50: NEW - WM Active -Inventory Sync Schedule Failed | E50: search | F50: scriptuser | H50: 2022-02-15T01:05:51-05:00 | I50: Already Covered
A51: alert | B51: SORF - ABQ Depletion Inventory Report | C51: | loadjob savedsearch="admin:search:SORF - ABQ Depletion inventory" | search Percentage_Sold < 20 | E51: search | F51: admin | H51: 2022-02-18T17:16:44-05:00 | I51: ?
A52: alert | B52: SORF - ABQ Depletion Inventory Report Weekly | C52: | loadjob savedsearch="admin:search:SORF - ABQ Depletion inventory" | search Percentage_Sold < 20 | E52: search | F52: scriptuser | H52: 2022-02-18T17:17:28-05:00 | I52: ?
A53: alert | B53: SORF - ABQ Depletion inventory | C53: | dbxquery query="select pi.description, po.TC_PURCHASE_ORDERS_ID, pi.purchase_orders_id, pi.sku, pi.received_qty , pi.std_pack_qty, pi.orig_order_qty, pi.created_dttm, pi.last_updated_dttm from purchase_orders_line_item pi inner join purchase_orders po ON pi.PURCHASE_ORDERS_ID = po.PURCHASE_ORDERS_ID and pi.ref_field_3='SORF' and pi.created_dttm > sysdate - 60" connection=ABQ_WM13 shortnames=true maxrows=500000 | rename SKU AS PRODUCT_ID TC_PURCHASE_ORDERS_ID AS PO_NUMBER | fillnull value=0 RECEIVED_QTY | eval Received_QTY = RECEIVED_QTY / STD_PACK_QTY | eval Original_QTY = ORIG_ORDER_QTY / STD_PACK_QTY | fields - ORIG_ORDER_QTY, STD_PACK_QTY, PURCHASE_ORDERS_ID, RECEIVED_QTY | join PRODUCT_ID , PO_NUMBER max=500000 [| dbxquery query="select pi.sku , pi.last_updated_dttm,po.TC_PURCHASE_ORDERS_ID AS PO from purchase_orders_line_item pi inner join purchase_orders po ON pi.PURCHASE_ORDERS_ID = po.PURCHASE_ORDERS_ID and pi.ref_field_3='SORF' and pi.created_dttm > sysdate - 60 " connection=ABQ_WM13 shortnames=true maxrows=500000 | rename SKU AS PRODUCT_ID | eval RECEIVED_QTY = strftime(strptime(LAST_UPDATED_DTTM,"%Y-%m-%d %H:%M:%S"),"%d-%b-%y") |eval today=strftime(now(), "%d-%b-%y") | stats last(RECEIVED_QTY) AS "Received_Date" values(today) AS Today by PRODUCT_ID, PO | map maxsearches=1000 search="| dbxquery query=\"select sum(sales.CASES_SOLD) AS CASES_SOLD,product.PRODUCT_ID, product.description,d.SORFID,w2.USER_NAME AS Approver ,w.USER_NAME,d.sorf_cases,p.PO_NUMBER from DW_MAIN.sales sales INNER join DW_MAIN.product product on sales.prodid=product.prodid INNER join sorfdetail d on product.PRODUCT_ID=d.product_id and sales.house_id=d.house_id INNER JOIN sorfmain m ON m.sorfid=d.sorfid INNER JOIN webapps_owner.user_d w ON m.requested_by=w.user_id INNER JOIN webapps_owner.user_d w2 ON m.approved_by = w2.user_id INNER JOIN sorfpurch p ON m.sorfid=p.sorfid INNER JOIN DW_MAIN.house house ON house.house_id=d.house_id where house.house_desc='ABQ' and product.PRODUCT_ID=$PRODUCT_ID$ and p.PO_NUMBER=$PO$ and date_id between '$Received_Date$' and '$Today$' and m.requested_date > add_months(sysdate-60,-1) group by product.description ,product.PRODUCT_ID,d.SORFID,w.USER_NAME,w2.USER_NAME,d.sorf_cases,p.PO_NUMBER \" connection=DW_PROD shortnames=true "] | eval CASES_SOLD=round(CASES_SOLD,0) | eval CREATED_DTTM=strftime(strptime(CREATED_DTTM, "%Y-%m-%d %H:%M:%S"), "%m-%d-%Y") | eval LAST_UPDATED_DTTM=strftime(strptime(LAST_UPDATED_DTTM, "%Y-%m-%d %H:%M:%S"), "%m-%d-%Y") | stats values(APPROVER) AS Aprover, values(DESCRIPTION) AS Description , values(CREATED_DTTM) AS "Created date", values(LAST_UPDATED_DTTM) AS "Received Date", sum(SORF_CASES) AS "Cases Ordered", sum(Received_QTY) AS Cases_Received, sum(CASES_SOLD) AS Cases_Sold by PRODUCT_ID,USER_NAME,SORFID,PO_NUMBER | sort "Received Date" | rename PRODUCT_ID AS SKU, USER_NAME AS Request_Username | eval Percentage_Sold=round(Cases_Sold/Cases_Received*100,2) | E53: search | F53: admin | H53: 2022-02-18T17:17:44-05:00 | I53: ?
A54: alert | B54: SPLK - Metadata - POC | C54: | inputlookup WMS_ACTIVE_SCHEMAS.csv | table USERNAME | D54: SPLK - Metadata - POC | E54: search | F54: scriptuser | H54: 2023-05-03T11:31:02-04:00
A55: alert | B55: STAGE - ALL - MAWM - In Packing oLPNS > 5 Minutes | C55: | dbxquery query="SELECT ORG_ID, OLPN_ID, STATUS, ORDER_ID, ORDER_TYPE , ORDER_PLANNING_RUN_ID, SHIPMENT_ID, ORDER_PIPELINE_ID , UPDATED_BY , UPDATED_TIMESTAMP FROM default_pickpack.PPK_OLPN WHERE 1=1 AND STATUS = '7100' AND ORDER_TYPE = 'Standard' AND ORG_ID NOT IN ('NEWQA','NEWSDN') AND UPDATED_TIMESTAMP <= NOW() - INTERVAL 5 MINUTE" connection="MASTG_NEW" | D55: STAGE - ALL - MAWM - In Packing oLPNS > 5 Minutes | E55: search | F55: scriptuser | H55: 2024-02-19T10:43:31-05:00 | I55: Not Needed
A56: alert | B56: STAGE - ALL - MAWM - LPN Storage Locs with Inventory Not Tied to an LPN | C56: | dbxquery query="select DISTINCT INV.ORG_ID, LOC.LOCATION_ID, INV.ITEM_ID, INV.ON_HAND, INV.INVENTORY_ID, INV.CREATED_BY, INV.UPDATED_BY, INV.LAST_LOCATED_DATE_TIME, INV.PROCESS, INV.UPDATED_TIMESTAMP FROM default_dcinventory.DCI_LOCATION LOC LEFT JOIN default_dcinventory.DCI_INVENTORY INV on INV.LOCATION_ID = LOC.LOCATION_ID AND SUBSTR(LOC.PROFILE_ID,1,3) = INV.ORG_ID WHERE LOC.STORAGE_UOM_ID = 'LPN' AND (INV.INVENTORY_CONTAINER_TYPE_ID = 'LOCATION' AND INV.ON_HAND > 0) " connection="MASTG_NEW" |rename ORG_ID AS "ORG ID", LOCATION_ID AS "LOCATION ID", ITEM_ID AS "ITEM ID", ON_HAND AS "ON HAND", INVENTORY_ID AS "INVENTORY ID", CREATED_BY AS "CREATED BY", UPDATED_BY AS "UPDATED BY", LAST_LOCATED_DATE_TIME AS "LAST LOCATED DATE TIME", UPDATED_TIMESTAMP AS "UPDATED TIMESTAMP" |table "ORG ID", "LOCATION ID", "ITEM ID", "ON HAND", "INVENTORY ID", "CREATED BY", "UPDATED BY", "LAST LOCATED DATE TIME", PROCESS, "UPDATED TIMESTAMP" | D56: STAGE - ALL - MAWM - LPN Storage Locs with Inventory Not Tied to an LPN | E56: search | F56: scriptuser | H56: 2024-02-19T10:44:16-05:00 | I56: Not Needed
A57: alert | B57: STAGE - ALL - MAWM - Loaded Shipments w/ no Ship Confirm > 30 Minutes | C57: | dbxquery query="SELECT S.ORG_ID, SHIP_STATUS.SHIPMENT_ID , S.UPDATED_TIMESTAMP AS SHIPMENT_UPDATED, CONCAT(SHIP_STATUS.MIN_STATUS,'-',OLPN_STAT.DESCRIPTION) MIN_OLPN_STATUS, MAX_TIME AS OLPN_UPDATED FROM ( SELECT OLPN.ORG_ID, OLPN.SHIPMENT_ID, min(OLPN.STATUS) MIN_STATUS, MAX(UPDATED_TIMESTAMP) MAX_TIME FROM ( SELECT OLPN.ORG_ID, OLPN.OLPN_ID, OLPN.LPN_TYPE, OLPN.STATUS, CONCAT(OLPN.STATUS,'-',OLPN_STAT.DESCRIPTION) OLPN_STATUS ,OLPN.ORDER_ID, OLPN.ORDER_TYPE, ORDER_PLANNING_RUN_ID, OLPN.UPDATED_BY, OLPN.PICK_LOCATION_ID, OLPN.SHIPMENT_ID, OLPN.UPDATED_TIMESTAMP FROM default_pickpack.PPK_OLPN OLPN LEFT JOIN default_pickpack.PPK_OLPN_STATUS OLPN_STAT ON OLPN_STAT.OLPN_STATUS_ID = OLPN.STATUS ) OLPN GROUP BY OLPN.SHIPMENT_ID, OLPN.ORG_ID ORDER BY MIN_STATUS asc ) SHIP_STATUS LEFT JOIN default_shipment.SHP_SHIPMENT S ON S.SHIPMENT_ID = SHIP_STATUS.SHIPMENT_ID AND S.ORG_ID = SHIP_STATUS.ORG_ID LEFT JOIN default_pickpack.PPK_OLPN_STATUS OLPN_STAT ON OLPN_STAT.OLPN_STATUS_ID = SHIP_STATUS.MIN_STATUS WHERE 1=1 AND SHIP_STATUS.MIN_STATUS IN ('7900','7800') AND SHIP_STATUS.ORG_ID NOT IN ('NEWQA','NEWSDN') AND SHIP_STATUS.MAX_TIME <= NOW() - INTERVAL 30 MINUTE AND SHIP_STATUS.SHIPMENT_ID NOT IN (SELECT SHIPMENT_ID FROM default_shipconfirm.SHC_SHIP_CONFIRM_BATCH WHERE SHIPMENT_ID IS NOT NULL)" connection="MASTG_NEW" | D57: STAGE - ALL - MAWM - Loaded Shipments w/ no Ship Confirm > 30 Minutes | E57: search | F57: scriptuser | H57: 2023-09-13T10:36:09-04:00 | I57: Not Needed
A58: alert | B58: STAGE - ALL - MAWM - Loaded Shipments w/ no Ship Confirm > 6 hours | C58: | dbxquery query="SELECT S.ORG_ID, SHIP_STATUS.SHIPMENT_ID , S.UPDATED_TIMESTAMP AS SHIPMENT_UPDATED, CONCAT(SHIP_STATUS.MIN_STATUS,'-',OLPN_STAT.DESCRIPTION) MIN_OLPN_STATUS, MAX_TIME AS OLPN_UPDATED FROM ( SELECT OLPN.ORG_ID, OLPN.SHIPMENT_ID, min(OLPN.STATUS) MIN_STATUS, MAX(UPDATED_TIMESTAMP) MAX_TIME FROM ( SELECT OLPN.ORG_ID, OLPN.OLPN_ID, OLPN.LPN_TYPE, OLPN.STATUS, CONCAT(OLPN.STATUS,'-',OLPN_STAT.DESCRIPTION) OLPN_STATUS ,OLPN.ORDER_ID, OLPN.ORDER_TYPE, ORDER_PLANNING_RUN_ID, OLPN.UPDATED_BY, OLPN.PICK_LOCATION_ID, OLPN.SHIPMENT_ID, OLPN.UPDATED_TIMESTAMP FROM default_pickpack.PPK_OLPN OLPN LEFT JOIN default_pickpack.PPK_OLPN_STATUS OLPN_STAT ON OLPN_STAT.OLPN_STATUS_ID = OLPN.STATUS ) OLPN GROUP BY OLPN.SHIPMENT_ID, OLPN.ORG_ID ORDER BY MIN_STATUS asc ) SHIP_STATUS LEFT JOIN default_shipment.SHP_SHIPMENT S ON S.SHIPMENT_ID = SHIP_STATUS.SHIPMENT_ID AND S.ORG_ID = SHIP_STATUS.ORG_ID LEFT JOIN default_pickpack.PPK_OLPN_STATUS OLPN_STAT ON OLPN_STAT.OLPN_STATUS_ID = SHIP_STATUS.MIN_STATUS WHERE 1=1 AND SHIP_STATUS.MIN_STATUS IN ('7900','7800') AND SHIP_STATUS.ORG_ID NOT IN ('NEWQA','NEWSDN') AND SHIP_STATUS.MAX_TIME <= NOW() - INTERVAL 30 MINUTE AND SHIP_STATUS.SHIPMENT_ID NOT IN (SELECT SHIPMENT_ID FROM default_shipconfirm.SHC_SHIP_CONFIRM_BATCH WHERE SHIPMENT_ID IS NOT NULL)" connection="MASTG_NEW" | D58: STAGE - ALL - MAWM - Loaded Shipments w/ no Ship Confirm > 6 hours | E58: search | F58: scriptuser | H58: 2024-02-19T10:44:27-05:00 | I58: Not Needed
A59: alert | B59: STAGE - ALL - MAWM - PIX Specification Found > 1 Hour | C59: | dbxquery query="SELECT P.ORG_ID, P.PIX_SPECIFICATION_ID, PS.DESCRIPTION, P.PIX_EVENT_PAYLOAD_ID, P.UPDATED_TIMESTAMP, P.PK FROM default_pix.PIX_PIX_ENTRY P LEFT JOIN default_pix.PIX_PIX_STATUS PS ON PS.STATUS_ID = P.STATUS_ID WHERE P.STATUS_ID NOT IN ('9000', '8000') AND P.ORG_ID NOT IN ('NEWQA','NEWSDN','NEWDEV') AND P.UPDATED_TIMESTAMP < NOW() - INTERVAL 1 HOUR AND P.UPDATED_TIMESTAMP > NOW() - INTERVAL 1*24*365 HOUR ORDER BY P.UPDATED_TIMESTAMP DESC " connection="MASTG_NEW" | D59: STAGE - ALL - MAWM - PIX Specification Found > 1 Hour | E59: search | F59: scriptuser | H59: 2024-02-19T10:40:20-05:00 | I59: Not Needed
A60: alert | B60: STAGE - ALL - MAWM - Pallet LPNs w/ Inventory Records | C60: | dbxquery query="select INV.ORG_ID, L.STATUS, L.PARENT_LPN_ID as PALLET, INV.ON_HAND AS PLT_QTY, INV.ALLOCATED AS PLT_ALLOCATED_QTY ,INV.TO_BE_FILLED AS PLT_TBF, INV.LOCATION_ID AS PLT_LOCATION, L.ILPN_ID AS CHILD_LPN , INV.ITEM_ID from default_dcinventory.DCI_INVENTORY INV LEFT JOIN default_dcinventory.DCI_ILPN L ON L.PARENT_LPN_ID = INV.ILPN_ID AND L.ORG_ID = INV.ORG_ID where L.PARENT_LPN_ID IN (SELECT ILPN_ID FROM default_dcinventory.DCI_INVENTORY) AND INV.ORG_ID NOT IN ('NEWQA','NEWSDN') and L.PARENT_LPN_ID IN (SELECT ILPN_ID FROM default_dcinventory.DCI_ILPN where status not in ('9000','11000') );" connection="MASTG_NEW" | D60: STAGE - ALL - MAWM - Pallet LPNs w/ Inventory Records | E60: search | F60: scriptuser | H60: 2024-02-19T10:40:32-05:00 | I60: Not Needed
A61: alert | B61: STAGE - ALL - MAWM - Pick Locations With Negative TBF | C61: | dbxquery query="SELECT org_id, location_id, item_id, on_hand, to_be_filled, allocated, updated_timestamp, INVENTORY_ID FROM default_dcinventory.DCI_INVENTORY WHERE to_be_filled < 0 AND ORG_ID NOT IN ('NEWQA','NEWSDN') ORDER BY org_id, item_id; " connection="MASTG_NEW" | D61: STAGE - ALL - MAWM - Pick Locations With Negative TBF | E61: search | F61: scriptuser | H61: 2023-08-07T08:46:47-04:00 | I61: Not Needed
A62: alert | B62: STAGE - ALL - MAWM - Pick Locations With TBF Quantity and No Open Task Details | C62: | dbxquery query="select org_id, location_id, storage_uom_id, item_id, on_hand, to_be_filled, allocated, case when nolocqty is null then 0 else nolocqty end as nolocqty, ilpn_id from ( select org_id, location_id, storage_uom_id, item_id, on_hand, to_be_filled, allocated, case when nolocqty is null then 0 else nolocqty end as nolocqty, ilpn_id from ( select X.updated_timestamp, X.org_id,X.location_id,X.storage_uom_id,X.item_id,X.on_hand,X.to_be_filled,X.allocated, Y.NOLOCQTY, Y.PARENT_LPN_ID, Y.ILPN_ID From ( select dci.updated_timestamp, dci.org_id as org_id,dci.location_id as location_id,dl.storage_uom_id as storage_uom_id,dci.item_id as item_id,dci.on_hand as on_hand,dci.to_be_filled as to_be_filled,dci.allocated as allocated from default_dcinventory.DCI_INVENTORY dci join default_dcinventory.DCI_LOCATION dl on dci.org_id = substr(dl.profile_id,1,3) and dci.location_id = dl.location_id where dl.storage_uom_id in ('UNIT','PACK') AND dci.org_id NOT IN ('NEWQA','NEWSDN') and dci.to_be_filled > 0 and dci.location_id not in (select td.target_location_id from default_task.TSK_TASK_DETAIL td join default_dcinventory.DCI_LOCATION dl on td.org_id = substr(dl.profile_id,1,3) and td.target_location_id = dl.location_id where td.type_id in ('PUTAWAY','REPLENISHMENT', 'SLOTTING') and dl.storage_uom_id in ('UNIT','PACK') and td.status < 8000) ) as X left join (select DCI.ORG_ID as ORG_ID, DCI.ITEM_ID as ITEM_ID, DCI.LOCATION_ID as LCOATION_ID, sum(DCI.ON_HAND) as NOLOCQTY , LPN.parent_lpn_id, DCI.ILPN_ID from default_dcinventory.DCI_INVENTORY DCI join default_dcinventory.DCI_ILPN LPN on DCI.ilpn_id = LPN.ilpn_id and DCI.org_id = LPN.ORG_ID Where DCI.LOCATION_ID is null and DCI.INVENTORY_CONTAINER_TYPE_ID <> 'OLPN' and LPN.purchase_order_id is null AND DCI.org_id NOT IN ('NEWQA','NEWSDN') GROUP BY DCI.ORG_ID, DCI.ITEM_ID, DCI.LOCATION_ID, LPN.parent_lpn_id, DCI.ILPN_ID HAVING sum(DCI.ON_HAND) > 0) as Y on X.ORG_ID = Y.ORG_ID and X.ITEM_ID = Y.ITEM_ID)a)b where to_be_filled <> nolocqty order by org_id, ilpn_id;" connection="MASTG_NEW" | D62: STAGE - ALL - MAWM - Pick Locations With TBF Quantity and No Open Task Details | E62: search | F62: scriptuser | H62: 2024-02-19T10:40:02-05:00 | I62: Not Needed
A63: alert | B63: STAGE - ALL - MAWM - Putaway Task is Open but iLPN is Putaway | C63: | dbxquery query="SELECT TD.ORG_ID, TD.TASK_ID, CONCAT(TD.STATUS,'-',TDS.DESCRIPTION) TD_STAT , T.TRANSACTION_TYPE_ID , TD.SOURCE_CONTAINER_ID ILPN , TD.TARGET_CONTAINER_ID , TD.TARGET_CONTAINER_TYPE_ID , TD.TARGET_LOCATION_ID , ILPN.CURRENT_LOCATION_ID , UOM_TYPE_ID , TD.UPDATED_BY , TD.UPDATED_TIMESTAMP , TD.ALLOCATION_ID FROM default_task.TSK_TASK_DETAIL TD LEFT JOIN default_task.TSK_TASK T ON T.TASK_ID = TD.TASK_ID AND T.ORG_ID = TD.ORG_ID LEFT JOIN default_task.TSK_TASK_DETAIL_STATUS TDS ON TDS.TASK_DETAIL_STATUS_ID = TD.STATUS LEFT JOIN default_dcinventory.DCI_ILPN ILPN ON ILPN.ILPN_ID = TD.SOURCE_CONTAINER_ID AND ILPN.ORG_ID = TD.ORG_ID WHERE 1=1 AND T.TRANSACTION_TYPE_ID = 'Putaway' AND TD.STATUS < '8000' AND TD.ORG_ID NOT IN ('NEWQA','NEWSDN') AND ILPN.CURRENT_LOCATION_ID = TD.TARGET_LOCATION_ID ; " connection="MASTG_NEW" |rename ORG_ID AS "Org ID", TASK_ID AS "Task ID", TD_STAT AS "Task Detail Status", TRANSACTION_TYPE_ID AS "Transaction Type ID", ILPN AS "iLPN", TARGET_CONTAINER_ID AS "Target Container ID", TARGET_CONTAINER_TYPE_ID AS "Target Container Type ID", TARGET_LOCATION_ID AS "Target Location ID", CURRENT_LOCATION_ID AS "Current Location ID", UOM_TYPE_ID AS "UOM Type ID", UPDATED_BY AS "Updated By", UPDATED_TIMESTAMP AS "Updated Timestamp", ALLOCATION_ID AS "Allocation ID" | table "Org ID", "Task ID", "Task Detail Status", "Transaction Type ID", "iLPN", "Target Container ID", "Target Container Type ID", "Target Location ID", "Current Location ID", "UOM Type ID", "Updated By", "Updated Timestamp", "Allocation ID" | D63: STAGE - ALL - MAWM - Putaway Task is Open but iLPN is Putaway ***MSP TO CLEAN UP*** Note: Manhattan case 795138 is opened for this alert. Steps to clear: 1) Cancel the task from the Tasks UI. | E63: search | F63: scriptuser | H63: 2024-02-19T10:39:21-05:00 | I63: Not Needed
A64: alert | B64: STAGE - ALL - MAWM - Task Completed or Cancelled w/ Open Task Details | C64: | dbxquery query="SELECT T2.ORG_ID,T2.TASK_ID, T2.HDR_STAT TASK_HDR_STATUS, T2.TRANSACTION_ID, CONCAT(T2.MIN_TASK_DTL_STAT,'-',TDS.DESCRIPTION) MIN_TASK_DETAIL_STATUS, T2.UPDATED_TIMESTAMP, T2.TASK_DETAIL_ID FROM ( SELECT ORG_ID, TASK_ID, HDR_STAT, STATUS, TRANSACTION_ID, MIN(TASK_DETAIL_STATUS_ID) MIN_TASK_DTL_STAT, UPDATED_TIMESTAMP, TASK_DETAIL_ID FROM ( select TSK.ORG_ID , TSK.TASK_ID , TSK.STATUS , CONCAT(TSK.STATUS,'-',TS.DESCRIPTION) HDR_STAT , TSK.CURRENT_USER_ID , TSK.ASSIGNED_TASK_GROUP_ID , TSK.TRANSACTION_ID , TSK.TRANSACTION_TYPE_ID , TD.SEQUENCE , TDS.TASK_DETAIL_STATUS_ID , CONCAT(TD.STATUS,'-',TDS.DESCRIPTION) DTL_STAT , TD.SOURCE_CONTAINER_ID , TSK.UPDATED_TIMESTAMP , TD.TASK_DETAIL_ID from default_task.TSK_TASK TSK LEFT JOIN default_task.TSK_TASK_DETAIL TD ON TD.TASK_ID = TSK.TASK_ID AND TD.ORG_ID = TSK.ORG_ID LEFT JOIN default_task.TSK_TASK_STATUS TS ON TS.TASK_STATUS_ID = TSK.STATUS LEFT JOIN default_task.TSK_TASK_DETAIL_STATUS TDS ON TDS.TASK_DETAIL_STATUS_ID = TD.STATUS WHERE 1=1 ORDER BY TASK_ID, SEQUENCE ) T1 WHERE 1=1 AND STATUS >= '8000' and STATUS <> '8500' GROUP BY TASK_ID, ORG_ID, TRANSACTION_ID, STATUS, HDR_STAT, UPDATED_TIMESTAMP, TASK_DETAIL_ID ) T2 LEFT JOIN default_task.TSK_TASK_DETAIL_STATUS TDS ON TDS.TASK_DETAIL_STATUS_ID = T2.MIN_TASK_DTL_STAT WHERE MIN_TASK_DTL_STAT < '8000' AND T2.ORG_ID NOT IN ('NEWQA','NEWSDN') AND T2.UPDATED_TIMESTAMP < NOW() - INTERVAL 20 MINUTE ORDER BY 1; " connection="MASTG_NEW" | rename ORG_ID AS "Org ID", TASK_ID AS "Task ID", TASK_HDR_STATUS AS "Task Header Status", TRANSACTION_ID AS "Transaction ID", MIN_TASK_DETAIL_STATUS AS "Min Task Detail Status", UPDATED_TIMESTAMP AS "Updated Timestamp", TASK_DETAIL_ID AS "Task Detail ID" | table "Org ID", "Task ID", "Task Header Status", "Transaction ID", "Min Task Detail Status", "Updated Timestamp", "Task Detail ID" | D64: STAGE - ALL - MAWM - Task Completed or Cancelled w/ Open Task Details | E64: search | F64: scriptuser | H64: 2024-02-19T10:36:22-05:00 | I64: Not Needed
A65: alert | B65: STAGE - ALL - MAWM - Task Open w/ Completed or Cancelled Task Details | C65: | dbxquery query="SELECT T2.ORG_ID, T2.TASK_ID, /*TASK_DETAIL_ID, */ T2.HDR_STAT TASK_HDR_STATUS, T2.TRANSACTION_ID, CONCAT(T2.MIN_TASK_DTL_STAT, '-', TDS.DESCRIPTION) MIN_TASK_DETAIL_STATUS, T2.UPDATED_TIMESTAMP FROM (SELECT ORG_ID, TASK_ID, /*TASK_DETAIL_ID, */ HDR_STAT, STATUS, TRANSACTION_ID, MIN(TASK_DETAIL_STATUS_ID) MIN_TASK_DTL_STAT, UPDATED_TIMESTAMP FROM (SELECT TSK.ORG_ID, TSK.TASK_ID, TSK.STATUS, CONCAT(TSK.STATUS, '-', TS.DESCRIPTION) HDR_STAT, TSK.CURRENT_USER_ID, TSK.ASSIGNED_TASK_GROUP_ID, TSK.TRANSACTION_ID, TSK.TRANSACTION_TYPE_ID, TD.SEQUENCE, TDS.TASK_DETAIL_STATUS_ID, CONCAT(TD.STATUS, '-', TDS.DESCRIPTION) DTL_STAT, TD.SOURCE_CONTAINER_ID, TSK.UPDATED_TIMESTAMP, TD.TASK_DETAIL_ID FROM default_task.TSK_TASK TSK LEFT JOIN default_task.TSK_TASK_DETAIL TD ON TD.TASK_ID = TSK.TASK_ID AND TD.ORG_ID = TSK.ORG_ID LEFT JOIN default_task.TSK_TASK_STATUS TS ON TS.TASK_STATUS_ID = TSK.STATUS LEFT JOIN default_task.TSK_TASK_DETAIL_STATUS TDS ON TDS.TASK_DETAIL_STATUS_ID = TD.STATUS WHERE 1 = 1 ORDER BY TASK_ID, SEQUENCE) T1 WHERE 1 = 1 AND STATUS < '8000' GROUP BY TASK_ID, /*TASK_DETAIL_ID,*/ ORG_ID, TRANSACTION_ID, STATUS, HDR_STAT, UPDATED_TIMESTAMP) T2 LEFT JOIN default_task.TSK_TASK_DETAIL_STATUS TDS ON TDS.TASK_DETAIL_STATUS_ID = T2.MIN_TASK_DTL_STAT WHERE MIN_TASK_DTL_STAT IN ('8000', '9000') AND T2.UPDATED_TIMESTAMP < NOW() - INTERVAL 120 MINUTE AND T2.ORG_ID NOT IN ('NEWQA','NEWSDN') ORDER BY 1; " connection="MASTG_NEW" | D65: Update the task to completed (8000) or cancelled (9000) using the below API. Post: {{app_host}}/task/api/task/task/save { "TaskId":"CCNTDCI000000366", "Status":"9000" } | E65: search | F65: scriptuser | H65: 2024-02-19T10:35:48-05:00 | I65: Not Needed
A66: alert | B66: STAGE - ALL - MAWM - Task â€˜In Progressâ€™ w/ Completed or Cancelled Task Details | C66: | dbxquery query="SELECT T2.ORG_ID,T2.TASK_ID, T2.HDR_STAT TASK_HDR_STATUS, T2.TRANSACTION_ID, CONCAT(T2.MIN_TASK_DTL_STAT,'-',TDS.DESCRIPTION) MIN_TASK_DETAIL_STATUS, DTL_UPDATED_TIMESTAMP FROM ( SELECT ORG_ID, TASK_ID, HDR_STAT, TRANSACTION_ID, MIN(TASK_DETAIL_STATUS_ID) MIN_TASK_DTL_STAT, MAX(DTL_UPDATED_TIMESTAMP) DTL_UPDATED_TIMESTAMP FROM ( select TSK.ORG_ID , TSK.TASK_ID , TSK.STATUS , CONCAT(TSK.STATUS,'-',TS.DESCRIPTION) HDR_STAT , TSK.CURRENT_USER_ID , TSK.ASSIGNED_TASK_GROUP_ID , TSK.TRANSACTION_ID , TSK.TRANSACTION_TYPE_ID , TD.SEQUENCE , TDS.TASK_DETAIL_STATUS_ID , CONCAT(TD.STATUS,'-',TDS.DESCRIPTION) DTL_STAT , TD.SOURCE_CONTAINER_ID , TSK.UPDATED_TIMESTAMP HDR_UPDATED_TIMESTAMP , TD.UPDATED_TIMESTAMP DTL_UPDATED_TIMESTAMP from default_task.TSK_TASK TSK LEFT JOIN default_task.TSK_TASK_DETAIL TD ON TD.TASK_ID = TSK.TASK_ID AND TD.ORG_ID = TSK.ORG_ID LEFT JOIN default_task.TSK_TASK_STATUS TS ON TS.TASK_STATUS_ID = TSK.STATUS LEFT JOIN default_task.TSK_TASK_DETAIL_STATUS TDS ON TDS.TASK_DETAIL_STATUS_ID = TD.STATUS WHERE 1=1 ORDER BY TASK_ID, SEQUENCE ) T1 WHERE 1=1 AND HDR_STAT IN ('7000-In Progress') GROUP BY TASK_ID, ORG_ID, TRANSACTION_ID ) T2 LEFT JOIN default_task.TSK_TASK_DETAIL_STATUS TDS ON TDS.TASK_DETAIL_STATUS_ID = T2.MIN_TASK_DTL_STAT WHERE MIN_TASK_DTL_STAT >= '8000' AND T2.ORG_ID NOT IN ('NEWQA','NEWSDN') AND DTL_UPDATED_TIMESTAMP < NOW() - INTERVAL 6 HOUR;" connection="MASTG_NEW" | D66: STAGE - ALL - MAWM - Task â€˜In Progressâ€™ w/ Completed or Cancelled Task Details | E66: search | F66: scriptuser | H66: 2024-02-19T10:35:23-05:00 | I66: Not Needed
... A70: alert | B70: STAGE - All - MAWM - Multiple Order Lines Per Original Order Line | C70: | dbxquery query="select distinct (org_id), order_id, case when order_planning_run_id is not null then order_planning_run_id else shorted_order_planning_run_id end as \"wave_nbr\", order_type, original_order_line_id, item_id, count(order_line_id) from ( select o.org_id, o.order_id, o.order_type, oli.original_order_line_id, oli.order_line_id, oli.item_id, oli.order_planning_run_id, oli.shorted_order_planning_run_id, oli.status, oli.shortage_line, oli.ext_original_order_line_quantity, oli.ext_allocation_strategy, oli.packed_quantity, o.updated_timestamp from default_dcorder.DCO_ORDER_LINE oli join default_dcorder.DCO_ORDER o on oli.original_order_id = o.order_id and o.org_id = oli.org_id AND o.ORG_ID NOT IN ('NEWQA','NEWSDN') where oli.pipeline_status > 1000 and oli.updated_timestamp >= now() - INTERVAL 12 HOUR ) a group by org_id, order_id, wave_nbr, order_type, original_order_line_id, item_id having count(order_line_id) > 1 order by org_id, order_id, original_order_line_id; " connection="MASTG_NEW" | D70: STAGE - All - MAWM - Multiple Order Lines Per Original Order Line | E70: search | F70: scriptuser | H70: 2024-02-19T10:30:14-05:00 | I70: Not Needed
A71: alert | B71: ServiceNow Testing Alert | C71: | inputlookup WMS_ACTIVE_SCHEMAS.csv | table USERNAME, instance | E71: search | F71: scriptuser | H71: 2023-05-17T12:07:10-04:00 | I71: Not Needed
A72: alert | B72: Splunk - Daily License Usage | C72: | rest splunk_server=local /services/licenser/pools | rename title AS Pool | search [rest splunk_server=local /services/licenser/groups | search is_active=1 | eval stack_id=stack_ids | fields stack_id] | join type=outer stack_id [rest splunk_server=local /services/licenser/stacks | eval stack_id=title | eval stack_quota=quota | fields stack_id stack_quota] | stats sum(used_bytes) as used max(stack_quota) as total | eval usedGB=round(used/1024/1024/1024,3) | eval totalGB=round(total/1024/1024/1024,3) | rename totalGB as Total, usedGB as Used | table Used Total | D72: Daily License Usage | E72: search | F72: scriptuser | H72: 2021-07-27T16:36:27-04:00 | I72: Not Needed
A73: alert | B73: Splunk - License Used > 95% | C73: | rest splunk_server=local /services/licenser/pools | rename title AS Pool | search [rest splunk_server=local /services/licenser/groups | search is_active=1 | eval stack_id=stack_ids | fields stack_id] | eval quota=if(isnull(effective_quota),quota,effective_quota) | eval Used=round(used_bytes/quota*100,2) | fields Pool Used | where Used>95 | E73: search | F73: admin | H73: 2021-07-27T16:57:29-04:00 | I73: Not Needed
A74: alert | B74: Splunk Admin - Duplicate Will Call Emails | C74: sourcetype=willcall | stats count by Invoice, schema | where count>1 | E74: search | F74: admin | H74: 2021-08-24T11:00:09-04:00 | I74: ?
A75: alert | B75: Splunk License | C75: | rest splunk_server=local /services/licenser/pools | rename title AS Pool | search [rest splunk_server=local /services/licenser/groups | search is_active=1 | eval stack_id=stack_ids | fields stack_id] | eval quota=if(isnull(effective_quota),quota,effective_quota) | eval "Used"=round(used_bytes/1024/1024/1024, 3) | eval "Quota"=round(quota/1024/1024/1024, 3) | fields "Used" "Quota" | E75: search | F75: scriptuser | H75: 2021-07-27T16:57:16-04:00 | I75: Not Needed
A76: alert | B76: URL Down: dev-compitcs.corp.rndc-usa.com/ControlStates/ | C76: sourcetype="web_ping" () title="DevCompitcsControlStates" | where response_code!=200 | D76: URL Down: dev-compitcs.corp.rndc-usa.com/ControlStates/ | E76: search | F76: scriptuser | H76: 2022-03-01T11:48:06-05:00 | I76: ?
A77: alert | B77: URL Down: dev-mixology | C77: sourcetype="web_ping" () title="Dev-mixology" | where response_code!=200 | D77: URL Down: dev-mixology | E77: search | F77: scriptuser | H77: 2022-03-01T12:13:07-05:00 | I77: ?
A78: alert | B78: URL Down: rac-dev | C78: sourcetype="web_ping" () title="Rac-dev" | where response_code!=200 | D78: URL Down: rac-dev | E78: search | F78: scriptuser | H78: 2022-03-01T12:29:21-05:00 | I78: ?
A79: alert | B79: WMS â€“ RNDC WEST MGH - Orders with Null Inventory Type | C79: | dbxquery query="SELECT (SELECT DISTINCT whse FROM locn_hdr) whse, tc_order_id, do_Status, delivery_end_Dttm, created_dttm FROM orders WHERE order_id IN (SELECT order_id FROM order_line_item WHERE invn_type is null) AND do_status = '110' " connection="YMC_MGH_PROD" | E79: search | F79: scriptuser | H79: 2021-07-20T19:08:32-04:00 | I79: Not Needed
A80: alert | B80: WMS â€“ RNDC WEST - Items Unable to be Received on PO | C80: | inputlookup WMS_WEST_SCHEMAS.csv | table WAREHOUSE | map maxsearches=1000 search="| dbxquery query=\"SELECT PO.D_FACILITY_ALIAS_ID "FACILITY", PO.TC_PURCHASE_ORDERS_ID "PO", PO.CREATED_DTTM \\\"PO CREATED DATE HOST\\\", POLI.PURCHASE_ORDERS_LINE_STATUS, IC.AUDIT_CREATED_DTTM \\\"ITEM CREATE DATE IN WM\\\", POLI.TC_PO_LINE_ID, POLI.ORIG_ORDER_QTY, POLI.STD_PACK_QTY, POLI.QTY_CONV_FACTOR, POLI.SKU_ID, POLI.SKU "ITEM", IC.LONG_DESCRIPTION, IC.AUDIT_LAST_UPDATED_SOURCE \\\"ITEM LAST UPDATED SOURCE\\\", IC.MARK_FOR_DELETION FROM PURCHASE_ORDERS_LINE_ITEM POLI JOIN PURCHASE_ORDERS PO ON POLI.PURCHASE_ORDERS_ID = PO.PURCHASE_ORDERS_ID JOIN ITEM_CBO IC ON POLI.SKU = IC.ITEM_NAME WHERE PO.CREATED_DTTM < POLI.CREATED_DTTM AND POLI.SKU_ID IS NULL AND (PO.PURCHASE_ORDERS_STATUS = '20' AND POLI.PURCHASE_ORDERS_LINE_STATUS = '20') ORDER BY PO.CREATED_DTTM DESC\" connection=$WAREHOUSE$ shortnames=true" | D80: WMS â€“ Items Unable to be Received on PO | E80: search | F80: scriptuser | H80: 2021-10-18T13:38:07-04:00 | I80: Not Needed
A81: report | B81: Errors in the last 24 hours | C81: error OR failed OR severe OR ( sourcetype=access_* ( 404 OR 500 OR 503 ) ) | E81: search | F81: nobody | H81: 2017-05-24T09:24:43-04:00 | I81: Not Needed
A82: report | B82: Errors in the last hour | C82: error OR failed OR severe OR ( sourcetype=access_* ( 404 OR 500 OR 503 ) ) | E82: search | F82: nobody | H82: 2017-05-24T09:24:44-04:00 | I82: Not Needed
A83: report | B83: License Usage Data Cube | C83: index=_internal source=*license_usage.log* type="Usage" | eval h=if(len(h)=0 OR isnull(h),"(SQUASHED)",h) | eval s=if(len(s)=0 OR isnull(s),"(SQUASHED)",s) | eval idx=if(len(idx)=0 OR isnull(idx),"(UNKNOWN)",idx) | bin _time span=1d | stats sum(b) as b by _time, pool, s, st, h, idx | D83: Faster License Usage Report | E83: search | F83: nobody | H83: 2014-10-31T09:16:00-04:00 | I83: Not Needed
A84: report | B84: WMS-Printing_DO_Status_165_report | C84: | dbxquery query="SELECT LAST_UPDATED_DTTM, DO_STATUS, \"Invoice Number\", \"Location\", \"Salesperson\", \"Customer Number\", \"Ship To\", SUM(\"Cases\") CASES, SUM(\"Bottles\") BOTTLES, '*' || \"oLPN\" || '*' \"oLPN\" FROM ( select o.last_updated_dttm, o.do_status, lh.locN_brcd \"Location\", lpn.tc_lpn_id \"oLPN\", lpn.tc_order_Id \"Invoice Number\" , SUM(floor(ld.size_value / package.quantity ))\"Cases\", SUM(mod(ld.size_value,package.quantity)) \"Bottles\", o.ref_field_4 as \"Salesperson\", o.ref_Field_1 \"Customer Number\", O.D_Name \"Ship To\" from locn_hdr lh join lpn lpn on lh.locn_id = lpn.curr_sub_locn_id join lpn_detail ld on lpn.lpn_id =ld.lpn_id join orders o on lpn.tc_order_Id = o.tc_order_id join item_cbo cbo on cbo.item_id = ld.item_id join item_package_cbo package on cbo.item_id = package.item_id and package.is_std = 1 and package.mark_for_deletion = 0 and package.package_uom_id = '46' where lh.locn_class = 'S' and o.do_status = 165 GROUP BY o.last_updated_dttm, o.do_status, lh.locN_brcd, lpn.tc_lpn_id ,lpn.tc_order_Id ,o.ref_field_4 , o.ref_Field_1 , O.D_Name ) GROUP BY LAST_UPDATED_DTTM, DO_STATUS, \"Invoice Number\" ,\"Salesperson\",\"Customer Number\", \"Ship To\", \"Location\", \"oLPN\" " connection="ATL_WM13" shortnames = true | fields - _raw _time |head 5 | E84: search | F84: admin | H84: 2018-03-19T09:04:20-04:00 | I84: Not Needed
A85: alert | B85: ABQ - MAWM - Missing Item Level Verification PIX | C85: | dbxquery query="select pt.warehouse, pt.asn_no asn_number, listagg(po.po_no,' , ') within group (order by pt.asn_no) purchase_orders, pt.pixid, pt.created_dttm FROM abq_wmsods.pix_trx pt LEFT JOIN (SELECT DISTINCT po_no, asn_no FROM abq_wmsods.pix_trx t2 WHERE pix_spec = 'SupplierReceiptId') po ON po.asn_no = pt.asn_no WHERE pt.pix_spec = 'ASN Level' and pt.asn_type = 'P' AND pt.asn_no NOT IN (SELECT asn_no FROM abq_wmsods.pix_trx WHERE pix_spec = 'ITEM_Level') AND created_dttm >= sysdate -1 GROUP BY pt.asn_no, created_dttm, warehouse, pixid;" connection="MAWM_SOA_PRD" | D85: ABQ - MAWM - Missing Item Level Verification PIX | E85: splunk_app_db_connect | F85: scriptuser | H85: 2024-05-14T16:54:54-04:00 | I85: Required
A86: alert | B86: ABQ - MAWM - Replenishment Tasks With Multiple Details For Same Item | C86: | dbxquery query="SELECT DISTINCT (th.task_id), th.org_id, th.created_timestamp, th.transaction_id, td.item_id, count(td.task_detail_id) FROM default_task.TSK_TASK_DETAIL td JOIN default_dcinventory.DCI_LOCATION dl ON td.working_location_id = dl.location_id AND dl.profile_id ='ABQ_Fac_Prof' JOIN default_task.TSK_TASK th ON td.task_id = th.task_id AND th.org_id = td.org_id WHERE th.transaction_type_id ='Pick' AND th.transaction_id LIKE 'Replen Case%' AND th.created_timestamp >= now() - INTERVAL 1 HOUR AND td.status ='8000' GROUP BY th.task_id,th.org_id,th.created_timestamp,th.transaction_id,td.item_id HAVING count(td.task_detail_id) > 1 " connection="MAPRD_NEW" | D86: ABQ - MAWM - Replenishment Tasks With Multiple Details For Same Item | E86: splunk_app_db_connect | F86: scriptuser | H86: 2022-11-15T15:08:30-05:00 | I86: Required
A87: alert | B87: ABQ - MAWM - Standard Orders w/ No Designated Shipments Created | C87: | dbxquery query="SELECT O.ORG_ID, O.ORIGINAL_ORDER_ID AS \"ORDER\", O.ORDER_TYPE ,CONCAT(O.MAXIMUM_STATUS,'-',MAX_STAT.DESCRIPTION) MAX_STATUS ,CONCAT(O.MINIMUM_STATUS,'-',MIN_STAT.DESCRIPTION) MIN_STATUS , O.DESIGNATED_SHIPMENT_ID SHIPMENT, O.CREATED_TIMESTAMP FROM default_dcorder.DCO_ORIGINAL_ORDER O LEFT JOIN default_dcorder.DCO_ORDER_STATUS MAX_STAT ON MAX_STAT.ORDER_STATUS_ID = O.MAXIMUM_STATUS LEFT JOIN default_dcorder.DCO_ORDER_STATUS MIN_STAT ON MIN_STAT.ORDER_STATUS_ID = O.MAXIMUM_STATUS WHERE 1=1 AND O.ORG_ID = 'ABQ' AND O.ORDER_TYPE = 'Standard' AND O.MINIMUM_STATUS < '8000' AND O.CREATED_TIMESTAMP <= NOW() - INTERVAL 15 MINUTE AND O.DESIGNATED_SHIPMENT_ID NOT IN (SELECT DISTINCT SHIPMENT_ID FROM default_shipment.SHP_SHIPMENT S WHERE S.ORG_ID = O.ORG_ID) " connection="MAPRD_NEW" | D87: ABQ - MAWM - Standard Orders w/ No Designated Shipments Created | E87: splunk_app_db_connect | F87: scriptuser | H87: 2022-11-22T15:54:29-05:00 | I87: Required
A88: alert | B88: ABQ â€“ MAWM - Item Level Receipts With 0 Quantity | C88: | dbxquery query="SELECT itlvl.warehouse, itlvl.pix_spec, itlvl.asn_no, itlvl.po_no, itlvl.po_line, itlvl.item_no, itlvl.qty, spl.rcv_qty, ( 'update pix_Trx set qty =' || ' ' || spl.rcv_qty || ',' || 'prc_status = 10, prc_time = null , prc_date = null, trx_time= ' || '''' || 121821.657 || '''' || ' ' || 'where pix_spec =' || '''' || 'ITEM_Level' || '''' || ' ' || 'and asn_no =' || '''' || itlvl.asn_no || '''' || ' ' || 'and po_no=' || '''' || itlvl.po_no || '''' || ' ' || 'and item_no =' || '''' || itlvl.item_no || '''' || 'and qty = 0' || ';' )\"UPDATE\" FROM (SELECT DISTINCT ( warehouse ), pix_spec, asn_no, po_no, po_line, item_no, Sum(qty) AS qty FROM abq_wmsods.pix_trx WHERE pix_spec = 'ITEM_Level' GROUP BY warehouse, pix_spec, asn_no, po_no, po_line, item_no HAVING Sum(qty) = 0 ORDER BY asn_no, po_no, po_line)itlvl JOIN (SELECT DISTINCT( warehouse ), asn_no, po_no, po_line, item_no, Sum(abs_qty) AS \"RCV_QTY\" FROM (SELECT warehouse, pix_spec, asn_no, po_no, po_line, item_no, CASE WHEN add_sub = 'A' THEN ( qty * 1 ) WHEN add_sub = 'S' THEN ( qty *- 1 ) END AS \"ABS_QTY\" FROM abq_wmsods.pix_trx WHERE pix_spec IN ( 'SupplierReceiptId','Inventory Adjustment') ORDER BY trx_time) fin GROUP BY warehouse, asn_no, po_no, po_line, item_no ) spl ON itlvl.po_no = spl.po_no AND itlvl.po_line = spl.po_line AND itlvl.asn_no = spl.asn_no WHERE itlvl.qty <> spl.rcv_qty AND itlvl.asn_no NOT IN (SELECT DISTINCT asn_no FROM (SELECT t1.asn_no, t1.item_level_qty, t2.asn_level_qty FROM ( (SELECT asn_no, sum(qty) item_level_qty FROM abq_wmsods.pix_trx WHERE pix_spec = 'ITEM_Level' GROUP BY asn_no ) t1 LEFT JOIN (SELECT asn_no, sum(qty) asn_level_qty FROM abq_wmsods.pix_trx pt WHERE pix_spec = 'ASN Level' GROUP BY asn_no ) t2 ON t2.asn_no = t1.asn_no ) WHERE t1.item_level_qty = t2.asn_level_qty ) ) " connection="MAWM_SOA_PRD" | D88: ABQ â€“ MAWM - Item Level Receipts With 0 Quantity | E88: splunk_app_db_connect | F88: scriptuser | H88: 2024-08-15T09:48:11-04:00 | I88: Required
A89: alert | B89: ALL - MAWM - Day Waving > 10 Minutes | C89: | dbxquery query="SELECT org_id, planning_strategy_id, order_planning_run_id, created_timestamp, run_completion_date_time, wave_run_time, selected_order_lines, round((selected_order_lines/wave_run_time), 2)lines_per_min, description FROM (SELECT ops.org_id, ops.planning_strategy_id, ops.order_planning_run_id, ops.created_timestamp, ops.run_completion_date_time, timestampdiff(minute, ops.created_timestamp, ops.run_completion_date_time)WAVE_RUN_TIME, ops.selected_order_lines, st.description FROM default_dcorder.DCO_ORDER_PLAN_RUN_STRATEGY ops JOIN default_dcorder.DCO_PLANNING_RUN_STATUS st ON ops.status = st.planning_run_status_id WHERE ops.planning_strategy_id NOT IN ('Standard Wave Order Planning Strategy','Forecast Replenishment Case Only','Forecast Replenishment') AND timediff(ops.run_completion_date_time,ops.created_timestamp) > '00:10:00' AND ops.created_timestamp >= now() - INTERVAL 1 DAY ORDER BY 6 desc)orders;" connection="MAPRD_NEW" | D89: ALL - MAWM - Day Waving > 10 Minutes | E89: splunk_app_db_connect | F89: scriptuser | H89: 2022-12-13T12:43:43-05:00 | I89: Required
A90: alert | B90: ALL - MAWM - LPNs Putaway With PP Condition Codes Still Assigned | C90: | dbxquery query="select dci.org_id,dci.ilpn_id,dci.location_id,dl.storage_uom_id,dl.pick_allocation_zone_id,dci.item_id,dci.on_hand,dcc.condition_code,dci.created_timestamp,dci.updated_timestamp from default_dcinventory.DCI_INVENTORY dci join default_dcinventory.DCI_CONTAINER_CONDITION dcc on dci.org_id = dcc.org_id and dci.ilpn_id = dcc.inventory_container_id join default_dcinventory.DCI_LOCATION dl on dci.org_id = substr(dl.profile_id,1,3) and dci.location_id = dl.location_id where dl.storage_uom_id ='LPN' and dcc.condition_code ='PP' and dl.pick_allocation_zone_id != 'No Allocation' and dl.location_id not like 'DOCK%' and dl.location_id not in ('VINTAG') order by dci.org_id,dci.ilpn_id;" connection="MAPRD_NEW" | D90: ALL - MAWM - LPNs Putaway With PP Condition Codes Still Assigned | E90: splunk_app_db_connect | F90: scriptuser | H90: 2022-12-05T08:42:36-05:00 | I90: Required
A91: alert | B91: ALL - MAWM - Monthly Slotting Dashboard | C91: | dbxquery query="select org.org_id,Open_Bottle_Slots,Odd_Bottle_Over_2cswk,StaticBottle_Less_1_BtlPerWk,StaticBottle_Over_4_CsPerWk,BottleFlow_Less_1_BtlPerWk, round(((obbtls/(btls+obbtls))*100),2)\"OddBtlPercent\",round((((1-ideal_bottle)*100)),2)\"PerfectBtlPercent\", round(((1-((obbtls/(btls+obbtls))))/(1-(1-ideal_bottle))),2)\"BtlRatio\", Open_Case_Slots,Odd_Case_Over_5cswk,CaseFlow_Less_1_CsPerWk,CaseFlow_Over_30_CsPerWk,PalletFlow_Less_5_CsPerWk, round(((OddCases/(Caseline+OddCases))*100),2)\"OddCasePercent\",round(((1-(case_within_rank.hits/allcase_hist.hits))*100),2)\"PerfectCasePercent\", round((1-((OddCases/(Caseline+OddCases)))/(1-(1-(case_within_rank.hits/allcase_hist.hits)))),2)\"CaseRatio\" from (select distinct (dci.org_id) from default_dcinventory.DCI_INVENTORY dci order by dci.org_id)org left join (select distinct (org_id),count(location_id)\"Open_Bottle_Slots\" from ( select substr(dl.profile_id,1,3)org_id,dl.location_id,lia.item_id from default_dcinventory.DCI_LOCATION dl left join default_dcinventory.DCI_LOCATION_ITEM_ASSIGNMENT lia on dl.location_id = lia.location_id and substr(dl.profile_id,1,3) = lia.org_id where dl.eligible_for_slotting ='1' and dl.is_active ='1' and dl.storage_uom_id ='UNIT' and lia.item_id is null)open_bottle group by org_id order by org_id)open_bottle on org.org_id = open_bottle.org_id left join (select distinct org_id,count(item_id)\"Odd_Bottle_Over_2cswk\" from( select sid.org_id,sid.item_id,it.description,it.ext_odd_bottle,sid.demand_uom_id,qpc.quantity,sid.movement,round(sid.movement/qpc.quantity)case_per_week from default_slotting.SLO_ITEM_DEMAND sid join default_item_master.ITE_ITEM it on sid.item_id = it.item_id and sid.org_id = substr(it.profile_id,1,3) join default_item_master.ITE_ITEM_PACKAGE qpc on it.pk = qpc.item_pk and qpc.standard_quantity_uom_id = 'PACK' where it.ext_odd_bottle ='true' and sid.demand_uom_id ='UNIT' and round(sid.movement/qpc.quantity)>2)oddbottle_case_per_week group by org_id order by org_id)oddbottle_case_per_week on org.org_id = oddbottle_case_per_week.org_id left join (select distinct org_id,count(item_id)\"StaticBottle_Less_1_BtlPerWk\" from( select sid.org_id,dl.location_id,dl.pick_execution_zone_id,sid.item_id,it.description,it.ext_odd_bottle,sid.demand_uom_id,qpc.quantity,sid.movement from default_slotting.SLO_ITEM_DEMAND sid join default_item_master.ITE_ITEM it on sid.item_id = it.item_id and sid.org_id = substr(it.profile_id,1,3) join default_item_master.ITE_ITEM_PACKAGE qpc on it.pk = qpc.item_pk and qpc.standard_quantity_uom_id = 'PACK' join default_dcinventory.DCI_LOCATION_ITEM_ASSIGNMENT lia on sid.item_id = lia.item_id and sid.org_id = lia.org_id join default_dcinventory.DCI_LOCATION dl on lia.location_id = dl.location_id and substr(dl.profile_id,1,3) = lia.org_id and dl.storage_uom_id ='UNIT' and dl.pick_execution_zone_id in ('Slow Bottle','SPB') where it.ext_odd_bottle ='false' and sid.demand_uom_id ='UNIT' and sid.movement < 1)slow_static_bottle group by org_id order by org_id)slow_static_bottle on org.org_id = slow_static_bottle.org_id left join (select distinct org_id,count(item_id)\"StaticBottle_Over_4_CsPerWk\" from( select sid.org_id,dl.location_id,dl.pick_execution_zone_id,sid.item_id,it.description,it.ext_odd_bottle,sid.demand_uom_id,qpc.quantity,sid.movement,round(sid.movement/qpc.quantity)case_per_week from default_slotting.SLO_ITEM_DEMAND sid join default_item_master.ITE_ITEM it on sid.item_id = it.item_id and sid.org_id = substr(it.profile_id,1,3) join default_item_master.ITE_ITEM_PACKAGE qpc on it.pk = qpc.item_pk and qpc.standard_quantity_uom_id = 'PACK' join default_dcinventory.DCI_LOCATION_ITEM_ASSIGNMENT lia on sid.item_id = lia.item_id and sid.org_id = lia.org_id join default_dcinventory.DCI_LOCATION dl on lia.location_id = dl.location_id and substr(dl.profile_id,1,3) = lia.org_id and dl.storage_uom_id ='UNIT' and dl.pick_execution_zone_id in ('Slow Bottle','SPB') where it.ext_odd_bottle ='false' and sid.demand_uom_id ='UNIT' and round(sid.movement/qpc.quantity)>4)fast_static_bottle group by org_id order by org_id)fast_static_bottle on org.org_id = fast_static_bottle.org_id left join (select distinct org_id,count(item_id)\"BottleFlow_Less_1_BtlPerWk\" from( select sid.org_id,dl.location_id,dl.pick_execution_zone_id,sid.item_id,it.description,it.ext_odd_bottle,sid.demand_uom_id,qpc.quantity,sid.movement from default_slotting.SLO_ITEM_DEMAND sid join default_item_master.ITE_ITEM it on sid.item_id = it.item_id and sid.org_id = substr(it.profile_id,1,3) join default_item_master.ITE_ITEM_PACKAGE qpc on it.pk = qpc.item_pk and qpc.standard_quantity_uom_id = 'PACK' join default_dcinventory.DCI_LOCATION_ITEM_ASSIGNMENT lia on sid.item_id = lia.item_id and sid.org_id = lia.org_id join default_dcinventory.DCI_LOCATION dl on lia.location_id = dl.location_id and substr(dl.profile_id,1,3) = lia.org_id and dl.storage_uom_id ='UNIT' and dl.pick_execution_zone_id in ('Fast Bottle','Fast Bottle X','Fast Bottle Y','FPB','Fast Bottle L','Fast Bottle R') where it.ext_odd_bottle ='false' and sid.demand_uom_id ='UNIT' and sid.movement < 1)slow_flow_bottle group by org_id order by org_id)slow_flow_bottle on org.org_id = slow_flow_bottle.org_id left join (select distinct org_id,sum(quantity)btls from ( select dca.org_id,dca.olpn_id,dca.pick_allocation_zone_id,dca.quantity from default_dcinventory.DCI_ALLOCATION dca join default_pickpack.PPK_OLPN ol on dca.olpn_id = ol.olpn_id and dca.org_id = ol.org_id where dca.generation_code_id ='Wave' and dca.type_id ='PICK/PACK' and dca.allocation_uom_type_id ='UNIT' and dca.pick_allocation_zone_id in ('Split Case') and ol.order_planning_strategy_id ='Standard Wave Order Planning Strategy' and dca.created_timestamp >= now() - INTERVAL 30 DAY)btls group by org_id)btls on org.org_id = btls.org_id left join (select distinct org_id,sum(quantity)obbtls from ( select dca.org_id,dca.olpn_id,dca.pick_allocation_zone_id,dca.quantity from default_dcinventory.DCI_ALLOCATION dca join default_pickpack.PPK_OLPN ol on dca.olpn_id = ol.olpn_id and dca.org_id = ol.org_id where dca.generation_code_id ='Wave' and dca.type_id ='PICK/PACK' and dca.allocation_uom_type_id ='UNIT' and dca.pick_allocation_zone_id in ('DYBD') and ol.order_planning_strategy_id ='Standard Wave Order Planning Strategy' and dca.created_timestamp >= now() - INTERVAL 30 DAY)obbtls group by org_id)obbtls on org.org_id = obbtls.org_id left join (select distinct org_id,count(location_id)\"Open_Case_Slots\" from ( select substr(dl.profile_id,1,3)org_id,dl.location_id,lia.item_id from default_dcinventory.DCI_LOCATION dl left join default_dcinventory.DCI_LOCATION_ITEM_ASSIGNMENT lia on dl.location_id = lia.location_id and substr(dl.profile_id,1,3) = lia.org_id where dl.eligible_for_slotting ='1' and dl.is_active ='1' and dl.storage_uom_id ='PACK' and lia.item_id is null)open_case group by org_id order by org_id)open_case on org.org_id = open_case.org_id left join (select distinct org_id,count(item_id) \"Odd_Case_Over_5cswk\" from( select sid.org_id,sid.item_id,it.description,it.ext_odd_bottle,sid.demand_uom_id,qpc.quantity,sid.movement,round(sid.movement/qpc.quantity)case_per_week from default_slotting.SLO_ITEM_DEMAND sid join default_item_master.ITE_ITEM it on sid.item_id = it.item_id and sid.org_id = substr(it.profile_id,1,3) join default_item_master.ITE_ITEM_PACKAGE qpc on it.pk = qpc.item_pk and qpc.standard_quantity_uom_id = 'PACK' where it.ext_odd_case ='true' and sid.demand_uom_id ='PACK' and round(sid.movement/qpc.quantity)>5)oddcase_case_per_week group by org_id order by org_id)oddcase_case_per_week on org.org_id = oddcase_case_per_week.org_id left join (select distinct org_id,count(item_id) \"CaseFlow_Less_1_CsPerWk\" from( select sid.org_id,dl.location_id,dl.pick_allocation_zone_id,sid.item_id,it.description,it.ext_odd_bottle,sid.demand_uom_id,qpc.quantity,sid.movement,round(sid.movement/qpc.quantity)case_per_week from default_slotting.SLO_ITEM_DEMAND sid join default_item_master.ITE_ITEM it on sid.item_id = it.item_id and sid.org_id = substr(it.profile_id,1,3) join default_item_master.ITE_ITEM_PACKAGE qpc on it.pk = qpc.item_pk and qpc.standard_quantity_uom_id = 'PACK' join default_dcinventory.DCI_LOCATION_ITEM_ASSIGNMENT lia on sid.item_id = lia.item_id and sid.org_id = lia.org_id join default_dcinventory.DCI_LOCATION dl on lia.location_id = dl.location_id and substr(dl.profile_id,1,3) = lia.org_id and dl.storage_uom_id ='PACK' and dl.pick_allocation_zone_id in ('Flow Rack') where it.ext_odd_case ='false' and sid.demand_uom_id ='PACK' and round(sid.movement/qpc.quantity) < 1)slow_flowrack_case group by org_id order by org_id)slow_flowrack_case on org.org_id = slow_flowrack_case.org_id left join (select distinct org_id,count(item_id) \"CaseFlow_Over_30_CsPerWk\" from( select sid.org_id,dl.location_id,dl.pick_allocation_zone_id,sid.item_id,it.description,it.ext_odd_bottle,sid.demand_uom_id,qpc.quantity,sid.movement,round(sid.movement/qpc.quantity)case_per_week from default_slotting.SLO_ITEM_DEMAND sid join default_item_master.ITE_ITEM it on sid.item_id = it.item_id and sid.org_id = substr(it.profile_id,1,3) join default_item_master.ITE_ITEM_PACKAGE qpc on it.pk = qpc.item_pk and qpc.standard_quantity_uom_id = 'PACK' join default_dcinventory.DCI_LOCATION_ITEM_ASSIGNMENT lia on sid.item_id = lia.item_id and sid.org_id = lia.org_id join default_dcinventory.DCI_LOCATION dl on lia.location_id = dl.location_id and substr(dl.profile_id,1,3) = lia.org_id and dl.storage_uom_id ='PACK' and dl.pick_allocation_zone_id in ('Flow Rack') where it.ext_odd_case ='false' and sid.demand_uom_id ='PACK' and round(sid.movement/qpc.quantity) > 30)fast_flowrack_case group by org_id order by org_id)fast_flowrack_case on org.org_id = fast_flowrack_case.org_id left join (select distinct org_id,count(item_id) \"PalletFlow_Less_5_CsPerWk\" from( select sid.org_id,dl.location_id,dl.pick_allocation_zone_id,sid.item_id,it.description,it.ext_odd_bottle,sid.demand_uom_id,qpc.quantity,sid.movement,round(sid.movement/qpc.quantity)case_per_week from default_slotting.SLO_ITEM_DEMAND sid join default_item_master.ITE_ITEM it on sid.item_id = it.item_id and sid.org_id = substr(it.profile_id,1,3) join default_item_master.ITE_ITEM_PACKAGE qpc on it.pk = qpc.item_pk and qpc.standard_quantity_uom_id = 'PACK' join default_dcinventory.DCI_LOCATION_ITEM_ASSIGNMENT lia on sid.item_id = lia.item_id and sid.org_id = lia.org_id join default_dcinventory.DCI_LOCATION dl on lia.location_id = dl.location_id and substr(dl.profile_id,1,3) = lia.org_id and dl.storage_uom_id ='PACK' and dl.pick_allocation_zone_id in ('Dedicated','Cluster') where it.ext_odd_case ='false' and sid.demand_uom_id ='PACK' and round(sid.movement/qpc.quantity) < 5)slow_palletflow_case group by org_id order by org_id)slow_palletflow_case on org.org_id = slow_palletflow_case.org_id left join (select distinct org_id, count(olpn_id)\"OddCases\" from( select dca.org_id,dca.olpn_id,dca.pick_allocation_zone_id from default_dcinventory.DCI_ALLOCATION dca join default_pickpack.PPK_OLPN ol on dca.olpn_id = ol.olpn_id and dca.org_id = ol.org_id where dca.generation_code_id ='Wave' and dca.type_id ='PICK/PACK' and dca.allocation_uom_type_id ='PACK' and dca.pick_allocation_zone_id in ('Reserve','High Dollar Cage') and ol.order_planning_strategy_id ='Standard Wave Order Planning Strategy' and dca.created_timestamp >= now() - INTERVAL 30 DAY and ol.container_type_id is null)oddcase group by org_id) oddcase on org.org_id = oddcase.org_id left join (select distinct org_id, count(olpn_id)\"Caseline\" from( select dca.org_id,dca.olpn_id,dca.pick_allocation_zone_id from default_dcinventory.DCI_ALLOCATION dca join default_pickpack.PPK_OLPN ol on dca.olpn_id = ol.olpn_id and dca.org_id = ol.org_id where dca.generation_code_id ='Wave' and dca.type_id ='PICK/PACK' and dca.allocation_uom_type_id ='PACK' and dca.pick_allocation_zone_id in ('Flow Rack','Dedicated','Cluster','Beer Flow Rack') and ol.order_planning_strategy_id ='Standard Wave Order Planning Strategy' and dca.created_timestamp >= now() - INTERVAL 30 DAY and ol.container_type_id is null)casepick group by org_id) casepick on org.org_id = casepick.org_id join (select btl_qty.org_id,(btl_qty.btl_quantity)/(ttl_btl_hist.ttl_btl_qty)ideal_bottle from ( select distinct (item_history.org_id),sum(item_history.quantity)btl_quantity from( select dca.org_id,dca.item_id,dca.quantity,it.conveyable from default_dcinventory.DCI_ALLOCATION dca join default_item_master.ITE_ITEM it on dca.item_id = it.item_id and dca.org_id = substr(it.profile_id,1,3) join default_item_master.ITE_ITEM_PACKAGE qpc on it.pk = qpc.item_pk and qpc.standard_quantity_uom_id = 'PACK' and dca.generation_code_id ='Wave' and dca.pick_allocation_zone_id in ('Split Case','DYBD') and dca.order_criteria_id like 'Standard%' and it.conveyable ='1' and dca.created_timestamp >= now() - INTERVAL 90 DAY)item_history join (select org_id,item_id,row_number()over (partition by org_id order by HITS desc)RANKS from ( select distinct org_id,(item_id),count(allocation_id)HITS from default_dcinventory.DCI_ALLOCATION where generation_code_id ='Wave' and pick_allocation_zone_id in ('Split Case','DYBD') and order_criteria_id like 'Standard%' and created_timestamp >= now() - INTERVAL 90 DAY group by org_id,item_id order by org_id,3 desc)HITS)item_rank on item_history.org_id = item_rank.org_id and item_history.item_id = item_rank.item_id join (select substr(profile_id,1,3)org_id,count(location_id)btl_locs from default_dcinventory.DCI_LOCATION where storage_uom_id ='UNIT' and sku_dedication_type_id ='PERMANENT' group by substr(profile_id,1,3))btl_locs on item_history.org_id = btl_locs.org_id where ranks < btl_locs group by org_id order by org_id,ranks)btl_qty join (select distinct (org_id),sum(quantity)ttl_btl_qty from ( select dca.org_id,dca.item_id,dca.quantity,it.conveyable from default_dcinventory.DCI_ALLOCATION dca join default_item_master.ITE_ITEM it on dca.item_id = it.item_id and dca.org_id = substr(it.profile_id,1,3) join default_item_master.ITE_ITEM_PACKAGE qpc on it.pk = qpc.item_pk and qpc.standard_quantity_uom_id = 'PACK' and dca.generation_code_id ='Wave' and dca.pick_allocation_zone_id in ('Split Case','DYBD') and dca.order_criteria_id like 'Standard%' and it.conveyable ='1' and dca.created_timestamp >= now() - INTERVAL 90 DAY)ttl_btl_hist group by org_id order by org_id)ttl_btl_hist on btl_qty.org_id = ttl_btl_hist.org_id group by org_id order by org_id)ideal_bottle on org.org_id = ideal_bottle.org_id join (select org_id,sum(hits)hits from ( select org_id,item_id,hits,row_number()over (partition by org_id order by HITS desc)CASE_RANKS from ( select distinct (dca.org_id),dca.item_id,count(dca.olpn_id)HITS from default_dcinventory.DCI_ALLOCATION dca join default_item_master.ITE_ITEM it on dca.item_id = it.item_id and dca.org_id = substr(it.profile_id,1,3) join default_item_master.ITE_ITEM_PACKAGE qpc on it.pk = qpc.item_pk and qpc.standard_quantity_uom_id = 'PACK' where dca.order_criteria_id like 'Standard%' and dca.generation_code_id ='Wave' and dca.allocation_uom_type_id ='PACK' and dca.type_id ='PICK/PACK' and dca.pick_allocation_zone_id not in ('High Dollar Cage','Beer Cooler') and it.conveyable ='1' and dca.created_timestamp >= now() - INTERVAL 90 DAY group by dca.org_id,dca.item_id)case_rank order by org_id,CASE_RANKS)case_rank join (select substr(profile_id,1,3)org,sum(max_items)case_slots from default_dcinventory.DCI_LOCATION where storage_uom_id ='PACK' and sku_dedication_type_id ='PERMANENT' group by substr(profile_id,1,3) order by substr(profile_id,1,3))case_slots on case_rank.org_id = case_slots.org where case_ranks < case_slots group by org_id order by org_id,case_ranks)case_within_rank on org.org_id = case_within_rank.org_id join (select org_id,sum(hits)hits from ( select org_id,item_id,hits,row_number()over (partition by org_id order by HITS desc)CASE_RANKS from ( select distinct (dca.org_id),dca.item_id,count(dca.olpn_id)HITS from default_dcinventory.DCI_ALLOCATION dca join default_item_master.ITE_ITEM it on dca.item_id = it.item_id and dca.org_id = substr(it.profile_id,1,3) join default_item_master.ITE_ITEM_PACKAGE qpc on it.pk = qpc.item_pk and qpc.standard_quantity_uom_id = 'PACK' where dca.order_criteria_id like 'Standard%' and dca.generation_code_id ='Wave' and dca.allocation_uom_type_id ='PACK' and dca.type_id ='PICK/PACK' and dca.pick_allocation_zone_id not in ('High Dollar Cage','Beer Cooler') and it.conveyable ='1' and dca.created_timestamp >= now() - INTERVAL 90 DAY group by dca.org_id,dca.item_id)case_rank)allcase_hist group by org_id)allcase_hist on org.org_id = allcase_hist.org_id order by org_id; " connection="MAPRD_NEW" | D91: ALL - MAWM - Monthly Slotting Dashboard | E91: splunk_app_db_connect | F91: scriptuser | H91: 2022-11-18T09:51:39-05:00 | I91: Required
A92: alert | B92: ALL - MAWM â€“ Replen Putaway Tasks Multiple Details Same Item | C92: | dbxquery query="SELECT td.org_id, td.task_id, td.source_container_id, td.item_id, td.target_location_id, count(1) AS repeat_details FROM default_putaway.TSK_TASK_DETAIL td LEFT JOIN default_putaway.TSK_TASK t ON t.task_id = td.task_id WHERE td.type_id = 'PUTAWAY' AND t.status = '1000' AND t.transaction_id = 'Putaway Replenishment Cases' GROUP BY td.org_id, td.task_id, td.source_container_id, td.item_id, td.target_location_id HAVING count(1) > 1; " connection="MAPRD_NEW" | E92: splunk_app_db_connect | F92: scriptuser | H92: 2023-02-14T14:26:25-05:00 | I92: Required
A93: alert | B93: ALL MAWM - Standard Wave Run Times > 10 Minutes | C93: | dbxquery query="SELECT org_id, planning_strategy_id, order_planning_run_id, created_timestamp, run_completion_date_time, wave_run_time, selected_order_lines, round((selected_order_lines/wave_run_time), 2)lines_per_min, description FROM (SELECT ops.org_id, ops.planning_strategy_id, ops.order_planning_run_id, ops.created_timestamp, ops.run_completion_date_time, timestampdiff(minute, ops.created_timestamp, ops.run_completion_date_time)WAVE_RUN_TIME, ops.selected_order_lines, st.description FROM default_dcorder.DCO_ORDER_PLAN_RUN_STRATEGY ops JOIN default_dcorder.DCO_PLANNING_RUN_STATUS st ON ops.status = st.planning_run_status_id WHERE ops.planning_strategy_id IN ('Standard Wave Order Planning Strategy') AND timediff(ops.run_completion_date_time,ops.created_timestamp) > '00:05:00' AND ops.created_timestamp >= now() - INTERVAL 1 DAY ORDER BY 6 desc)orders; " connection="MAPRD_NEW" | D93: ALL MAWM - Standard Wave Run Times > 10 Minutes | E93: splunk_app_db_connect | F93: scriptuser | H93: 2022-11-21T08:12:42-05:00 | I93: Required
A94: alert | B94: ALL MAWM - Standard Wave Run Times > 5 Minutes Clone | C94: | dbxquery query="SELECT org_id, planning_strategy_id, order_planning_run_id, created_timestamp, run_completion_date_time, wave_run_time, selected_order_lines, round((selected_order_lines/wave_run_time), 2)lines_per_min, description FROM (SELECT ops.org_id, ops.planning_strategy_id, ops.order_planning_run_id, ops.created_timestamp, ops.run_completion_date_time, timestampdiff(minute, ops.created_timestamp, ops.run_completion_date_time)WAVE_RUN_TIME, ops.selected_order_lines, st.description FROM default_dcorder.DCO_ORDER_PLAN_RUN_STRATEGY ops JOIN default_dcorder.DCO_PLANNING_RUN_STATUS st ON ops.status = st.planning_run_status_id WHERE ops.planning_strategy_id IN ('Standard Wave Order Planning Strategy') AND timediff(ops.run_completion_date_time,ops.created_timestamp) > '00:05:00' AND ops.created_timestamp >= now() - INTERVAL 1 DAY ORDER BY 6 desc)orders; " connection="MAPRD_NEW" | D94: ALL MAWM - Standard Wave Run Times > 5 Minutes | E94: splunk_app_db_connect | F94: scriptuser | H94: 2022-12-13T08:47:32-05:00 | I94: Required
A95: alert | B95: ASH - MAWM - Missing Item Level Verification PIX | C95: | dbxquery query="select pt.warehouse, pt.asn_no asn_number, listagg(po.po_no,' , ') within group (order by pt.asn_no) purchase_orders, pt.pixid, pt.created_dttm from ash_wmsods.pix_trx pt left join (select distinct po_no, asn_no from ash_wmsods.pix_trx t2 where pix_spec = 'SupplierReceiptId') po on po.asn_no = pt.asn_no WHERE pt.pix_spec = 'ASN Level' and pt.asn_type = 'P' AND pt.asn_no not in (select asn_no from ash_wmsods.pix_trx where pix_spec = 'ITEM_Level') and created_dttm >= sysdate -1 group by pt.asn_no, created_dttm, warehouse, pixid;" connection="MAWM_SOA_PRD" | D95: ASH - MAWM - Missing Item Level Verification PIX | E95: splunk_app_db_connect | F95: scriptuser | H95: 2024-05-17T02:05:27-04:00 | I95: Required
A96: alert | B96: ASH - MAWM - Replenishment Tasks With Multiple Details For Same Item | C96: | dbxquery query="select distinct (th.task_id),th.org_id, th.created_timestamp,th.transaction_id,td.item_id,count(td.task_detail_id) from default_task.TSK_TASK_DETAIL td join default_dcinventory.DCI_LOCATION dl on td.working_location_id = dl.location_id and dl.profile_id ='ASH_Fac_Prof' join default_task.TSK_TASK th on td.task_id = th.task_id and th.org_id = td.org_id where th.transaction_type_id ='Pick' and th.transaction_id like 'Replen Case%' and th.created_timestamp >= now() - INTERVAL 1 HOUR and td.status ='8000' group by th.task_id,th.org_id,th.created_timestamp,th.transaction_id,td.item_id having count(td.task_detail_id) > 1" connection="MAPRD_NEW" | D96: ASH - MAWM - Replenishment Tasks With Multiple Details For Same Item | E96: splunk_app_db_connect | F96: scriptuser | H96: 2022-11-18T09:53:44-05:00 | I96: Required
A97: alert | B97: ASH - MAWM - Standard Orders w/ No Designated Shipments Created | C97: | dbxquery query="SELECT O.ORG_ID, O.ORIGINAL_ORDER_ID AS \"ORDER\", O.ORDER_TYPE ,CONCAT(O.MAXIMUM_STATUS,'-',MAX_STAT.DESCRIPTION) MAX_STATUS ,CONCAT(O.MINIMUM_STATUS,'-',MIN_STAT.DESCRIPTION) MIN_STATUS , O.DESIGNATED_SHIPMENT_ID SHIPMENT, O.CREATED_TIMESTAMP FROM default_dcorder.DCO_ORIGINAL_ORDER O LEFT JOIN default_dcorder.DCO_ORDER_STATUS MAX_STAT ON MAX_STAT.ORDER_STATUS_ID = O.MAXIMUM_STATUS LEFT JOIN default_dcorder.DCO_ORDER_STATUS MIN_STAT ON MIN_STAT.ORDER_STATUS_ID = O.MAXIMUM_STATUS WHERE 1=1 AND O.ORG_ID = 'ASH' AND O.ORDER_TYPE = 'Standard' AND O.MINIMUM_STATUS < '8000' AND O.CREATED_TIMESTAMP <= NOW() - INTERVAL 15 MINUTE AND O.DESIGNATED_SHIPMENT_ID NOT IN (SELECT DISTINCT SHIPMENT_ID FROM default_shipment.SHP_SHIPMENT S WHERE S.ORG_ID = O.ORG_ID)" connection="MAPRD_NEW" | D97: ASH - MAWM - Standard Orders w/ No Designated Shipments Created | E97: splunk_app_db_connect | F97: scriptuser | H97: 2023-01-31T15:50:45-05:00 | I97: Required
A98: alert | B98: ASH â€“ MAWM - Item Level Receipts With 0 Quantity | C98: | dbxquery query="SELECT itlvl.warehouse, itlvl.pix_spec, itlvl.asn_no, itlvl.po_no, itlvl.po_line, itlvl.item_no, itlvl.qty, spl.rcv_qty, ( 'update pix_Trx set qty =' || ' ' || spl.rcv_qty || ',' || 'prc_status = 10, prc_time = null , prc_date = null, trx_time= ' || '''' || 121821.657 || '''' || ' ' || 'where pix_spec =' || '''' || 'ITEM_Level' || '''' || ' ' || 'and asn_no =' || '''' || itlvl.asn_no || '''' || ' ' || 'and po_no=' || '''' || itlvl.po_no || '''' || ' ' || 'and item_no =' || '''' || itlvl.item_no || '''' || 'and qty = 0' || ';' )\"UPDATE\" FROM (SELECT DISTINCT ( warehouse ), pix_spec, asn_no, po_no, po_line, item_no, Sum(qty) AS qty FROM ash_wmsods.pix_trx WHERE pix_spec = 'ITEM_Level' GROUP BY warehouse, pix_spec, asn_no, po_no, po_line, item_no HAVING Sum(qty) = 0 ORDER BY asn_no, po_no, po_line)itlvl JOIN (SELECT DISTINCT( warehouse ), asn_no, po_no, po_line, item_no, Sum(abs_qty) AS \"RCV_QTY\" FROM (SELECT warehouse, pix_spec, asn_no, po_no, po_line, item_no, CASE WHEN add_sub = 'A' THEN ( qty * 1 ) WHEN add_sub = 'S' THEN ( qty *- 1 ) END AS \"ABS_QTY\" FROM ash_wmsods.pix_trx WHERE pix_spec IN ( 'SupplierReceiptId','Inventory Adjustment') ORDER BY trx_time) fin GROUP BY warehouse, asn_no, po_no, po_line, item_no ) spl ON itlvl.po_no = spl.po_no AND itlvl.po_line = spl.po_line AND itlvl.asn_no = spl.asn_no WHERE itlvl.qty <> spl.rcv_qty AND itlvl.asn_no NOT IN (SELECT DISTINCT asn_no FROM (SELECT t1.asn_no, t1.item_level_qty, t2.asn_level_qty FROM ( (SELECT asn_no, sum(qty) item_level_qty FROM ash_wmsods.pix_trx WHERE pix_spec = 'ITEM_Level' GROUP BY asn_no ) t1 LEFT JOIN (SELECT asn_no, sum(qty) asn_level_qty FROM ash_wmsods.pix_trx pt WHERE pix_spec = 'ASN Level' GROUP BY asn_no ) t2 ON t2.asn_no = t1.asn_no ) WHERE t1.item_level_qty = t2.asn_level_qty ) ) " connection="MAWM_SOA_PRD" | D98: ASH â€“ MAWM - Item Level Receipts With 0 Quantity | E98: splunk_app_db_connect | F98: scriptuser | H98: 2024-08-15T09:50:32-04:00 | I98: Required
A99: alert | B99: ATL - MAWM - Missing Item Level Verification PIX | C99: | dbxquery query="select pt.warehouse, pt.asn_no asn_number, listagg(po.po_no,' , ') within group (order by pt.asn_no) purchase_orders, pt.pixid, pt.created_dttm from atl_wmsods.pix_trx pt left join (select distinct po_no, asn_no from atl_wmsods.pix_trx t2 where pix_spec = 'SupplierReceiptId') po on po.asn_no = pt.asn_no WHERE pt.pix_spec = 'ASN Level' and pt.asn_type = 'P' AND pt.asn_no not in (select asn_no from atl_wmsods.pix_trx where pix_spec = 'ITEM_Level') and created_dttm >= sysdate -1 group by pt.asn_no, created_dttm, warehouse, pixid;" connection="MAWM_SOA_PRD" | D99: ATL - MAWM - Missing Item Level Verification PIX | E99: splunk_app_db_connect | F99: scriptuser | H99: 2024-05-17T02:14:44-04:00 | I99: Required
A100: alert | B100: ATL - MAWM - Replenishment Tasks With Multiple Details For Same Item | C100: | dbxquery query="select distinct (th.task_id),th.org_id, th.created_timestamp,th.transaction_id,td.item_id,count(td.task_detail_id) from default_task.TSK_TASK_DETAIL td join default_dcinventory.DCI_LOCATION dl on td.working_location_id = dl.location_id and dl.profile_id ='ATL_Fac_Prof' join default_task.TSK_TASK th on td.task_id = th.task_id and th.org_id = td.org_id where th.transaction_type_id ='Pick' and th.transaction_id like 'Replen Case%' and th.created_timestamp >= now() - INTERVAL 1 HOUR and td.status ='8000' group by th.task_id,th.org_id,th.created_timestamp,th.transaction_id,td.item_id having count(td.task_detail_id) > 1" connection="MAPRD_NEW" | D100: ATL - MAWM - Replenishment Tasks With Multiple Details For Same Item | E100: splunk_app_db_connect | F100: scriptuser | H100: 2022-11-18T10:00:06-05:00 | I100: Required
A101: alert | B101: ATL - MAWM - Standard Orders w/ No Designated Shipments Created | C101: | dbxquery query="SELECT O.ORG_ID, O.ORIGINAL_ORDER_ID AS \"ORDER\", O.ORDER_TYPE ,CONCAT(O.MAXIMUM_STATUS,'-',MAX_STAT.DESCRIPTION) MAX_STATUS ,CONCAT(O.MINIMUM_STATUS,'-',MIN_STAT.DESCRIPTION) MIN_STATUS , O.DESIGNATED_SHIPMENT_ID SHIPMENT, O.CREATED_TIMESTAMP FROM default_dcorder.DCO_ORIGINAL_ORDER O LEFT JOIN default_dcorder.DCO_ORDER_STATUS MAX_STAT ON MAX_STAT.ORDER_STATUS_ID = O.MAXIMUM_STATUS LEFT JOIN default_dcorder.DCO_ORDER_STATUS MIN_STAT ON MIN_STAT.ORDER_STATUS_ID = O.MAXIMUM_STATUS WHERE 1=1 AND O.ORG_ID = 'ATL' AND O.ORDER_TYPE = 'Standard' AND O.MINIMUM_STATUS < '8000' AND O.CREATED_TIMESTAMP <= NOW() - INTERVAL 15 MINUTE AND O.DESIGNATED_SHIPMENT_ID NOT IN (SELECT DISTINCT SHIPMENT_ID FROM default_shipment.SHP_SHIPMENT S WHERE S.ORG_ID = O.ORG_ID)" connection="MAPRD_NEW" | D101: ATL - MAWM - Standard Orders w/ No Designated Shipments Created | E101: splunk_app_db_connect | F101: scriptuser | H101: 2023-06-30T08:41:13-04:00 | I101: Required
A102: alert | B102: ATL â€“ MAWM - Item Level Receipts With 0 Quantity | C102: | dbxquery query="SELECT itlvl.warehouse, itlvl.pix_spec, itlvl.asn_no, itlvl.po_no, itlvl.po_line, itlvl.item_no, itlvl.qty, spl.rcv_qty, ( 'update pix_Trx set qty =' || ' ' || spl.rcv_qty || ',' || 'prc_status = 10, prc_time = null , prc_date = null, trx_time= ' || '''' || 121821.657 || '''' || ' ' || 'where pix_spec =' || '''' || 'ITEM_Level' || '''' || ' ' || 'and asn_no =' || '''' || itlvl.asn_no || '''' || ' ' || 'and po_no=' || '''' || itlvl.po_no || '''' || ' ' || 'and item_no =' || '''' || itlvl.item_no || '''' || 'and qty = 0' || ';' )\"UPDATE\" FROM (SELECT DISTINCT ( warehouse ), pix_spec, asn_no, po_no, po_line, item_no, Sum(qty) AS qty FROM atl_wmsods.pix_trx WHERE pix_spec = 'ITEM_Level' GROUP BY warehouse, pix_spec, asn_no, po_no, po_line, item_no HAVING Sum(qty) = 0 ORDER BY asn_no, po_no, po_line)itlvl JOIN (SELECT DISTINCT( warehouse ), asn_no, po_no, po_line, item_no, Sum(abs_qty) AS \"RCV_QTY\" FROM (SELECT warehouse, pix_spec, asn_no, po_no, po_line, item_no, CASE WHEN add_sub = 'A' THEN ( qty * 1 ) WHEN add_sub = 'S' THEN ( qty *- 1 ) END AS \"ABS_QTY\" FROM atl_wmsods.pix_trx WHERE pix_spec IN ( 'SupplierReceiptId','Inventory Adjustment') ORDER BY trx_time) fin GROUP BY warehouse, asn_no, po_no, po_line, item_no ) spl ON itlvl.po_no = spl.po_no AND itlvl.po_line = spl.po_line AND itlvl.asn_no = spl.asn_no WHERE itlvl.qty <> spl.rcv_qty AND itlvl.asn_no NOT IN (SELECT DISTINCT asn_no FROM (SELECT t1.asn_no, t1.item_level_qty, t2.asn_level_qty FROM ( (SELECT asn_no, sum(qty) item_level_qty FROM atl_wmsods.pix_trx WHERE pix_spec = 'ITEM_Level' GROUP BY asn_no ) t1 LEFT JOIN (SELECT asn_no, sum(qty) asn_level_qty FROM atl_wmsods.pix_trx pt WHERE pix_spec = 'ASN Level' GROUP BY asn_no ) t2 ON t2.asn_no = t1.asn_no ) WHERE t1.item_level_qty = t2.asn_level_qty ) ) " connection="MAWM_SOA_PRD" | D102: ATL â€“ MAWM - Item Level Receipts With 0 Quantity | E102: splunk_app_db_connect | F102: scriptuser | H102: 2024-08-15T09:51:40-04:00 | I102: Required
A103: alert | B103: COL - MAWM - Missing Item Level Verification PIX | C103: | dbxquery query="select pt.warehouse, pt.asn_no asn_number, listagg(po.po_no,' , ') within group (order by pt.asn_no) purchase_orders, pt.pixid, pt.created_dttm from col_wmsods.pix_trx pt left join (select distinct po_no, asn_no from col_wmsods.pix_trx t2 where pix_spec = 'SupplierReceiptId') po on po.asn_no = pt.asn_no WHERE pt.pix_spec = 'ASN Level' and pt.asn_type = 'P' AND pt.asn_no not in (select asn_no from col_wmsods.pix_trx where pix_spec = 'ITEM_Level') and created_dttm >= sysdate -1 group by pt.asn_no, created_dttm, warehouse, pixid;" connection="MAWM_SOA_PRD" | D103: COL - MAWM - Missing Item Level Verification PIX | E103: splunk_app_db_connect | F103: scriptuser | H103: 2024-05-17T02:18:12-04:00 | I103: Required
...

Sheet Splunk Alerts
A1: Script Details | K1: House Enabled
A2: Current Script Name | B2: In Use | C2: New Script Name | D2: Description | E2: Desired Cron Frequency | F2: Script Type | G2: Email Notification | H2: DB | I2: Unstarted Work/In Design/Being Develped/Deployed | J2: Note | K2: ABQ | L2: ARK | M2: ASH | N2: ATL | O2: AUB | P2: CCR | Q2: CHI | R2: COL | S2: DEN | T2: DFB | U2: ELP | V2: FAR | W2: GRP | X2: HAW | Y2: HOU | Z2: IND | AA2: JAC | AB2: JES | AC2: KAP | AD2: KAU | AE2: LAF | AF2: LIV | AG2: LOU | AH2: LUB | AI2: MAU | AJ2: NEW | AK2: OAH | AL2: OKL | AM2: OMA | AN2: ORL | AO2: PEN | AP2: PHO | AQ2: POR | AR2: ROM | AS2: RVR | AT2: SAA | AU2: SIO | AV2: TAM | AW2: TOL | AX2: WSD
A3: ABQ - MAWM -Inventory Sync Schedule API Failed | D3: ABQ - WM Active -Inventory Sync Schedule Failed | F3: File Check | H3: OnPrem | I3: In Design
A4: ALL - MAWM - LPN Storage Locs with Inventory Not Tied to an LPN | D4: ALL - MAWM - LPN Storage Locs with Inventory Not Tied to an LPN | F4: DB Query | H4: MySQL/Cloud | I4: In Design | J4: | dbxquery query="select DISTINCT INV.ORG_ID, LOC.LOCATION_ID, INV.ITEM_ID, INV.ON_HAND, INV.INVENTORY_ID, INV.CREATED_BY, INV.UPDATED_BY, INV.LAST_LOCATED_DATE_TIME, INV.PROCESS, INV.UPDATED_TIMESTAMP FROM default_dcinventory.DCI_LOCATION LOC LEFT JOIN default_dcinventory.DCI_INVENTORY INV on INV.LOCATION_ID = LOC.LOCATION_ID AND SUBSTR(LOC.PROFILE_ID,1,3) = INV.ORG_ID WHERE LOC.STORAGE_UOM_ID = 'LPN' AND (INV.INVENTORY_CONTAINER_TYPE_ID = 'LOCATION' AND INV.ON_HAND > 0) " connection="MAPRD_NEW" |rename ORG_ID AS "ORG ID", LOCATION_ID AS "LOCATION ID", ITEM_ID AS "ITEM ID", ON_HAND AS "ON HAND", INVENTORY_ID AS "INVENTORY ID", CREATED_BY AS "CREATED BY", UPDATED_BY AS "UPDATED BY", LAST_LOCATED_DATE_TIME AS "LAST LOCATED DATE TIME", UPDATED_TIMESTAMP AS "UPDATED TIMESTAMP" |table "ORG ID", "LOCATION ID", "ITEM ID", "ON HAND", "INVENTORY ID", "CREATED BY", "UPDATED BY", "LAST LOCATED DATE TIME", PROCESS, "UPDATED TIMESTAMP" | K4: MySQL
A5: ALL - MAWM - Pallet LPNs w/ Inventory Records | D5: ALL - MAWM - Pallet LPNs w/ Inventory Records | F5: DB Query | H5: MySQL/Cloud | I5: In Design | J5: dbxquery query="select INV.ORG_ID, L.STATUS, L.PARENT_LPN_ID as PALLET, INV.ON_HAND AS PLT_QTY, INV.ALLOCATED AS PLT_ALLOCATED_QTY ,INV.TO_BE_FILLED AS PLT_TBF, INV.LOCATION_ID AS PLT_LOCATION, L.ILPN_ID AS CHILD_LPN , INV.ITEM_ID from default_dcinventory.DCI_INVENTORY INV LEFT JOIN default_dcinventory.DCI_ILPN L ON L.PARENT_LPN_ID = INV.ILPN_ID AND L.ORG_ID = INV.ORG_ID where L.PARENT_LPN_ID IN (SELECT ILPN_ID FROM default_dcinventory.DCI_INVENTORY) and L.PARENT_LPN_ID IN (SELECT ILPN_ID FROM default_dcinventory.DCI_ILPN where status not in ('9000','11000') );" connection="MAPRD_NEW"
A6: AUB - MISSING WM_INVENTORY RECORD | D6: AUB - MISSING WM_INVENTORY RECORD | F6: DB Query | H6: Oracle/OnPrem | I6: In Design | J6: dbxquery query="SELECT PLD.PICK_LOCN_DTL_ID, LH.DSP_LOCN, IC.ITEM_NAME, PLD.INVN_TYPE FROM WMSAUB.PICK_LOCN_DTL PLD LEFT JOIN WMSAUB.LOCN_HDR LH ON LH.LOCN_ID = PLD.LOCN_ID LEFT JOIN WMSAUB.ITEM_CBO IC ON IC.ITEM_ID = PLD.ITEM_ID LEFT JOIN WMSAUB.WM_INVENTORY WI ON WI.LOCATION_ID = PLD.LOCN_ID AND WI.ITEM_ID = PLD.ITEM_ID AND WI.INVENTORY_TYPE = PLD.INVN_TYPE WHERE WI.WM_INVENTORY_ID IS NULL AND PLD.LAST_WAVE_NBR NOT IN ( SELECT MAX(SHIP_WAVE_NBR) FROM WMSAUB.SHIP_WAVE_PARM ) " connection="YMC_PROD"
A7: DEN - MAWM - Inventory Adjustment PIX Missing Reason Code | D7: DEN - MAWM - Inventory Adjustment PIX Missing Reason Code | F7: DB Query | H7: MySQL/Cloud | I7: In Design | J7: dbxquery query="SELECT PE.ORG_ID, PE.CREATED_TIMESTAMP, PE.ITEM_ID, CASE WHEN PE.ADJUSTED_TYPE = 'SUBTRACT' THEN -PE.QUANTITY WHEN PE.ADJUSTED_TYPE = 'ADD' THEN PE.QUANTITY END AS QUANTITY , PE.REASON_CODE_ID ,PE.SYNC_BATCH_ID, PE.PIX_SPECIFICATION_ID, CONCAT(PE.STATUS_ID,'-',PS.DESCRIPTION) STATUS, PE.CREATED_BY FROM default_pix.PIX_PIX_ENTRY PE LEFT JOIN default_pix.PIX_PIX_STATUS PS ON PS.STATUS_ID = PE.STATUS_ID WHERE PE.PIX_SPECIFICATION_ID = 'Inventory Adjustment' AND PE.CREATED_TIMESTAMP between NOW() + INTERVAL 15 minute and now() + interval 1455 minute AND REASON_CODE_ID IS NULL AND PE.ORG_ID = 'DEN'" connection="MAPRD_NEW" | rename ORG_ID as "Org ID", CREATED_TIMESTAMP as "Created Timestamp", ITEM_ID as "Item ID", QUANTITY as "Quantity", REASON_CODE_ID as "Reason Code ID", SYNC_BATCH_ID as "Sync Batch ID", PIX_SPECIFICATION_ID as "PIX Specification ID", STATUS AS "Status", CREATED_BY as "Created By" | table "Org ID", "Created Timestamp", "Item ID", "Quantity", "Reason Code ID", "Sync Batch ID", "PIX Specification ID", "Status", "Created By"
A8: DEN - MAWM - Locations w/ Inventory for Items not Assigned | D8: DEN - MAWM - Locations w/ Inventory for Items not Assigned | F8: DB Query | H8: MySQL/OnPrem | I8: In Design | J8: dbxquery query="select INVN.ORG_ID, INVN.LOCATION_ID, LOC.PICK_ALLOCATION_ZONE_ID,COUNT(DISTINCT(INVN.ITEM_ID)) ITEMS, (case when INVN.LOCATION_ID IN (SELECT INVN_2.LOCATION_ID FROM default_dcinventory.DCI_INVENTORY INVN_2 WHERE INVN.LOCATION_ID = INVN_2.LOCATION_ID AND INVN.ORG_ID = INVN_2.ORG_ID AND INVN_2.TO_BE_FILLED > 0) THEN 'TBF' ELSE null END) TBF, (case when INVN.LOCATION_ID IN (SELECT INVN_2.LOCATION_ID FROM default_dcinventory.DCI_INVENTORY INVN_2 WHERE INVN.LOCATION_ID = INVN_2.LOCATION_ID AND INVN.ORG_ID = INVN_2.ORG_ID AND INVN_2.ALLOCATED > 0) THEN 'TBP' ELSE null END) TBP from default_dcinventory.DCI_INVENTORY INVN left join default_dcinventory.DCI_LOCATION LOC on LOC.LOCATION_ID = INVN.LOCATION_ID AND INVN.ORG_ID = SUBSTR(LOC.PROFILE_ID,1,3) left join default_dcinventory.DCI_ILPN ILPN ON ILPN.ORG_ID = INVN.ORG_ID AND ILPN.ILPN_ID = INVN.ILPN_ID where (LOC.STORAGE_UOM_ID = 'LPN' AND LOC.MAX_ITEMS = 1 AND LOC.LOCATION_TYPE_ID = 'STORAGE' AND LOC.PICK_ALLOCATION_ZONE_ID IS NOT NULL) and INVN.ITEM_ID NOT IN (select ASSIGN.Item_id from default_dcinventory.DCI_LOCATION_ITEM_ASSIGNMENT ASSIGN WHERE ASSIGN.LOCATION_ID = INVN.LOCATION_ID AND INVN.ORG_ID = ASSIGN.ORG_ID) and INVN.LOCATION_ID NOT IN ('SLOT01','RETURN','DEFECT') AND LOC.PROFILE_ID = 'DEN_Fac_Prof' AND ILPN.SINGLE_ITEM_LPN = '1' GROUP BY INVN.ORG_ID, INVN.LOCATION_ID, LOC.PICK_ALLOCATION_ZONE_ID HAVING COUNT(DISTINCT(INVN.ITEM_ID)) > 0 Order by INVN.LOCATION_ID" connection="MAPRD_NEW" |rename ITEMS as Items, LOCATION_ID as "Location ID", PICK_ALLOCATION_ZONE_ID as "Pick Allocation Zone ID", TBF as "To Be Filled", TBP as "To Be Picked" |table Item, "Location ID", "Pick Allocation Zone ID", "To Be Filled", "To Be Picked"
A9: DEN - MAWM - Temporary Reserve Locations w/ Assignments, but no Inventory | D9: DEN - MAWM - Temporary Reserve Locations w/ Assignments, but no Inventory | F9: DB Query | H9: MySQL/Cloud | I9: In Design | J9: dbxquery query="SELECT ASSIGN.ORG_ID, ASSIGN.LOCATION_ID, ASSIGN.ITEM_ID, ASSIGN.ASSIGNMENT_ID FROM default_dcinventory.DCI_LOCATION_ITEM_ASSIGNMENT ASSIGN LEFT JOIN default_dcinventory.DCI_LOCATION LOC ON LOC.LOCATION_ID = ASSIGN.LOCATION_ID AND SUBSTR(LOC.PROFILE_ID,1,3) = ASSIGN.ORG_ID WHERE ASSIGN.LOCATION_ID NOT IN ( SELECT DISTINCT INVN1.LOCATION_ID FROM default_dcinventory.DCI_INVENTORY INVN1 WHERE INVN1.LOCATION_ID IS NOT NULL ) AND ASSIGN.LOCATION_ID NOT IN ( SELECT DISTINCT INVN2.INVENTORY_CONTAINER_ID FROM default_dcinventory.DCI_INVENTORY INVN2 WHERE INVN2.INVENTORY_CONTAINER_TYPE_ID = 'LOCATION' ) AND LOC.STORAGE_UOM_ID = 'LPN' AND LOC.SKU_DEDICATION_TYPE_ID = 'TEMPORARY' AND LOC.LOCATION_TYPE_ID = 'STORAGE' AND ASSIGN.ORG_ID = 'DEN'" connection="MAPRD_NEW" | rename ORG_ID AS "Org ID", ASSIGNMENT_ID AS "Assignment ID", ITEM_ID AS "Item ID", "LOCATION_ID" AS "Location ID" | table "Org ID", "Assignment ID", "Item ID", "Location ID"
A10: DEN - MAWM - Temporary Reserve Locations w/ Inventory, but no Assignments | D10: DEN - MAWM - Temporary Reserve Locations w/ Inventory, but no Assignments | F10: DB Query | H10: MySQL/Cloud | I10: In Design | J10: dbxquery query="select DISTINCT INVN.ORG_ID, INVN.LOCATION_ID, COUNT(DISTINCT(INVN.ITEM_ID)) COUNT from default_dcinventory.DCI_INVENTORY INVN left join default_dcinventory.DCI_LOCATION LOC on LOC.LOCATION_ID = INVN.LOCATION_ID AND SUBSTR(LOC.PROFILE_ID,1,3) = INVN.ORG_ID where INVN.LOCATION_ID not in (select distinct ASSIGN.LOCATION_ID from default_dcinventory.DCI_LOCATION_ITEM_ASSIGNMENT ASSIGN where ASSIGN.ORG_ID = INVN.ORG_ID AND ASSIGN.ITEM_ID IS NOT NULL) AND LOC.STORAGE_UOM_ID = 'LPN' AND LOC.SKU_DEDICATION_TYPE_ID = 'TEMPORARY' AND LOC.LOCATION_TYPE_ID = 'STORAGE' AND LOC.PROFILE_ID = 'DEN_Fac_Prof' group by INVN.ORG_ID, INVN.LOCATION_ID ORDER BY COUNT(DISTINCT(INVN.ITEM_ID)) DESC" connection="MAPRD_NEW" |rename ORG_ID AS "Org ID", COUNT as Count, LOCATION_ID AS "Location ID" |table "Org ID", "Location ID", Count
A11: DEN - MAWM Active -Inventory Sync Schedule API Failed | D11: DEN - MAWM -Inventory Sync Schedule Failed | F11: File Check | H11: OnPrem | I11: In Design
A12: DEN - WM Active -Inventory Sync Schedule API Failed | D12: DEN - WM Active -Inventory Sync Schedule Failed | F12: File Check | H12: OnPrem | I12: In Design
A13: DFB - MAWM - Inventory Adjustment PIX Missing Reason Code | D13: DFB - MAWM - Inventory Adjustment PIX Missing Reason Code | F13: DB Query | H13: MySQL/Cloud | I13: In Design
A14: DFB - MAWM - Temporary Reserve Locations w/ Inventory, but no Assignments | D14: DFB - MAWM - Temporary Reserve Locations w/ Inventory, but no Assignments | F14: DB Query | H14: MySQL/Cloud | I14: In Design
A15: LAF - MAWM - Inventory Adjustment PIX Missing Reason Code | D15: LAF - MAWM - Inventory Adjustment PIX Missing Reason Code | F15: DB Query | H15: MySQL/Cloud | I15: In Design
A16: LAF - MAWM - Locations w/ Inventory for Items not Assigned | D16: LAF - MAWM - Locations w/ Inventory for Items not Assigned | F16: DB Query | H16: MySQL/OnPrem | I16: In Design
A17: LAF - MAWM -Inventory Sync Schedule API Failed | D17: LAF - WM Active -Inventory Sync Schedule Failed | F17: File Check | H17: OnPrem | I17: In Design
A18: LAF - WM Active -Inventory Sync Schedule API Failed | D18: LAF - WM Active -Inventory Sync Schedule Failed | F18: File Check | H18: OnPrem | I18: In Design
A19: LUB - MAWM - Inventory Adjustment PIX Missing Reason Code | D19: LUB - MAWM - Inventory Adjustment PIX Missing Reason Code | F19: DB Query | H19: MySQL/Cloud | I19: In Design
A20: LUB - MAWM - Locations w/ Inventory for Items not Assigned | D20: LUB - MAWM - Locations w/ Inventory for Items not Assigned | F20: DB Query | H20: MySQL/Cloud | I20: In Design
A21: LUB - MAWM - Temporary Reserve Locations w/ Assignments, but no Inventory | D21: LUB - MAWM - Temporary Reserve Locations w/ Assignments, but no Inventory | F21: DB Query | H21: MySQL/Cloud | I21: In Design
A22: LUB - MAWM - Temporary Reserve Locations w/ Inventory, but no Assignments | D22: LUB - MAWM - Temporary Reserve Locations w/ Inventory, but no Assignments | F22: DB Query | H22: MySQL/Cloud | I22: In Design
A23: MGH - MISSING WM_INVENTORY RECORD | D23: MGH - MISSING WM_INVENTORY RECORD | F23: DB Query | H23: Disabled | I23: In Design
A24: Manhattan Active NEW - Locations with item assignments but 0 inventory | F24: DB Query | H24: Disabled | I24: In Design
A25: NEW - MAWM -Inventory Sync Schedule API Failed | D25: NEW - WM Active -Inventory Sync Schedule Failed | F25: File Check | H25: OnPrem | I25: In Design
A26: NEW - WM Active -Inventory Sync Schedule API Failed | D26: NEW - WM Active -Inventory Sync Schedule Failed | F26: File Check | H26: OnPrem | I26: In Design
A27: WMS - ASH Aged Inventory | F27: DB Query | H27: Disabled | I27: In Design
A28: WMS - Aged Inventory | F28: DB Query | H28: Disabled | I28: In Design
A29: WMS - CORP Aged Inventory | F29: DB Query | H29: Oracle/OnPrem | I29: In Design
A30: WMS - InventorySync failed due to WMS factory | D30: Check source log for Warehouse | F30: Log Check | H30: OnPrem | I30: In Design
A31: WMS â€“ RNDC WEST MGH - Orders with Null Inventory Type | F31: DB Query | H31: Disabled | I31: In Design
A32: WMS â€“ RNDC WEST AUB - Orders with Null Inventory Type | F32: DB Query | H32: Oracle/OnPrem | I32: In Design | J32: | dbxquery query="SELECT (SELECT DISTINCT whse FROM locn_hdr) whse, tc_order_id, do_Status, delivery_end_Dttm, created_dttm FROM orders WHERE order_id IN (SELECT order_id FROM order_line_item WHERE invn_type is null) AND do_status = '110' " connection="YMC_AUB_PROD"
A33: WMS â€“ RNDC WEST CHI- Orders with Null Inventory Type | F33: DB Query | H33: Disabled | I33: In Design
A34: WMS â€“ RNDC WEST POR - Orders with Null Inventory Type | F34: DB Query | H34: Oracle/OnPrem | I34: In Design
A35: YMC_QA - CHI - MISSING WM_INVENTORY RECORD | D35: CHI - MISSING WM_INVENTORY RECORD | F35: DB Query | H35: Disabled | I35: In Design
A36: ABQ - MAWM - Inventory Adjustment PIX Missing Reason Code | D36: ABQ - MAWM - Inventory Adjustment PIX Missing Reason Code | F36: DB Query | H36: MySQL/Cloud | I36: In Design
A37: ABQ - MAWM - Locations w/ Inventory for Items not Assigned | D37: ABQ - MAWM - Locations w/ Inventory for Items not Assigned | F37: DB Query | H37: MySQL/Cloud | I37: In Design
A38: ABQ - MAWM - Temporary Reserve Locations w/ Assignments, but no Inventory | D38: ABQ - MAWM - Temporary Reserve Locations w/ Assignments, but no Inventory | F38: DB Query | H38: MySQL/Cloud | I38: In Design
A39: ABQ - MAWM - Temporary Reserve Locations w/ Inventory, but no Assignments | D39: ABQ - MAWM - Temporary Reserve Locations w/ Inventory, but no Assignments | F39: DB Query | H39: MySQL/Cloud | I39: In Design
A40: ALL - MAWM - Multiple Inventory Records for the Same Location/Item | D40: ALL - MAWM - Multiple Inventory Records for the Same Location/Item | F40: DB Query | H40: MySQL/Cloud | I40: In Design
A41: ALL - MAWM - Cancelled oLPNs With Inventory Records | F41: DB Query | H41: MySQL/Cloud | I41: In Design
A42: ALL - MAWM - Inventory Adjustment PIX w/ Null PO Line | D42: ALL - MAWM - Inventory Adjustment PIX w/ Null PO Line | F42: DB Query | H42: Oracle/Cloud | I42: In Design
A43: ALL - MAWM - Shipped oLPN With Inventory Record | D43: ALL - MAWM - Shipped oLPN With Inventory Record | F43: DB Query | H43: MySQL/Cloud | I43: In Design
A44: ALL - MAWM â€“ Inventory Records with Pack Quantity Populated | D44: ALL - MAWM â€“ Inventory Records with Pack Quantity Populated | F44: DB Query | H44: MySQL/Cloud | I44: In Design
A45: ALL MAWM - Inventory Adjustments Missing Reason Code | D45: MAWM - Inventory Adjustments Missing Reason Code | F45: DB Query | H45: MySQL/Cloud | I45: In Design
A46: ASH - MAWM - Inventory Adjustment PIX Missing Reason Code | D46: ASH - MAWM - Inventory Adjustment PIX Missing Reason Code | F46: DB Query | H46: MySQL/Cloud | I46: In Design
A47: ASH - MAWM - Locations w/ Inventory for Items not Assigned | D47: ASH - MAWM - Locations w/ Inventory for Items not Assigned | F47: DB Query | H47: MySQL/Cloud | I47: In Design
A48: ASH - MAWM - Temporary Reserve Locations w/ Assignments, but no Inventory | D48: ASH - MAWM - Temporary Reserve Locations w/ Assignments, but no Inventory | F48: DB Query | H48: MySQL/Cloud | I48: In Design
A49: ASH - MAWM - Temporary Reserve Locations w/ Inventory, but no Assignments | D49: ASH - MAWM - Temporary Reserve Locations w/ Inventory, but no Assignments | F49: DB Query | H49: MySQL/Cloud | I49: In Design
A50: ATL - MAWM - Inventory Adjustment PIX Missing Reason Code | D50: ATL - MAWM - Inventory Adjustment PIX Missing Reason Code | F50: DB Query | H50: MySQL/Cloud | I50: In Design
